Workbook
Name Срез_Стратегия: #N/A

Sheet Настройки
A1: НАСТРОЙКИ ПРОЕКТА | H1: А-акции | L1: Стратегия | M1: Вес акций | N1: Вес облигаций
A2: сумма вложений | B2: 115000 | H2: О-облигации | L2: Акции 100% | M2: 1 | N2: 0
A3: регулярность | B3: раз в месяц | L3: Облигации 100% | M3: 0 | N3: 1
A4: год начала | B4: 2004 | L4: Вклады 100% | M4: 0 | N4: 0
A5: год окончания | B5: 2024 | L5: А50%/О50% | M5: 0.5 | N5: 0.5
A6: индексировать на инфляцию? | B6: Да | L6: А10%/О90% | M6: 0.1 | N6: 0.9
A7: Стратегии для расчета | B7: Акции 100% | L7: А20%/О80% | M7: 0.2 | N7: 0.8
A8: Разовые пополнения | B8: Год | C8: Разовый взнос | L8: А30%/О70 | M8: 0.3 | N8: 0.7
B9: 2004 | C9: 0 | L9: А40%/О60% | M9: 0.4 | N9: 0.6
B10: 2005 | C10: 0 | L10: А60%/О40% | M10: 0.6 | N10: 0.4
B11: 2006 | C11: 0 | L11: А70%/О30% | M11: 0.7 | N11: 0.3
B12: 2007 | C12: 0 | L12: А80%/О20% | M12: 0.8 | N12: 0.2
B13: 2008 | C13: 0 | L13: А90%/О10% | M13: 0.9 | N13: 0.1
B14: 2009 | C14: 0
B15: 2010 | C15: 0
B16: 2011 | C16: 0
B17: 2012 | C17: 0
B18: 2013 | C18: 0
B19: 2014 | C19: 0
B20: 2015 | C20: 0
B21: 2016 | C21: 0
B22: 2017 | C22: 0
B23: 2018 | C23: 0
B24: 2019 | C24: 0
B25: 2020 | C25: 0
... B29: 2024 | C29: 0

Sheet Сырые данные
A1: Сырые Данные
A2: Тут хранятся исходные значения индексов Мосбиржи и расчёт годовой доходности.
A4: Год | B4: MCFTR значение | C4: Доходность акций | D4: RGBITR значение | E4: Доходность облигаций
A5: 2003 | B5: 514.71 | C5: нет исходной базы для расчёта | D5: 127.73 | E5: Нет исходной базы для расчета
A6: 2004 | B6: 552.22 | C6: =B6/B5-1 -> 0.072875988 | D6: 141.64 | E6: =D6/D5-1 -> 0.10890159
A7: 2005 | B7: 1020.91 | C7: =B7/B6-1 -> 0.84873782 | D7: 158.13 | E7: =D7/D6-1 -> 0.11642191
A8: 2006 | B8: 1733.52 | C8: =B8/B7-1 -> 0.69801452 | D8: 168.99 | E8: =D8/D7-1 -> 0.06867767
A9: 2007 | B9: 1952.83 | C9: =B9/B8-1 -> 0.12651138 | D9: 181.5 | E9: =D9/D8-1 -> 0.074028049
A10: 2008 | B10: 652.08 | C10: =B10/B9-1 -> -0.66608461 | D10: 171.42 | E10: =D10/D9-1 -> -0.05553719
A11: 2009 | B11: 1474.41 | C11: =B11/B10-1 -> 1.2610876 | D11: 231.98 | E11: =D11/D10-1 -> 0.35328433
A12: 2010 | B12: 1847.21 | C12: =B12/B11-1 -> 0.2528469 | D12: 257.84 | E12: =D12/D11-1 -> 0.11147513
A13: 2011 | B13: 1580.19 | C13: =B13/B12-1 -> -0.14455314 | D13: 272.78 | E13: =D13/D12-1 -> 0.05794291
A14: 2012 | B14: 1718.76 | C14: =B14/B13-1 -> 0.087691986 | D14: 312.73 | E14: =D14/D13-1 -> 0.14645502
A15: 2013 | B15: 1827.3 | C15: =B15/B14-1 -> 0.063150178 | D15: 324.62 | E15: =D15/D14-1 -> 0.038020017
A16: 2014 | B16: 1793.6 | C16: =B16/B15-1 -> -0.018442511 | D16: 278.02 | E16: =D16/D15-1 -> -0.14355246
A17: 2015 | B17: 2372.49 | C17: =B17/B16-1 -> 0.32275312 | D17: 360.19 | E17: =D17/D16-1 -> 0.29555428
... A26: 2024 | B26: 7112.22 | C26: =B26/B25-1 -> 0.016368282 | D26: 563.02 | E26: =D26/D25-1 -> -0.086555154

Sheet Исходные данные
A1: ИСХОДНЫЕ ДАННЫЕ
A3: Год | B3: Акции(MCFTR) | C3: Облигации(RGBITR) | D3: Вклады | E3: Инфляция (ИЦП) | F3: Кумулятивная инфляция | G3: Взнос с индексацией | H3: Разовый взнос | I3: Итоговый взнос
A4: 2004 | B4: =VLOOKUP(Данные[[#This Row],[Год]],'Сырые данные'!$A$5:$E$26,3,TRUE) -> 0.072875988 | C4: =VLOOKUP(Данные[[#This Row],[Год]],'Сырые данные'!$A$5:$E$26,5,0) -> 0.10890159 | D4: 0.102 | E4: 0.1174 | F4: =1+Данные[[#This Row],[Инфляция (ИЦП)]] -> 1.1174 | G4: =Настройки!$B$2 -> 115000 | H4: =IFERROR(VLOOKUP(A4,Таблица18[#All],2,FALSE),0) -> 0 | I4: =Данные[[#This Row],[Взнос с индексацией]]+Данные[[#This Row],[Разовый взнос]] -> 115000
A5: 2005 | B5: =VLOOKUP(Данные[[#This Row],[Год]],'Сырые данные'!$A$5:$E$26,3,TRUE) -> 0.84873782 | C5: =VLOOKUP(Данные[[#This Row],[Год]],'Сырые данные'!$A$5:$E$26,5,0) -> 0.11642191 | D5: 0.084 | E5: 0.1091 | F5: =F4 * (1 + E5) -> 1.2393083 | G5: =IF(Настройки!$B$6="да",'Исходные данные'!G4*(1+'Исходные данные'!E4),Настройки!$B$2) -> 128501 | H5: =IFERROR(VLOOKUP(A5,Таблица18[#All],2,FALSE),0) -> 0 | I5: =Данные[[#This Row],[Взнос с индексацией]]+Данные[[#This Row],[Разовый взнос]] -> 128501
A6: 2006 | B6: =VLOOKUP(Данные[[#This Row],[Год]],'Сырые данные'!$A$5:$E$26,3,TRUE) -> 0.69801452 | C6: =VLOOKUP(Данные[[#This Row],[Год]],'Сырые данные'!$A$5:$E$26,5,0) -> 0.06867767 | D6: 0.089 | E6: 0.09 | F6: =F5 * (1 + E6) -> 1.3508461 | G6: =IF(Настройки!$B$6="да",'Исходные данные'!G5*(1+'Исходные данные'!E5),Настройки!$B$2) -> 142520.46 | H6: =IFERROR(VLOOKUP(A6,Таблица18[#All],2,FALSE),0) -> 0 | I6: =Данные[[#This Row],[Взнос с индексацией]]+Данные[[#This Row],[Разовый взнос]] -> 142520.46
A7: 2007 | B7: =VLOOKUP(Данные[[#This Row],[Год]],'Сырые данные'!$A$5:$E$26,3,TRUE) -> 0.12651138 | C7: =VLOOKUP(Данные[[#This Row],[Год]],'Сырые данные'!$A$5:$E$26,5,0) -> 0.074028049 | D7: 0.08 | E7: 0.1187 | F7: =F6 * (1 + E7) -> 1.5111915 | G7: =IF(Настройки!$B$6="да",'Исходные данные'!G6*(1+'Исходные данные'!E6),Настройки!$B$2) -> 155347.3 | H7: =IFERROR(VLOOKUP(A7,Таблица18[#All],2,FALSE),0) -> 0 | I7: =Данные[[#This Row],[Взнос с индексацией]]+Данные[[#This Row],[Разовый взнос]] -> 155347.3
A8: 2008 | B8: =VLOOKUP(Данные[[#This Row],[Год]],'Сырые данные'!$A$5:$E$26,3,TRUE) -> -0.66608461 | C8: =VLOOKUP(Данные[[#This Row],[Год]],'Сырые данные'!$A$5:$E$26,5,0) -> -0.05553719 | D8: 0.112 | E8: 0.1328 | F8: =F7 * (1 + E8) -> 1.7118778 | G8: =IF(Настройки!$B$6="да",'Исходные данные'!G7*(1+'Исходные данные'!E7),Настройки!$B$2) -> 173787.02 | H8: =IFERROR(VLOOKUP(A8,Таблица18[#All],2,FALSE),0) -> 0 | I8: =Данные[[#This Row],[Взнос с индексацией]]+Данные[[#This Row],[Разовый взнос]] -> 173787.02
A9: 2009 | B9: =VLOOKUP(Данные[[#This Row],[Год]],'Сырые данные'!$A$5:$E$26,3,TRUE) -> 1.2610876 | C9: =VLOOKUP(Данные[[#This Row],[Год]],'Сырые данные'!$A$5:$E$26,5,0) -> 0.35328433 | D9: 0.112 | E9: 0.088 | F9: =F8 * (1 + E9) -> 1.862523 | G9: =IF(Настройки!$B$6="да",'Исходные данные'!G8*(1+'Исходные данные'!E8),Настройки!$B$2) -> 196865.94 | H9: =IFERROR(VLOOKUP(A9,Таблица18[#All],2,FALSE),0) -> 0 | I9: =Данные[[#This Row],[Взнос с индексацией]]+Данные[[#This Row],[Разовый взнос]] -> 196865.94
A10: 2010 | B10: =VLOOKUP(Данные[[#This Row],[Год]],'Сырые данные'!$A$5:$E$26,3,TRUE) -> 0.2528469 | C10: =VLOOKUP(Данные[[#This Row],[Год]],'Сырые данные'!$A$5:$E$26,5,0) -> 0.11147513 | D10: 0.068 | E10: 0.0878 | F10: =F9 * (1 + E10) -> 2.0260525 | G10: =IF(Настройки!$B$6="да",'Исходные данные'!G9*(1+'Исходные данные'!E9),Настройки!$B$2) -> 214190.14 | H10: =IFERROR(VLOOKUP(A10,Таблица18[#All],2,FALSE),0) -> 0 | I10: =Данные[[#This Row],[Взнос с индексацией]]+Данные[[#This Row],[Разовый взнос]] -> 214190.14
A11: 2011 | B11: =VLOOKUP(Данные[[#This Row],[Год]],'Сырые данные'!$A$5:$E$26,3,TRUE) -> -0.14455314 | C11: =VLOOKUP(Данные[[#This Row],[Год]],'Сырые данные'!$A$5:$E$26,5,0) -> 0.05794291 | D11: 0.078 | E11: 0.061 | F11: =F10 * (1 + E11) -> 2.1496417 | G11: =IF(Настройки!$B$6="да",'Исходные данные'!G10*(1+'Исходные данные'!E10),Настройки!$B$2) -> 232996.04 | H11: =IFERROR(VLOOKUP(A11,Таблица18[#All],2,FALSE),0) -> 0 | I11: =Данные[[#This Row],[Взнос с индексацией]]+Данные[[#This Row],[Разовый взнос]] -> 232996.04
A12: 2012 | B12: =VLOOKUP(Данные[[#This Row],[Год]],'Сырые данные'!$A$5:$E$26,3,TRUE) -> 0.087691986 | C12: =VLOOKUP(Данные[[#This Row],[Год]],'Сырые данные'!$A$5:$E$26,5,0) -> 0.14645502 | D12: 0.084 | E12: 0.0658 | F12: =F11 * (1 + E12) -> 2.2910881 | G12: =IF(Настройки!$B$6="да",'Исходные данные'!G11*(1+'Исходные данные'!E11),Настройки!$B$2) -> 247208.8 | H12: =IFERROR(VLOOKUP(A12,Таблица18[#All],2,FALSE),0) -> 0 | I12: =Данные[[#This Row],[Взнос с индексацией]]+Данные[[#This Row],[Разовый взнос]] -> 247208.8
A13: 2013 | B13: =VLOOKUP(Данные[[#This Row],[Год]],'Сырые данные'!$A$5:$E$26,3,TRUE) -> 0.063150178 | C13: =VLOOKUP(Данные[[#This Row],[Год]],'Сырые данные'!$A$5:$E$26,5,0) -> 0.038020017 | D13: 0.074 | E13: 0.0645 | F13: =F12 * (1 + E13) -> 2.4388633 | G13: =IF(Настройки!$B$6="да",'Исходные данные'!G12*(1+'Исходные данные'!E12),Настройки!$B$2) -> 263475.14 | H13: =IFERROR(VLOOKUP(A13,Таблица18[#All],2,FALSE),0) -> 0 | I13: =Данные[[#This Row],[Взнос с индексацией]]+Данные[[#This Row],[Разовый взнос]] -> 263475.14
A14: 2014 | B14: =VLOOKUP(Данные[[#This Row],[Год]],'Сырые данные'!$A$5:$E$26,3,TRUE) -> -0.018442511 | C14: =VLOOKUP(Данные[[#This Row],[Год]],'Сырые данные'!$A$5:$E$26,5,0) -> -0.14355246 | D14: 0.081 | E14: 0.1136 | F14: =F13 * (1 + E14) -> 2.7159182 | G14: =IF(Настройки!$B$6="да",'Исходные данные'!G13*(1+'Исходные данные'!E13),Настройки!$B$2) -> 280469.28 | H14: =IFERROR(VLOOKUP(A14,Таблица18[#All],2,FALSE),0) -> 0 | I14: =Данные[[#This Row],[Взнос с индексацией]]+Данные[[#This Row],[Разовый взнос]] -> 280469.28
A15: 2015 | B15: =VLOOKUP(Данные[[#This Row],[Год]],'Сырые данные'!$A$5:$E$26,3,TRUE) -> 0.32275312 | C15: =VLOOKUP(Данные[[#This Row],[Год]],'Сырые данные'!$A$5:$E$26,5,0) -> 0.29555428 | D15: 0.101 | E15: 0.1291 | F15: =F14 * (1 + E15) -> 3.0665432 | G15: =IF(Настройки!$B$6="да",'Исходные данные'!G14*(1+'Исходные данные'!E14),Настройки!$B$2) -> 312330.59 | H15: =IFERROR(VLOOKUP(A15,Таблица18[#All],2,FALSE),0) -> 0 | I15: =Данные[[#This Row],[Взнос с индексацией]]+Данные[[#This Row],[Разовый взнос]] -> 312330.59
A16: 2016 | B16: =VLOOKUP(Данные[[#This Row],[Год]],'Сырые данные'!$A$5:$E$26,3,TRUE) -> 0.32780328 | C16: =VLOOKUP(Данные[[#This Row],[Год]],'Сырые данные'!$A$5:$E$26,5,0) -> 0.14878259 | D16: 0.084 | E16: 0.0538 | F16: =F15 * (1 + E16) -> 3.2315233 | G16: =IF(Настройки!$B$6="да",'Исходные данные'!G15*(1+'Исходные данные'!E15),Настройки!$B$2) -> 352652.47 | H16: =IFERROR(VLOOKUP(A16,Таблица18[#All],2,FALSE),0) -> 0 | I16: =Данные[[#This Row],[Взнос с индексацией]]+Данные[[#This Row],[Разовый взнос]] -> 352652.47
... A24: 2024 | B24: =VLOOKUP(Данные[[#This Row],[Год]],'Сырые данные'!$A$5:$E$26,3,TRUE) -> 0.016368282 | C24: =VLOOKUP(Данные[[#This Row],[Год]],'Сырые данные'!$A$5:$E$26,5,0) -> -0.086555154 | D24: 0.153 | E24: 0.0952 | F24: =F23 * (1 + E24) -> 5.3308105 | G24: =IF(Настройки!$B$6="да",'Исходные данные'!G23*(1+'Исходные данные'!E23),Настройки!$B$2) -> 559754.57 | H24: =IFERROR(VLOOKUP(A24,Таблица18[#All],2,FALSE),0) -> 0 | I24: =Данные[[#This Row],[Взнос с индексацией]]+Данные[[#This Row],[Разовый взнос]] -> 559754.57

Sheet Калькулятор стратегий
A1: DCA
A2: Каждый период покупаем активы на фиксированную сумму. Чтобы в дальнейшем посчитать итоговую стоимость портфеля
A3: Год | B3: Взнос | C3: Доля Акций | D3: Доля Облигаций | E3: Доходность стратегии за год | F3: Портфель на НАЧАЛО года | G3: Доход | H3: Итоговый портфель, ₽ | I3: Вложено всего, ₽ | J3: Номинальная доходность | K3: Реальная доходность, % | L3: Среднегодовой рост
A4: 2004 | B4: =IF(AND(Таблица5[[#This Row],[Год]]>=Настройки!$B$4, Таблица5[[#This Row],[Год]]<=Настройки!$B$5), IFERROR(VLOOKUP(Таблица5[[#This Row],[Год]],Данные[#All],9,FALSE),0), 0) -> 115000 | C4: =VLOOKUP(Настройки!$B$7,Настройки!$L$1:$N$14,2,FALSE) -> 1 | D4: =VLOOKUP(Настройки!$B$7,Настройки!$L$1:$N$14,3,FALSE) -> 0 | E4: =C4*VLOOKUP(A4,Данные[#All],2,FALSE)+'Калькулятор стратегий'!D4*VLOOKUP(A4,Данные[#All],3,FALSE)+(1-C4-D4)*VLOOKUP(A4,Данные[#All],4,FALSE) -> 0.072875988 | F4: 0 | G4: =(F4+B4)*E4 -> 8380.7387 | H4: =F4+B4+G4 -> 123380.74 | I4: =SUM($B$4:B4) -> 115000 | J4: =IFERROR((H4-I4)/I4,"") -> 0.072875988 | K4: =IFERROR((1+J4)/(VLOOKUP(A4,Данные[#All],6,FALSE))-1,"") -> -0.039846082 | L4: =IFERROR((H4/I4)^((1/(A4-$A$4+1)))-1,"") -> 0.072875988
A5: 2005 | B5: =IF(AND(Таблица5[[#This Row],[Год]]>=Настройки!$B$4, Таблица5[[#This Row],[Год]]<=Настройки!$B$5), IFERROR(VLOOKUP(Таблица5[[#This Row],[Год]],Данные[#All],9,FALSE),0), 0) -> 128501 | C5: =VLOOKUP(Настройки!$B$7,Настройки!$L$1:$N$14,2,FALSE) -> 1 | D5: =VLOOKUP(Настройки!$B$7,Настройки!$L$1:$N$14,3,FALSE) -> 0 | E5: =C5*VLOOKUP(A5,Данные[#All],2,FALSE)+'Калькулятор стратегий'!D5*VLOOKUP(A5,Данные[#All],3,FALSE)+(1-C5-D5)*VLOOKUP(A5,Данные[#All],4,FALSE) -> 0.84873782 | F5: =H4 -> 123380.74 | G5: =(F5+B5)*E5 -> 213781.56 | H5: =F5+B5+G5 -> 465663.3 | I5: =SUM($B$4:B5) -> 243501 | J5: =IFERROR((H5-I5)/I5,"") -> 0.91236708 | K5: =IFERROR((1+J5)/(VLOOKUP(A5,Данные[#All],6,FALSE))-1,"") -> 0.54309224 | L5: =IFERROR((H5/I5)^((1/(A5-$A$4+1)))-1,"") -> 0.38288361
A6: 2006 | B6: =IF(AND(Таблица5[[#This Row],[Год]]>=Настройки!$B$4, Таблица5[[#This Row],[Год]]<=Настройки!$B$5), IFERROR(VLOOKUP(Таблица5[[#This Row],[Год]],Данные[#All],9,FALSE),0), 0) -> 142520.46 | C6: =VLOOKUP(Настройки!$B$7,Настройки!$L$1:$N$14,2,FALSE) -> 1 | D6: =VLOOKUP(Настройки!$B$7,Настройки!$L$1:$N$14,3,FALSE) -> 0 | E6: =C6*VLOOKUP(A6,Данные[#All],2,FALSE)+'Калькулятор стратегий'!D6*VLOOKUP(A6,Данные[#All],3,FALSE)+(1-C6-D6)*VLOOKUP(A6,Данные[#All],4,FALSE) -> 0.69801452 | F6: =H5 -> 465663.3 | G6: =(F6+B6)*E6 -> 424521.09 | H6: =F6+B6+G6 -> 1032704.8 | I6: =SUM($B$4:B6) -> 386021.46 | J6: =IFERROR((H6-I6)/I6,"") -> 1.6752524 | K6: =IFERROR((1+J6)/(VLOOKUP(A6,Данные[#All],6,FALSE))-1,"") -> 0.98042727 | L6: =IFERROR((H6/I6)^((1/(A6-$A$4+1)))-1,"") -> 0.38820921
A7: 2007 | B7: =IF(AND(Таблица5[[#This Row],[Год]]>=Настройки!$B$4, Таблица5[[#This Row],[Год]]<=Настройки!$B$5), IFERROR(VLOOKUP(Таблица5[[#This Row],[Год]],Данные[#All],9,FALSE),0), 0) -> 155347.3 | C7: =VLOOKUP(Настройки!$B$7,Настройки!$L$1:$N$14,2,FALSE) -> 1 | D7: =VLOOKUP(Настройки!$B$7,Настройки!$L$1:$N$14,3,FALSE) -> 0 | E7: =C7*VLOOKUP(A7,Данные[#All],2,FALSE)+'Калькулятор стратегий'!D7*VLOOKUP(A7,Данные[#All],3,FALSE)+(1-C7-D7)*VLOOKUP(A7,Данные[#All],4,FALSE) -> 0.12651138 | F7: =H6 -> 1032704.8 | G7: =(F7+B7)*E7 -> 150302.11 | H7: =F7+B7+G7 -> 1338354.3 | I7: =SUM($B$4:B7) -> 541368.76 | J7: =IFERROR((H7-I7)/I7,"") -> 1.4721675 | K7: =IFERROR((1+J7)/(VLOOKUP(A7,Данные[#All],6,FALSE))-1,"") -> 0.63590615 | L7: =IFERROR((H7/I7)^((1/(A7-$A$4+1)))-1,"") -> 0.25391897
A8: 2008 | B8: =IF(AND(Таблица5[[#This Row],[Год]]>=Настройки!$B$4, Таблица5[[#This Row],[Год]]<=Настройки!$B$5), IFERROR(VLOOKUP(Таблица5[[#This Row],[Год]],Данные[#All],9,FALSE),0), 0) -> 173787.02 | C8: =VLOOKUP(Настройки!$B$7,Настройки!$L$1:$N$14,2,FALSE) -> 1 | D8: =VLOOKUP(Настройки!$B$7,Настройки!$L$1:$N$14,3,FALSE) -> 0 | E8: =C8*VLOOKUP(A8,Данные[#All],2,FALSE)+'Калькулятор стратегий'!D8*VLOOKUP(A8,Данные[#All],3,FALSE)+(1-C8-D8)*VLOOKUP(A8,Данные[#All],4,FALSE) -> -0.66608461 | F8: =H7 -> 1338354.3 | G8: =(F8+B8)*E8 -> -1007214 | H8: =F8+B8+G8 -> 504927.25 | I8: =SUM($B$4:B8) -> 715155.78 | J8: =IFERROR((H8-I8)/I8,"") -> -0.29396187 | K8: =IFERROR((1+J8)/(VLOOKUP(A8,Данные[#All],6,FALSE))-1,"") -> -0.5875651 | L8: =IFERROR((H8/I8)^((1/(A8-$A$4+1)))-1,"") -> -0.067249198
A9: 2009 | B9: =IF(AND(Таблица5[[#This Row],[Год]]>=Настройки!$B$4, Таблица5[[#This Row],[Год]]<=Настройки!$B$5), IFERROR(VLOOKUP(Таблица5[[#This Row],[Год]],Данные[#All],9,FALSE),0), 0) -> 196865.94 | C9: =VLOOKUP(Настройки!$B$7,Настройки!$L$1:$N$14,2,FALSE) -> 1 | D9: =VLOOKUP(Настройки!$B$7,Настройки!$L$1:$N$14,3,FALSE) -> 0 | E9: =C9*VLOOKUP(A9,Данные[#All],2,FALSE)+'Калькулятор стратегий'!D9*VLOOKUP(A9,Данные[#All],3,FALSE)+(1-C9-D9)*VLOOKUP(A9,Данные[#All],4,FALSE) -> 1.2610876 | F9: =H8 -> 504927.25 | G9: =(F9+B9)*E9 -> 885022.69 | H9: =F9+B9+G9 -> 1586815.9 | I9: =SUM($B$4:B9) -> 912021.73 | J9: =IFERROR((H9-I9)/I9,"") -> 0.73988825 | K9: =IFERROR((1+J9)/(VLOOKUP(A9,Данные[#All],6,FALSE))-1,"") -> -0.065843345 | L9: =IFERROR((H9/I9)^((1/(A9-$A$4+1)))-1,"") -> 0.096697599
A10: 2010 | B10: =IF(AND(Таблица5[[#This Row],[Год]]>=Настройки!$B$4, Таблица5[[#This Row],[Год]]<=Настройки!$B$5), IFERROR(VLOOKUP(Таблица5[[#This Row],[Год]],Данные[#All],9,FALSE),0), 0) -> 214190.14 | C10: =VLOOKUP(Настройки!$B$7,Настройки!$L$1:$N$14,2,FALSE) -> 1 | D10: =VLOOKUP(Настройки!$B$7,Настройки!$L$1:$N$14,3,FALSE) -> 0 | E10: =C10*VLOOKUP(A10,Данные[#All],2,FALSE)+'Калькулятор стратегий'!D10*VLOOKUP(A10,Данные[#All],3,FALSE)+(1-C10-D10)*VLOOKUP(A10,Данные[#All],4,FALSE) -> 0.2528469 | F10: =H9 -> 1586815.9 | G10: =(F10+B10)*E10 -> 455378.8 | H10: =F10+B10+G10 -> 2256384.8 | I10: =SUM($B$4:B10) -> 1126211.9 | J10: =IFERROR((H10-I10)/I10,"") -> 1.0035172 | K10: =IFERROR((1+J10)/(VLOOKUP(A10,Данные[#All],6,FALSE))-1,"") -> -0.011122782 | L10: =IFERROR((H10/I10)^((1/(A10-$A$4+1)))-1,"") -> 0.10436668
A11: 2011 | B11: =IF(AND(Таблица5[[#This Row],[Год]]>=Настройки!$B$4, Таблица5[[#This Row],[Год]]<=Настройки!$B$5), IFERROR(VLOOKUP(Таблица5[[#This Row],[Год]],Данные[#All],9,FALSE),0), 0) -> 232996.04 | C11: =VLOOKUP(Настройки!$B$7,Настройки!$L$1:$N$14,2,FALSE) -> 1 | D11: =VLOOKUP(Настройки!$B$7,Настройки!$L$1:$N$14,3,FALSE) -> 0 | E11: =C11*VLOOKUP(A11,Данные[#All],2,FALSE)+'Калькулятор стратегий'!D11*VLOOKUP(A11,Данные[#All],3,FALSE)+(1-C11-D11)*VLOOKUP(A11,Данные[#All],4,FALSE) -> -0.14455314 | F11: =H10 -> 2256384.8 | G11: =(F11+B11)*E11 -> -359847.81 | H11: =F11+B11+G11 -> 2129533.1 | I11: =SUM($B$4:B11) -> 1359207.9 | J11: =IFERROR((H11-I11)/I11,"") -> 0.56674563 | K11: =IFERROR((1+J11)/(VLOOKUP(A11,Данные[#All],6,FALSE))-1,"") -> -0.27115965 | L11: =IFERROR((H11/I11)^((1/(A11-$A$4+1)))-1,"") -> 0.057729974
A12: 2012 | B12: =IF(AND(Таблица5[[#This Row],[Год]]>=Настройки!$B$4, Таблица5[[#This Row],[Год]]<=Настройки!$B$5), IFERROR(VLOOKUP(Таблица5[[#This Row],[Год]],Данные[#All],9,FALSE),0), 0) -> 247208.8 | C12: =VLOOKUP(Настройки!$B$7,Настройки!$L$1:$N$14,2,FALSE) -> 1 | D12: =VLOOKUP(Настройки!$B$7,Настройки!$L$1:$N$14,3,FALSE) -> 0 | E12: =C12*VLOOKUP(A12,Данные[#All],2,FALSE)+'Калькулятор стратегий'!D12*VLOOKUP(A12,Данные[#All],3,FALSE)+(1-C12-D12)*VLOOKUP(A12,Данные[#All],4,FALSE) -> 0.087691986 | F12: =H11 -> 2129533.1 | G12: =(F12+B12)*E12 -> 208421.21 | H12: =F12+B12+G12 -> 2585163.1 | I12: =SUM($B$4:B12) -> 1606416.7 | J12: =IFERROR((H12-I12)/I12,"") -> 0.60927302 | K12: =IFERROR((1+J12)/(VLOOKUP(A12,Данные[#All],6,FALSE))-1,"") -> -0.29759445 | L12: =IFERROR((H12/I12)^((1/(A12-$A$4+1)))-1,"") -> 0.054287018
A13: 2013 | B13: =IF(AND(Таблица5[[#This Row],[Год]]>=Настройки!$B$4, Таблица5[[#This Row],[Год]]<=Настройки!$B$5), IFERROR(VLOOKUP(Таблица5[[#This Row],[Год]],Данные[#All],9,FALSE),0), 0) -> 263475.14 | C13: =VLOOKUP(Настройки!$B$7,Настройки!$L$1:$N$14,2,FALSE) -> 1 | D13: =VLOOKUP(Настройки!$B$7,Настройки!$L$1:$N$14,3,FALSE) -> 0 | E13: =C13*VLOOKUP(A13,Данные[#All],2,FALSE)+'Калькулятор стратегий'!D13*VLOOKUP(A13,Данные[#All],3,FALSE)+(1-C13-D13)*VLOOKUP(A13,Данные[#All],4,FALSE) -> 0.063150178 | F13: =H12 -> 2585163.1 | G13: =(F13+B13)*E13 -> 179892.01 | H13: =F13+B13+G13 -> 3028530.2 | I13: =SUM($B$4:B13) -> 1869891.8 | J13: =IFERROR((H13-I13)/I13,"") -> 0.61962855 | K13: =IFERROR((1+J13)/(VLOOKUP(A13,Данные[#All],6,FALSE))-1,"") -> -0.33590844 | L13: =IFERROR((H13/I13)^((1/(A13-$A$4+1)))-1,"") -> 0.049401166
A14: 2014 | B14: =IF(AND(Таблица5[[#This Row],[Год]]>=Настройки!$B$4, Таблица5[[#This Row],[Год]]<=Настройки!$B$5), IFERROR(VLOOKUP(Таблица5[[#This Row],[Год]],Данные[#All],9,FALSE),0), 0) -> 280469.28 | C14: =VLOOKUP(Настройки!$B$7,Настройки!$L$1:$N$14,2,FALSE) -> 1 | D14: =VLOOKUP(Настройки!$B$7,Настройки!$L$1:$N$14,3,FALSE) -> 0 | E14: =C14*VLOOKUP(A14,Данные[#All],2,FALSE)+'Калькулятор стратегий'!D14*VLOOKUP(A14,Данные[#All],3,FALSE)+(1-C14-D14)*VLOOKUP(A14,Данные[#All],4,FALSE) -> -0.018442511 | F14: =H13 -> 3028530.2 | G14: =(F14+B14)*E14 -> -61026.259 | H14: =F14+B14+G14 -> 3247973.2 | I14: =SUM($B$4:B14) -> 2150361.1 | J14: =IFERROR((H14-I14)/I14,"") -> 0.51043152 | K14: =IFERROR((1+J14)/(VLOOKUP(A14,Данные[#All],6,FALSE))-1,"") -> -0.44385972 | L14: =IFERROR((H14/I14)^((1/(A14-$A$4+1)))-1,"") -> 0.038202124
A15: 2015 | B15: =IF(AND(Таблица5[[#This Row],[Год]]>=Настройки!$B$4, Таблица5[[#This Row],[Год]]<=Настройки!$B$5), IFERROR(VLOOKUP(Таблица5[[#This Row],[Год]],Данные[#All],9,FALSE),0), 0) -> 312330.59 | C15: =VLOOKUP(Настройки!$B$7,Настройки!$L$1:$N$14,2,FALSE) -> 1 | D15: =VLOOKUP(Настройки!$B$7,Настройки!$L$1:$N$14,3,FALSE) -> 0 | E15: =C15*VLOOKUP(A15,Данные[#All],2,FALSE)+'Калькулятор стратегий'!D15*VLOOKUP(A15,Данные[#All],3,FALSE)+(1-C15-D15)*VLOOKUP(A15,Данные[#All],4,FALSE) -> 0.32275312 | F15: =H14 -> 3247973.2 | G15: =(F15+B15)*E15 -> 1149099.2 | H15: =F15+B15+G15 -> 4709403 | I15: =SUM($B$4:B15) -> 2462691.7 | J15: =IFERROR((H15-I15)/I15,"") -> 0.91229904 | K15: =IFERROR((1+J15)/(VLOOKUP(A15,Данные[#All],6,FALSE))-1,"") -> -0.37639913 | L15: =IFERROR((H15/I15)^((1/(A15-$A$4+1)))-1,"") -> 0.055511535
A16: 2016 | B16: =IF(AND(Таблица5[[#This Row],[Год]]>=Настройки!$B$4, Таблица5[[#This Row],[Год]]<=Настройки!$B$5), IFERROR(VLOOKUP(Таблица5[[#This Row],[Год]],Данные[#All],9,FALSE),0), 0) -> 352652.47 | C16: =VLOOKUP(Настройки!$B$7,Настройки!$L$1:$N$14,2,FALSE) -> 1 | D16: =VLOOKUP(Настройки!$B$7,Настройки!$L$1:$N$14,3,FALSE) -> 0 | E16: =C16*VLOOKUP(A16,Данные[#All],2,FALSE)+'Калькулятор стратегий'!D16*VLOOKUP(A16,Данные[#All],3,FALSE)+(1-C16-D16)*VLOOKUP(A16,Данные[#All],4,FALSE) -> 0.32780328 | F16: =H15 -> 4709403 | G16: =(F16+B16)*E16 -> 1659358.4 | H16: =F16+B16+G16 -> 6721413.9 | I16: =SUM($B$4:B16) -> 2815344.2 | J16: =IFERROR((H16-I16)/I16,"") -> 1.3874217 | K16: =IFERROR((1+J16)/(VLOOKUP(A16,Данные[#All],6,FALSE))-1,"") -> -0.26120857 | L16: =IFERROR((H16/I16)^((1/(A16-$A$4+1)))-1,"") -> 0.069230829
... A24: 2024 | B24: =IF(AND(Таблица5[[#This Row],[Год]]>=Настройки!$B$4, Таблица5[[#This Row],[Год]]<=Настройки!$B$5), IFERROR(VLOOKUP(Таблица5[[#This Row],[Год]],Данные[#All],9,FALSE),0), 0) -> 559754.57 | C24: =VLOOKUP(Настройки!$B$7,Настройки!$L$1:$N$14,2,FALSE) -> 1 | D24: =VLOOKUP(Настройки!$B$7,Настройки!$L$1:$N$14,3,FALSE) -> 0 | E24: =C24*VLOOKUP(A24,Данные[#All],2,FALSE)+'Калькулятор стратегий'!D24*VLOOKUP(A24,Данные[#All],3,FALSE)+(1-C24-D24)*VLOOKUP(A24,Данные[#All],4,FALSE) -> 0.016368282 | F24: =H23 -> 19654735 | G24: =(F24+B24)*E24 -> 330876.47 | H24: =F24+B24+G24 -> 20545366 | I24: =SUM($B$4:B24) -> 6350420.1 | J24: =IFERROR((H24-I24)/I24,"") -> 2.2352767 | K24: =IFERROR((1+J24)/(VLOOKUP(A24,Данные[#All],6,FALSE))-1,"") -> -0.39309853 | L24: =IFERROR((H24/I24)^((1/(A24-$A$4+1)))-1,"") -> 0.057502729
A25: Итог

Sheet Расчёт всех стратегий
A1: Расчёт всех стратегий | Q1: Таблица для Дашбордов
A2: Тут находятся все стратегии уже с расчётом доходности. Этот лист нужен для таблиц и дашбордов | Q2: Год | R2: Акции 100% | S2: Облигации 100% | T2: А50%/О50% | U2: Вложено всего, ₽
Q3: 2004 | R3: =I6 -> 123380.74 | S3: =I30 -> 127523.68 | T3: =I78 -> 125452.21 | U3: =J6 -> 115000
Q4: 2005 | R4: =I7 -> 465663.3 | S4: =I31 -> 285831.57 | T4: =I79 -> 376505.92 | U4: =J7 -> 243501
A5: Стратегия | B5: Год | C5: Взнос | D5: Доля Акций | E5: Доля Облигаций | F5: Доходность стратегии за год | G5: Портфель на НАЧАЛО года | H5: Доход | I5: Итоговый портфель, ₽ | J5: Вложено всего, ₽ | K5: Номинальная доходность | L5: Реальная доходность, % | M5: Среднегодовой рост | Q5: 2006 | R5: =I8 -> 1032704.8 | S5: =I32 -> 457770.24 | T5: =I80 -> 717993.11 | U5: =J8 -> 386021.46
A6: Акции 100% | B6: ='Исходные данные'!A4 -> 2004 | C6: =IF(AND(Таблица16[[#This Row],[Год]]>=Настройки!$B$4, Таблица16[[#This Row],[Год]]<=Настройки!$B$5),IFERROR(VLOOKUP(Таблица16[[#This Row],[Год]],Данные[#All],9,FALSE),0),0) -> 115000 | D6: =VLOOKUP($A$6,Настройки!$L$2:$N$13,2,FALSE) -> 1 | E6: =VLOOKUP($A$6,Настройки!$L$2:$N$13,3,FALSE) -> 0 | F6: =D6*VLOOKUP(B6,'Исходные данные'!$A$4:$G$24,2,FALSE)+E6*VLOOKUP(B6,'Исходные данные'!$A$4:$G$24,3,FALSE)+(1-D6-E6)*VLOOKUP(B6,'Исходные данные'!$A$4:$G$24,4,FALSE) -> 0.072875988 | G6: =0 -> 0 | H6: =(G6+C6)*F6 -> 8380.7387 | I6: =G6+C6+H6 -> 123380.74 | J6: =C6 -> 115000 | K6: =IFERROR((I6-J6)/J6,"") -> 0.072875988 | L6: =IFERROR((1+K6)/VLOOKUP(B6,'Исходные данные'!$A$4:$G$24,6,FALSE)-1,"") -> -0.039846082 | M6: =IFERROR((I6/J6)^(1/(B6-$B$6+1))-1,"") -> 0.072875988 | Q6: 2007 | R6: =I9 -> 1338354.3 | S6: =I33 -> 658505.44 | T6: =I81 -> 960910 | U6: =J9 -> 541368.76
A7: Акции 100% | B7: ='Исходные данные'!A5 -> 2005 | C7: =IF(AND(Таблица16[[#This Row],[Год]]>=Настройки!$B$4, Таблица16[[#This Row],[Год]]<=Настройки!$B$5),IFERROR(VLOOKUP(Таблица16[[#This Row],[Год]],Данные[#All],9,FALSE),0),0) -> 128501 | D7: =VLOOKUP($A$6,Настройки!$L$2:$N$13,2,FALSE) -> 1 | E7: =VLOOKUP($A$6,Настройки!$L$2:$N$13,3,FALSE) -> 0 | F7: =D7*VLOOKUP(B7,'Исходные данные'!$A$4:$G$24,2,FALSE)+E7*VLOOKUP(B7,'Исходные данные'!$A$4:$G$24,3,FALSE)+(1-D7-E7)*VLOOKUP(B7,'Исходные данные'!$A$4:$G$24,4,FALSE) -> 0.84873782 | G7: =I6 -> 123380.74 | H7: =(G7+C7)*F7 -> 213781.56 | I7: =G7+C7+H7 -> 465663.3 | J7: =J6+C7 -> 243501 | K7: =IFERROR((I7-J7)/J7,"") -> 0.91236708 | L7: =IFERROR((1+K7)/VLOOKUP(B7,'Исходные данные'!$A$4:$G$24,6,FALSE)-1,"") -> 0.54309224 | M7: =IFERROR((I7/J7)^(1/(B7-$B$6+1))-1,"") -> 0.38288361 | Q7: 2008 | R7: =I10 -> 504927.25 | S7: =I34 -> 786069.28 | T7: =I82 -> 725285.97 | U7: =J10 -> 715155.78
A8: Акции 100% | B8: ='Исходные данные'!A6 -> 2006 | C8: =IF(AND(Таблица16[[#This Row],[Год]]>=Настройки!$B$4, Таблица16[[#This Row],[Год]]<=Настройки!$B$5),IFERROR(VLOOKUP(Таблица16[[#This Row],[Год]],Данные[#All],9,FALSE),0),0) -> 142520.46 | D8: =VLOOKUP($A$6,Настройки!$L$2:$N$13,2,FALSE) -> 1 | E8: =VLOOKUP($A$6,Настройки!$L$2:$N$13,3,FALSE) -> 0 | F8: =D8*VLOOKUP(B8,'Исходные данные'!$A$4:$G$24,2,FALSE)+E8*VLOOKUP(B8,'Исходные данные'!$A$4:$G$24,3,FALSE)+(1-D8-E8)*VLOOKUP(B8,'Исходные данные'!$A$4:$G$24,4,FALSE) -> 0.69801452 | G8: =I7 -> 465663.3 | H8: =(G8+C8)*F8 -> 424521.09 | I8: =G8+C8+H8 -> 1032704.8 | J8: =J7+C8 -> 386021.46 | K8: =IFERROR((I8-J8)/J8,"") -> 1.6752524 | L8: =IFERROR((1+K8)/VLOOKUP(B8,'Исходные данные'!$A$4:$G$24,6,FALSE)-1,"") -> 0.98042727 | M8: =IFERROR((I8/J8)^(1/(B8-$B$6+1))-1,"") -> 0.38820921 | Q8: 2009 | R8: =I11 -> 1586815.9 | S8: =I35 -> 1330190.8 | T8: =I83 -> 1666500 | U8: =J11 -> 912021.73
A9: Акции 100% | B9: ='Исходные данные'!A7 -> 2007 | C9: =IF(AND(Таблица16[[#This Row],[Год]]>=Настройки!$B$4, Таблица16[[#This Row],[Год]]<=Настройки!$B$5),IFERROR(VLOOKUP(Таблица16[[#This Row],[Год]],Данные[#All],9,FALSE),0),0) -> 155347.3 | D9: =VLOOKUP($A$6,Настройки!$L$2:$N$13,2,FALSE) -> 1 | E9: =VLOOKUP($A$6,Настройки!$L$2:$N$13,3,FALSE) -> 0 | F9: =D9*VLOOKUP(B9,'Исходные данные'!$A$4:$G$24,2,FALSE)+E9*VLOOKUP(B9,'Исходные данные'!$A$4:$G$24,3,FALSE)+(1-D9-E9)*VLOOKUP(B9,'Исходные данные'!$A$4:$G$24,4,FALSE) -> 0.12651138 | G9: =I8 -> 1032704.8 | H9: =(G9+C9)*F9 -> 150302.11 | I9: =G9+C9+H9 -> 1338354.3 | J9: =J8+C9 -> 541368.76 | K9: =IFERROR((I9-J9)/J9,"") -> 1.4721675 | L9: =IFERROR((1+K9)/VLOOKUP(B9,'Исходные данные'!$A$4:$G$24,6,FALSE)-1,"") -> 0.63590615 | M9: =IFERROR((I9/J9)^(1/(B9-$B$6+1))-1,"") -> 0.25391897 | Q9: 2010 | R9: =I12 -> 2256384.8 | S9: =I36 -> 1716541 | T9: =I84 -> 2223278.6 | U9: =J12 -> 1126211.9
A10: Акции 100% | B10: ='Исходные данные'!A8 -> 2008 | C10: =IF(AND(Таблица16[[#This Row],[Год]]>=Настройки!$B$4, Таблица16[[#This Row],[Год]]<=Настройки!$B$5),IFERROR(VLOOKUP(Таблица16[[#This Row],[Год]],Данные[#All],9,FALSE),0),0) -> 173787.02 | D10: =VLOOKUP($A$6,Настройки!$L$2:$N$13,2,FALSE) -> 1 | E10: =VLOOKUP($A$6,Настройки!$L$2:$N$13,3,FALSE) -> 0 | F10: =D10*VLOOKUP(B10,'Исходные данные'!$A$4:$G$24,2,FALSE)+E10*VLOOKUP(B10,'Исходные данные'!$A$4:$G$24,3,FALSE)+(1-D10-E10)*VLOOKUP(B10,'Исходные данные'!$A$4:$G$24,4,FALSE) -> -0.66608461 | G10: =I9 -> 1338354.3 | H10: =(G10+C10)*F10 -> -1007214 | I10: =G10+C10+H10 -> 504927.25 | J10: =J9+C10 -> 715155.78 | K10: =IFERROR((I10-J10)/J10,"") -> -0.29396187 | L10: =IFERROR((1+K10)/VLOOKUP(B10,'Исходные данные'!$A$4:$G$24,6,FALSE)-1,"") -> -0.5875651 | M10: =IFERROR((I10/J10)^(1/(B10-$B$6+1))-1,"") -> -0.067249198 | Q10: 2011 | R10: =I13 -> 2129533.1 | S10: =I37 -> 2062498.9 | T10: =I85 -> 2349905.4 | U10: =J13 -> 1359207.9
A11: Акции 100% | B11: ='Исходные данные'!A9 -> 2009 | C11: =IF(AND(Таблица16[[#This Row],[Год]]>=Настройки!$B$4, Таблица16[[#This Row],[Год]]<=Настройки!$B$5),IFERROR(VLOOKUP(Таблица16[[#This Row],[Год]],Данные[#All],9,FALSE),0),0) -> 196865.94 | D11: =VLOOKUP($A$6,Настройки!$L$2:$N$13,2,FALSE) -> 1 | E11: =VLOOKUP($A$6,Настройки!$L$2:$N$13,3,FALSE) -> 0 | F11: =D11*VLOOKUP(B11,'Исходные данные'!$A$4:$G$24,2,FALSE)+E11*VLOOKUP(B11,'Исходные данные'!$A$4:$G$24,3,FALSE)+(1-D11-E11)*VLOOKUP(B11,'Исходные данные'!$A$4:$G$24,4,FALSE) -> 1.2610876 | G11: =I10 -> 504927.25 | H11: =(G11+C11)*F11 -> 885022.69 | I11: =G11+C11+H11 -> 1586815.9 | J11: =J10+C11 -> 912021.73 | K11: =IFERROR((I11-J11)/J11,"") -> 0.73988825 | L11: =IFERROR((1+K11)/VLOOKUP(B11,'Исходные данные'!$A$4:$G$24,6,FALSE)-1,"") -> -0.065843345 | M11: =IFERROR((I11/J11)^(1/(B11-$B$6+1))-1,"") -> 0.096697599 | Q11: 2012 | R11: =I14 -> 2585163.1 | S11: =I38 -> 2647976 | T11: =I86 -> 2901167.4 | U11: =J14 -> 1606416.7
A12: Акции 100% | B12: ='Исходные данные'!A10 -> 2010 | C12: =IF(AND(Таблица16[[#This Row],[Год]]>=Настройки!$B$4, Таблица16[[#This Row],[Год]]<=Настройки!$B$5),IFERROR(VLOOKUP(Таблица16[[#This Row],[Год]],Данные[#All],9,FALSE),0),0) -> 214190.14 | D12: =VLOOKUP($A$6,Настройки!$L$2:$N$13,2,FALSE) -> 1 | E12: =VLOOKUP($A$6,Настройки!$L$2:$N$13,3,FALSE) -> 0 | F12: =D12*VLOOKUP(B12,'Исходные данные'!$A$4:$G$24,2,FALSE)+E12*VLOOKUP(B12,'Исходные данные'!$A$4:$G$24,3,FALSE)+(1-D12-E12)*VLOOKUP(B12,'Исходные данные'!$A$4:$G$24,4,FALSE) -> 0.2528469 | G12: =I11 -> 1586815.9 | H12: =(G12+C12)*F12 -> 455378.8 | I12: =G12+C12+H12 -> 2256384.8 | J12: =J11+C12 -> 1126211.9 | K12: =IFERROR((I12-J12)/J12,"") -> 1.0035172 | L12: =IFERROR((1+K12)/VLOOKUP(B12,'Исходные данные'!$A$4:$G$24,6,FALSE)-1,"") -> -0.011122782 | M12: =IFERROR((I12/J12)^(1/(B12-$B$6+1))-1,"") -> 0.10436668 | Q12: 2013 | R12: =I15 -> 3028530.2 | S12: =I39 -> 3022144.6 | T12: =I87 -> 3324726.3 | U12: =J15 -> 1869891.8
A13: Акции 100% | B13: ='Исходные данные'!A11 -> 2011 | C13: =IF(AND(Таблица16[[#This Row],[Год]]>=Настройки!$B$4, Таблица16[[#This Row],[Год]]<=Настройки!$B$5),IFERROR(VLOOKUP(Таблица16[[#This Row],[Год]],Данные[#All],9,FALSE),0),0) -> 232996.04 | D13: =VLOOKUP($A$6,Настройки!$L$2:$N$13,2,FALSE) -> 1 | E13: =VLOOKUP($A$6,Настройки!$L$2:$N$13,3,FALSE) -> 0 | F13: =D13*VLOOKUP(B13,'Исходные данные'!$A$4:$G$24,2,FALSE)+E13*VLOOKUP(B13,'Исходные данные'!$A$4:$G$24,3,FALSE)+(1-D13-E13)*VLOOKUP(B13,'Исходные данные'!$A$4:$G$24,4,FALSE) -> -0.14455314 | G13: =I12 -> 2256384.8 | H13: =(G13+C13)*F13 -> -359847.81 | I13: =G13+C13+H13 -> 2129533.1 | J13: =J12+C13 -> 1359207.9 | K13: =IFERROR((I13-J13)/J13,"") -> 0.56674563 | L13: =IFERROR((1+K13)/VLOOKUP(B13,'Исходные данные'!$A$4:$G$24,6,FALSE)-1,"") -> -0.27115965 | M13: =IFERROR((I13/J13)^(1/(B13-$B$6+1))-1,"") -> 0.057729974 | Q13: 2014 | R13: =I16 -> 3247973.2 | S13: =I40 -> 2828515.5 | T13: =I88 -> 3313183.8 | U13: =J16 -> 2150361.1
A14: Акции 100% | B14: ='Исходные данные'!A12 -> 2012 | C14: =IF(AND(Таблица16[[#This Row],[Год]]>=Настройки!$B$4, Таблица16[[#This Row],[Год]]<=Настройки!$B$5),IFERROR(VLOOKUP(Таблица16[[#This Row],[Год]],Данные[#All],9,FALSE),0),0) -> 247208.8 | D14: =VLOOKUP($A$6,Настройки!$L$2:$N$13,2,FALSE) -> 1 | E14: =VLOOKUP($A$6,Настройки!$L$2:$N$13,3,FALSE) -> 0 | F14: =D14*VLOOKUP(B14,'Исходные данные'!$A$4:$G$24,2,FALSE)+E14*VLOOKUP(B14,'Исходные данные'!$A$4:$G$24,3,FALSE)+(1-D14-E14)*VLOOKUP(B14,'Исходные данные'!$A$4:$G$24,4,FALSE) -> 0.087691986 | G14: =I13 -> 2129533.1 | H14: =(G14+C14)*F14 -> 208421.21 | I14: =G14+C14+H14 -> 2585163.1 | J14: =J13+C14 -> 1606416.7 | K14: =IFERROR((I14-J14)/J14,"") -> 0.60927302 | L14: =IFERROR((1+K14)/VLOOKUP(B14,'Исходные данные'!$A$4:$G$24,6,FALSE)-1,"") -> -0.29759445 | M14: =IFERROR((I14/J14)^(1/(B14-$B$6+1))-1,"") -> 0.054287018 | Q14: 2015 | R14: =I17 -> 4709403 | S14: =I41 -> 4069136.6 | T14: =I89 -> 4746355.6 | U14: =J17 -> 2462691.7
A15: Акции 100% | B15: ='Исходные данные'!A13 -> 2013 | C15: =IF(AND(Таблица16[[#This Row],[Год]]>=Настройки!$B$4, Таблица16[[#This Row],[Год]]<=Настройки!$B$5),IFERROR(VLOOKUP(Таблица16[[#This Row],[Год]],Данные[#All],9,FALSE),0),0) -> 263475.14 | D15: =VLOOKUP($A$6,Настройки!$L$2:$N$13,2,FALSE) -> 1 | E15: =VLOOKUP($A$6,Настройки!$L$2:$N$13,3,FALSE) -> 0 | F15: =D15*VLOOKUP(B15,'Исходные данные'!$A$4:$G$24,2,FALSE)+E15*VLOOKUP(B15,'Исходные данные'!$A$4:$G$24,3,FALSE)+(1-D15-E15)*VLOOKUP(B15,'Исходные данные'!$A$4:$G$24,4,FALSE) -> 0.063150178 | G15: =I14 -> 2585163.1 | H15: =(G15+C15)*F15 -> 179892.01 | I15: =G15+C15+H15 -> 3028530.2 | J15: =J14+C15 -> 1869891.8 | K15: =IFERROR((I15-J15)/J15,"") -> 0.61962855 | L15: =IFERROR((1+K15)/VLOOKUP(B15,'Исходные данные'!$A$4:$G$24,6,FALSE)-1,"") -> -0.33590844 | M15: =IFERROR((I15/J15)^(1/(B15-$B$6+1))-1,"") -> 0.049401166 | Q15: 2016 | R15: =I18 -> 6721413.9 | S15: =I42 -> 5079674.3 | T15: =I90 -> 6314065.6 | U15: =J18 -> 2815344.2
A16: Акции 100% | B16: ='Исходные данные'!A14 -> 2014 | C16: =IF(AND(Таблица16[[#This Row],[Год]]>=Настройки!$B$4, Таблица16[[#This Row],[Год]]<=Настройки!$B$5),IFERROR(VLOOKUP(Таблица16[[#This Row],[Год]],Данные[#All],9,FALSE),0),0) -> 280469.28 | D16: =VLOOKUP($A$6,Настройки!$L$2:$N$13,2,FALSE) -> 1 | E16: =VLOOKUP($A$6,Настройки!$L$2:$N$13,3,FALSE) -> 0 | F16: =D16*VLOOKUP(B16,'Исходные данные'!$A$4:$G$24,2,FALSE)+E16*VLOOKUP(B16,'Исходные данные'!$A$4:$G$24,3,FALSE)+(1-D16-E16)*VLOOKUP(B16,'Исходные данные'!$A$4:$G$24,4,FALSE) -> -0.018442511 | G16: =I15 -> 3028530.2 | H16: =(G16+C16)*F16 -> -61026.259 | I16: =G16+C16+H16 -> 3247973.2 | J16: =J15+C16 -> 2150361.1 | K16: =IFERROR((I16-J16)/J16,"") -> 0.51043152 | L16: =IFERROR((1+K16)/VLOOKUP(B16,'Исходные данные'!$A$4:$G$24,6,FALSE)-1,"") -> -0.44385972 | M16: =IFERROR((I16/J16)^(1/(B16-$B$6+1))-1,"") -> 0.038202124 | Q16: 2017 | R16: =I19 -> 7079844.6 | S16: =I43 -> 6145721.6 | T16: =I91 -> 7105305.9 | U16: =J19 -> 3186969.4
A17: Акции 100% | B17: ='Исходные данные'!A15 -> 2015 | C17: =IF(AND(Таблица16[[#This Row],[Год]]>=Настройки!$B$4, Таблица16[[#This Row],[Год]]<=Настройки!$B$5),IFERROR(VLOOKUP(Таблица16[[#This Row],[Год]],Данные[#All],9,FALSE),0),0) -> 312330.59 | D17: =VLOOKUP($A$6,Настройки!$L$2:$N$13,2,FALSE) -> 1 | E17: =VLOOKUP($A$6,Настройки!$L$2:$N$13,3,FALSE) -> 0 | F17: =D17*VLOOKUP(B17,'Исходные данные'!$A$4:$G$24,2,FALSE)+E17*VLOOKUP(B17,'Исходные данные'!$A$4:$G$24,3,FALSE)+(1-D17-E17)*VLOOKUP(B17,'Исходные данные'!$A$4:$G$24,4,FALSE) -> 0.32275312 | G17: =I16 -> 3247973.2 | H17: =(G17+C17)*F17 -> 1149099.2 | I17: =G17+C17+H17 -> 4709403 | J17: =J16+C17 -> 2462691.7 | K17: =IFERROR((I17-J17)/J17,"") -> 0.91229904 | L17: =IFERROR((1+K17)/VLOOKUP(B17,'Исходные данные'!$A$4:$G$24,6,FALSE)-1,"") -> -0.37639913 | M17: =IFERROR((I17/J17)^(1/(B17-$B$6+1))-1,"") -> 0.055511535 | Q17: 2018 | R17: =I20 -> 8884765.2 | S17: =I44 -> 6665223.7 | T17: =I92 -> 8280129.3 | U17: =J20 -> 3567959.5
A18: Акции 100% | B18: ='Исходные данные'!A16 -> 2016 | C18: =IF(AND(Таблица16[[#This Row],[Год]]>=Настройки!$B$4, Таблица16[[#This Row],[Год]]<=Настройки!$B$5),IFERROR(VLOOKUP(Таблица16[[#This Row],[Год]],Данные[#All],9,FALSE),0),0) -> 352652.47 | D18: =VLOOKUP($A$6,Настройки!$L$2:$N$13,2,FALSE) -> 1 | E18: =VLOOKUP($A$6,Настройки!$L$2:$N$13,3,FALSE) -> 0 | F18: =D18*VLOOKUP(B18,'Исходные данные'!$A$4:$G$24,2,FALSE)+E18*VLOOKUP(B18,'Исходные данные'!$A$4:$G$24,3,FALSE)+(1-D18-E18)*VLOOKUP(B18,'Исходные данные'!$A$4:$G$24,4,FALSE) -> 0.32780328 | G18: =I17 -> 4709403 | H18: =(G18+C18)*F18 -> 1659358.4 | I18: =G18+C18+H18 -> 6721413.9 | J18: =J17+C18 -> 2815344.2 | K18: =IFERROR((I18-J18)/J18,"") -> 1.3874217 | L18: =IFERROR((1+K18)/VLOOKUP(B18,'Исходные данные'!$A$4:$G$24,6,FALSE)-1,"") -> -0.26120857 | M18: =IFERROR((I18/J18)^(1/(B18-$B$6+1))-1,"") -> 0.069230829 | Q18: 2019 | R18: =I21 -> 12851033 | S18: =I45 -> 8474415.2 | T18: =I93 -> 11213042 | U18: =J21 -> 3965217.9
... A23: Акции 100% | B23: ='Исходные данные'!A21 -> 2021 | C23: =IF(AND(Таблица16[[#This Row],[Год]]>=Настройки!$B$4, Таблица16[[#This Row],[Год]]<=Настройки!$B$5),IFERROR(VLOOKUP(Таблица16[[#This Row],[Год]],Данные[#All],9,FALSE),0),0) -> 429475.09 | D23: =VLOOKUP($A$6,Настройки!$L$2:$N$13,2,FALSE) -> 1 | E23: =VLOOKUP($A$6,Настройки!$L$2:$N$13,3,FALSE) -> 0 | F23: =D23*VLOOKUP(B23,'Исходные данные'!$A$4:$G$24,2,FALSE)+E23*VLOOKUP(B23,'Исходные данные'!$A$4:$G$24,3,FALSE)+(1-D23-E23)*VLOOKUP(B23,'Исходные данные'!$A$4:$G$24,4,FALSE) -> 0.21792712 | G23: =I22 -> 15226237 | H23: =(G23+C23)*F23 -> 3411804.1 | I23: =G23+C23+H23 -> 19067516 | J23: =J22+C23 -> 4804067.8 | K23: =IFERROR((I23-J23)/J23,"") -> 2.9690355 | L23: =IFERROR((1+K23)/VLOOKUP(B23,'Исходные данные'!$A$4:$G$24,6,FALSE)-1,"") -> -0.019481867 | M23: =IFERROR((I23/J23)^(1/(B23-$B$6+1))-1,"") -> 0.07959354 | Q23: 2024 | R23: =I26 -> 20545366 | S23: =I50 -> 10575459 | T23: =I98 -> 16523305 | U23: =J26 -> 6350420.1
A24: Акции 100% | B24: ='Исходные данные'!A22 -> 2022 | C24: =IF(AND(Таблица16[[#This Row],[Год]]>=Настройки!$B$4, Таблица16[[#This Row],[Год]]<=Настройки!$B$5),IFERROR(VLOOKUP(Таблица16[[#This Row],[Год]],Данные[#All],9,FALSE),0),0) -> 465508.05 | D24: =VLOOKUP($A$6,Настройки!$L$2:$N$13,2,FALSE) -> 1 | E24: =VLOOKUP($A$6,Настройки!$L$2:$N$13,3,FALSE) -> 0 | F24: =D24*VLOOKUP(B24,'Исходные данные'!$A$4:$G$24,2,FALSE)+E24*VLOOKUP(B24,'Исходные данные'!$A$4:$G$24,3,FALSE)+(1-D24-E24)*VLOOKUP(B24,'Исходные данные'!$A$4:$G$24,4,FALSE) -> -0.37258001 | G24: =I23 -> 19067516 | H24: =(G24+C24)*F24 -> -7277614.3 | I24: =G24+C24+H24 -> 12255410 | J24: =J23+C24 -> 5269575.8 | K24: =IFERROR((I24-J24)/J24,"") -> 1.3256918 | L24: =IFERROR((1+K24)/VLOOKUP(B24,'Исходные данные'!$A$4:$G$24,6,FALSE)-1,"") -> -0.48673989 | M24: =IFERROR((I24/J24)^(1/(B24-$B$6+1))-1,"") -> 0.045423406
A25: Акции 100% | B25: ='Исходные данные'!A23 -> 2023 | C25: =IF(AND(Таблица16[[#This Row],[Год]]>=Настройки!$B$4, Таблица16[[#This Row],[Год]]<=Настройки!$B$5),IFERROR(VLOOKUP(Таблица16[[#This Row],[Год]],Данные[#All],9,FALSE),0),0) -> 521089.72 | D25: =VLOOKUP($A$6,Настройки!$L$2:$N$13,2,FALSE) -> 1 | E25: =VLOOKUP($A$6,Настройки!$L$2:$N$13,3,FALSE) -> 0 | F25: =D25*VLOOKUP(B25,'Исходные данные'!$A$4:$G$24,2,FALSE)+E25*VLOOKUP(B25,'Исходные данные'!$A$4:$G$24,3,FALSE)+(1-D25-E25)*VLOOKUP(B25,'Исходные данные'!$A$4:$G$24,4,FALSE) -> 0.53835061 | G25: =I24 -> 12255410 | H25: =(G25+C25)*F25 -> 6878236.1 | I25: =G25+C25+H25 -> 19654735 | J25: =J24+C25 -> 5790665.6 | K25: =IFERROR((I25-J25)/J25,"") -> 2.3942101 | L25: =IFERROR((1+K25)/VLOOKUP(B25,'Исходные данные'!$A$4:$G$24,6,FALSE)-1,"") -> -0.3026691 | M25: =IFERROR((I25/J25)^(1/(B25-$B$6+1))-1,"") -> 0.063008986
A26: Акции 100% | B26: ='Исходные данные'!A24 -> 2024 | C26: =IF(AND(Таблица16[[#This Row],[Год]]>=Настройки!$B$4, Таблица16[[#This Row],[Год]]<=Настройки!$B$5),IFERROR(VLOOKUP(Таблица16[[#This Row],[Год]],Данные[#All],9,FALSE),0),0) -> 559754.57 | D26: =VLOOKUP($A$6,Настройки!$L$2:$N$13,2,FALSE) -> 1 | E26: =VLOOKUP($A$6,Настройки!$L$2:$N$13,3,FALSE) -> 0 | F26: =D26*VLOOKUP(B26,'Исходные данные'!$A$4:$G$24,2,FALSE)+E26*VLOOKUP(B26,'Исходные данные'!$A$4:$G$24,3,FALSE)+(1-D26-E26)*VLOOKUP(B26,'Исходные данные'!$A$4:$G$24,4,FALSE) -> 0.016368282 | G26: =I25 -> 19654735 | H26: =(G26+C26)*F26 -> 330876.47 | I26: =G26+C26+H26 -> 20545366 | J26: =J25+C26 -> 6350420.1 | K26: =IFERROR((I26-J26)/J26,"") -> 2.2352767 | L26: =IFERROR((1+K26)/VLOOKUP(B26,'Исходные данные'!$A$4:$G$24,6,FALSE)-1,"") -> -0.39309853 | M26: =IFERROR((I26/J26)^(1/(B26-$B$6+1))-1,"") -> 0.057502729
A29: Стратегия | B29: Год | C29: Взнос | D29: Доля Акций | E29: Доля Облигаций | F29: Доходность стратегии за год | G29: Портфель на НАЧАЛО года | H29: Доход | I29: Итоговый портфель, ₽ | J29: Вложено всего, ₽ | K29: Номинальная доходность | L29: Реальная доходность, % | M29: Среднегодовой рост
A30: Облигации 100% | B30: ='Исходные данные'!$A4 -> 2004 | C30: =IF(AND(Таблица15[[#This Row],[Год]]>=Настройки!$B$4, Таблица15[[#This Row],[Год]]<=Настройки!$B$5),IFERROR(VLOOKUP(Таблица15[[#This Row],[Год]],Данные[#All],9,FALSE),0),0) -> 115000 | D30: =VLOOKUP($A$30,Настройки!$L$2:$N$13,2,FALSE) -> 0 | E30: =VLOOKUP($A$30,Настройки!$L$2:$N$13,3,FALSE) -> 1 | F30: =D30*VLOOKUP(B30,'Исходные данные'!$A$4:$G$24,2,FALSE)+E30*VLOOKUP(B30,'Исходные данные'!$A$4:$G$24,3,FALSE)+(1-D30-E30)*VLOOKUP(B30,'Исходные данные'!$A$4:$G$24,4,FALSE) -> 0.10890159 | G30: =0 -> 0 | H30: =(G30+C30)*F30 -> 12523.683 | I30: =G30+C30+H30 -> 127523.68 | J30: =C30 -> 115000 | K30: =IFERROR((I30-J30)/J30,"") -> 0.10890159 | L30: =IFERROR((1+K30)/VLOOKUP(B30,'Исходные данные'!$A$4:$G$24,6,FALSE)-1,"") -> -0.0076055224 | M30: =IFERROR((I30/J30)^(1/(B30-$B$30+1))-1,"") -> 0.10890159
A31: Облигации 100% | B31: ='Исходные данные'!$A5 -> 2005 | C31: =IF(AND(Таблица15[[#This Row],[Год]]>=Настройки!$B$4, Таблица15[[#This Row],[Год]]<=Настройки!$B$5),IFERROR(VLOOKUP(Таблица15[[#This Row],[Год]],Данные[#All],9,FALSE),0),0) -> 128501 | D31: =VLOOKUP($A$30,Настройки!$L$2:$N$13,2,FALSE) -> 0 | E31: =VLOOKUP($A$30,Настройки!$L$2:$N$13,3,FALSE) -> 1 | F31: =D31*VLOOKUP(B31,'Исходные данные'!$A$4:$G$24,2,FALSE)+E31*VLOOKUP(B31,'Исходные данные'!$A$4:$G$24,3,FALSE)+(1-D31-E31)*VLOOKUP(B31,'Исходные данные'!$A$4:$G$24,4,FALSE) -> 0.11642191 | G31: =I30 -> 127523.68 | H31: =(G31+C31)*F31 -> 29806.884 | I31: =G31+C31+H31 -> 285831.57 | J31: =J30+C31 -> 243501 | K31: =IFERROR((I31-J31)/J31,"") -> 0.17384145 | L31: =IFERROR((1+K31)/VLOOKUP(B31,'Исходные данные'!$A$4:$G$24,6,FALSE)-1,"") -> -0.052825346 | M31: =IFERROR((I31/J31)^(1/(B31-$B$30+1))-1,"") -> 0.083439638
A32: Облигации 100% | B32: ='Исходные данные'!$A6 -> 2006 | C32: =IF(AND(Таблица15[[#This Row],[Год]]>=Настройки!$B$4, Таблица15[[#This Row],[Год]]<=Настройки!$B$5),IFERROR(VLOOKUP(Таблица15[[#This Row],[Год]],Данные[#All],9,FALSE),0),0) -> 142520.46 | D32: =VLOOKUP($A$30,Настройки!$L$2:$N$13,2,FALSE) -> 0 | E32: =VLOOKUP($A$30,Настройки!$L$2:$N$13,3,FALSE) -> 1 | F32: =D32*VLOOKUP(B32,'Исходные данные'!$A$4:$G$24,2,FALSE)+E32*VLOOKUP(B32,'Исходные данные'!$A$4:$G$24,3,FALSE)+(1-D32-E32)*VLOOKUP(B32,'Исходные данные'!$A$4:$G$24,4,FALSE) -> 0.06867767 | G32: =I31 -> 285831.57 | H32: =(G32+C32)*F32 -> 29418.219 | I32: =G32+C32+H32 -> 457770.24 | J32: =J31+C32 -> 386021.46 | K32: =IFERROR((I32-J32)/J32,"") -> 0.18586735 | L32: =IFERROR((1+K32)/VLOOKUP(B32,'Исходные данные'!$A$4:$G$24,6,FALSE)-1,"") -> -0.12212993 | M32: =IFERROR((I32/J32)^(1/(B32-$B$30+1))-1,"") -> 0.058470367
A33: Облигации 100% | B33: ='Исходные данные'!$A7 -> 2007 | C33: =IF(AND(Таблица15[[#This Row],[Год]]>=Настройки!$B$4, Таблица15[[#This Row],[Год]]<=Настройки!$B$5),IFERROR(VLOOKUP(Таблица15[[#This Row],[Год]],Данные[#All],9,FALSE),0),0) -> 155347.3 | D33: =VLOOKUP($A$30,Настройки!$L$2:$N$13,2,FALSE) -> 0 | E33: =VLOOKUP($A$30,Настройки!$L$2:$N$13,3,FALSE) -> 1 | F33: =D33*VLOOKUP(B33,'Исходные данные'!$A$4:$G$24,2,FALSE)+E33*VLOOKUP(B33,'Исходные данные'!$A$4:$G$24,3,FALSE)+(1-D33-E33)*VLOOKUP(B33,'Исходные данные'!$A$4:$G$24,4,FALSE) -> 0.074028049 | G33: =I32 -> 457770.24 | H33: =(G33+C33)*F33 -> 45387.896 | I33: =G33+C33+H33 -> 658505.44 | J33: =J32+C33 -> 541368.76 | K33: =IFERROR((I33-J33)/J33,"") -> 0.21637134 | L33: =IFERROR((1+K33)/VLOOKUP(B33,'Исходные данные'!$A$4:$G$24,6,FALSE)-1,"") -> -0.19509121 | M33: =IFERROR((I33/J33)^(1/(B33-$B$30+1))-1,"") -> 0.050186773
A34: Облигации 100% | B34: ='Исходные данные'!$A8 -> 2008 | C34: =IF(AND(Таблица15[[#This Row],[Год]]>=Настройки!$B$4, Таблица15[[#This Row],[Год]]<=Настройки!$B$5),IFERROR(VLOOKUP(Таблица15[[#This Row],[Год]],Данные[#All],9,FALSE),0),0) -> 173787.02 | D34: =VLOOKUP($A$30,Настройки!$L$2:$N$13,2,FALSE) -> 0 | E34: =VLOOKUP($A$30,Настройки!$L$2:$N$13,3,FALSE) -> 1 | F34: =D34*VLOOKUP(B34,'Исходные данные'!$A$4:$G$24,2,FALSE)+E34*VLOOKUP(B34,'Исходные данные'!$A$4:$G$24,3,FALSE)+(1-D34-E34)*VLOOKUP(B34,'Исходные данные'!$A$4:$G$24,4,FALSE) -> -0.05553719 | G34: =I33 -> 658505.44 | H34: =(G34+C34)*F34 -> -46223.185 | I34: =G34+C34+H34 -> 786069.28 | J34: =J33+C34 -> 715155.78 | K34: =IFERROR((I34-J34)/J34,"") -> 0.099158111 | L34: =IFERROR((1+K34)/VLOOKUP(B34,'Исходные данные'!$A$4:$G$24,6,FALSE)-1,"") -> -0.35792255 | M34: =IFERROR((I34/J34)^(1/(B34-$B$30+1))-1,"") -> 0.019088812
A35: Облигации 100% | B35: ='Исходные данные'!$A9 -> 2009 | C35: =IF(AND(Таблица15[[#This Row],[Год]]>=Настройки!$B$4, Таблица15[[#This Row],[Год]]<=Настройки!$B$5),IFERROR(VLOOKUP(Таблица15[[#This Row],[Год]],Данные[#All],9,FALSE),0),0) -> 196865.94 | D35: =VLOOKUP($A$30,Настройки!$L$2:$N$13,2,FALSE) -> 0 | E35: =VLOOKUP($A$30,Настройки!$L$2:$N$13,3,FALSE) -> 1 | F35: =D35*VLOOKUP(B35,'Исходные данные'!$A$4:$G$24,2,FALSE)+E35*VLOOKUP(B35,'Исходные данные'!$A$4:$G$24,3,FALSE)+(1-D35-E35)*VLOOKUP(B35,'Исходные данные'!$A$4:$G$24,4,FALSE) -> 0.35328433 | G35: =I34 -> 786069.28 | H35: =(G35+C35)*F35 -> 347255.61 | I35: =G35+C35+H35 -> 1330190.8 | J35: =J34+C35 -> 912021.73 | K35: =IFERROR((I35-J35)/J35,"") -> 0.45850784 | L35: =IFERROR((1+K35)/VLOOKUP(B35,'Исходные данные'!$A$4:$G$24,6,FALSE)-1,"") -> -0.21691821 | M35: =IFERROR((I35/J35)^(1/(B35-$B$30+1))-1,"") -> 0.064922806
A36: Облигации 100% | B36: ='Исходные данные'!$A10 -> 2010 | C36: =IF(AND(Таблица15[[#This Row],[Год]]>=Настройки!$B$4, Таблица15[[#This Row],[Год]]<=Настройки!$B$5),IFERROR(VLOOKUP(Таблица15[[#This Row],[Год]],Данные[#All],9,FALSE),0),0) -> 214190.14 | D36: =VLOOKUP($A$30,Настройки!$L$2:$N$13,2,FALSE) -> 0 | E36: =VLOOKUP($A$30,Настройки!$L$2:$N$13,3,FALSE) -> 1 | F36: =D36*VLOOKUP(B36,'Исходные данные'!$A$4:$G$24,2,FALSE)+E36*VLOOKUP(B36,'Исходные данные'!$A$4:$G$24,3,FALSE)+(1-D36-E36)*VLOOKUP(B36,'Исходные данные'!$A$4:$G$24,4,FALSE) -> 0.11147513 | G36: =I35 -> 1330190.8 | H36: =(G36+C36)*F36 -> 172160.07 | I36: =G36+C36+H36 -> 1716541 | J36: =J35+C36 -> 1126211.9 | K36: =IFERROR((I36-J36)/J36,"") -> 0.5241724 | L36: =IFERROR((1+K36)/VLOOKUP(B36,'Исходные данные'!$A$4:$G$24,6,FALSE)-1,"") -> -0.24771328 | M36: =IFERROR((I36/J36)^(1/(B36-$B$30+1))-1,"") -> 0.06205676
A37: Облигации 100% | B37: ='Исходные данные'!$A11 -> 2011 | C37: =IF(AND(Таблица15[[#This Row],[Год]]>=Настройки!$B$4, Таблица15[[#This Row],[Год]]<=Настройки!$B$5),IFERROR(VLOOKUP(Таблица15[[#This Row],[Год]],Данные[#All],9,FALSE),0),0) -> 232996.04 | D37: =VLOOKUP($A$30,Настройки!$L$2:$N$13,2,FALSE) -> 0 | E37: =VLOOKUP($A$30,Настройки!$L$2:$N$13,3,FALSE) -> 1 | F37: =D37*VLOOKUP(B37,'Исходные данные'!$A$4:$G$24,2,FALSE)+E37*VLOOKUP(B37,'Исходные данные'!$A$4:$G$24,3,FALSE)+(1-D37-E37)*VLOOKUP(B37,'Исходные данные'!$A$4:$G$24,4,FALSE) -> 0.05794291 | G37: =I36 -> 1716541 | H37: =(G37+C37)*F37 -> 112961.85 | I37: =G37+C37+H37 -> 2062498.9 | J37: =J36+C37 -> 1359207.9 | K37: =IFERROR((I37-J37)/J37,"") -> 0.51742711 | L37: =IFERROR((1+K37)/VLOOKUP(B37,'Исходные данные'!$A$4:$G$24,6,FALSE)-1,"") -> -0.29410231 | M37: =IFERROR((I37/J37)^(1/(B37-$B$30+1))-1,"") -> 0.053509558
A38: Облигации 100% | B38: ='Исходные данные'!$A12 -> 2012 | C38: =IF(AND(Таблица15[[#This Row],[Год]]>=Настройки!$B$4, Таблица15[[#This Row],[Год]]<=Настройки!$B$5),IFERROR(VLOOKUP(Таблица15[[#This Row],[Год]],Данные[#All],9,FALSE),0),0) -> 247208.8 | D38: =VLOOKUP($A$30,Настройки!$L$2:$N$13,2,FALSE) -> 0 | E38: =VLOOKUP($A$30,Настройки!$L$2:$N$13,3,FALSE) -> 1 | F38: =D38*VLOOKUP(B38,'Исходные данные'!$A$4:$G$24,2,FALSE)+E38*VLOOKUP(B38,'Исходные данные'!$A$4:$G$24,3,FALSE)+(1-D38-E38)*VLOOKUP(B38,'Исходные данные'!$A$4:$G$24,4,FALSE) -> 0.14645502 | G38: =I37 -> 2062498.9 | H38: =(G38+C38)*F38 -> 338268.29 | I38: =G38+C38+H38 -> 2647976 | J38: =J37+C38 -> 1606416.7 | K38: =IFERROR((I38-J38)/J38,"") -> 0.64837431 | L38: =IFERROR((1+K38)/VLOOKUP(B38,'Исходные данные'!$A$4:$G$24,6,FALSE)-1,"") -> -0.28052777 | M38: =IFERROR((I38/J38)^(1/(B38-$B$30+1))-1,"") -> 0.057103024
A39: Облигации 100% | B39: ='Исходные данные'!$A13 -> 2013 | C39: =IF(AND(Таблица15[[#This Row],[Год]]>=Настройки!$B$4, Таблица15[[#This Row],[Год]]<=Настройки!$B$5),IFERROR(VLOOKUP(Таблица15[[#This Row],[Год]],Данные[#All],9,FALSE),0),0) -> 263475.14 | D39: =VLOOKUP($A$30,Настройки!$L$2:$N$13,2,FALSE) -> 0 | E39: =VLOOKUP($A$30,Настройки!$L$2:$N$13,3,FALSE) -> 1 | F39: =D39*VLOOKUP(B39,'Исходные данные'!$A$4:$G$24,2,FALSE)+E39*VLOOKUP(B39,'Исходные данные'!$A$4:$G$24,3,FALSE)+(1-D39-E39)*VLOOKUP(B39,'Исходные данные'!$A$4:$G$24,4,FALSE) -> 0.038020017 | G39: =I38 -> 2647976 | H39: =(G39+C39)*F39 -> 110693.42 | I39: =G39+C39+H39 -> 3022144.6 | J39: =J38+C39 -> 1869891.8 | K39: =IFERROR((I39-J39)/J39,"") -> 0.61621358 | L39: =IFERROR((1+K39)/VLOOKUP(B39,'Исходные данные'!$A$4:$G$24,6,FALSE)-1,"") -> -0.33730867 | M39: =IFERROR((I39/J39)^(1/(B39-$B$30+1))-1,"") -> 0.04917969
A40: Облигации 100% | B40: ='Исходные данные'!$A14 -> 2014 | C40: =IF(AND(Таблица15[[#This Row],[Год]]>=Настройки!$B$4, Таблица15[[#This Row],[Год]]<=Настройки!$B$5),IFERROR(VLOOKUP(Таблица15[[#This Row],[Год]],Данные[#All],9,FALSE),0),0) -> 280469.28 | D40: =VLOOKUP($A$30,Настройки!$L$2:$N$13,2,FALSE) -> 0 | E40: =VLOOKUP($A$30,Настройки!$L$2:$N$13,3,FALSE) -> 1 | F40: =D40*VLOOKUP(B40,'Исходные данные'!$A$4:$G$24,2,FALSE)+E40*VLOOKUP(B40,'Исходные данные'!$A$4:$G$24,3,FALSE)+(1-D40-E40)*VLOOKUP(B40,'Исходные данные'!$A$4:$G$24,4,FALSE) -> -0.14355246 | G40: =I39 -> 3022144.6 | H40: =(G40+C40)*F40 -> -474098.35 | I40: =G40+C40+H40 -> 2828515.5 | J40: =J39+C40 -> 2150361.1 | K40: =IFERROR((I40-J40)/J40,"") -> 0.31536768 | L40: =IFERROR((1+K40)/VLOOKUP(B40,'Исходные данные'!$A$4:$G$24,6,FALSE)-1,"") -> -0.51568215 | M40: =IFERROR((I40/J40)^(1/(B40-$B$30+1))-1,"") -> 0.025232747
A41: Облигации 100% | B41: ='Исходные данные'!$A15 -> 2015 | C41: =IF(AND(Таблица15[[#This Row],[Год]]>=Настройки!$B$4, Таблица15[[#This Row],[Год]]<=Настройки!$B$5),IFERROR(VLOOKUP(Таблица15[[#This Row],[Год]],Данные[#All],9,FALSE),0),0) -> 312330.59 | D41: =VLOOKUP($A$30,Настройки!$L$2:$N$13,2,FALSE) -> 0 | E41: =VLOOKUP($A$30,Настройки!$L$2:$N$13,3,FALSE) -> 1 | F41: =D41*VLOOKUP(B41,'Исходные данные'!$A$4:$G$24,2,FALSE)+E41*VLOOKUP(B41,'Исходные данные'!$A$4:$G$24,3,FALSE)+(1-D41-E41)*VLOOKUP(B41,'Исходные данные'!$A$4:$G$24,4,FALSE) -> 0.29555428 | G41: =I40 -> 2828515.5 | H41: =(G41+C41)*F41 -> 928290.5 | I41: =G41+C41+H41 -> 4069136.6 | J41: =J40+C41 -> 2462691.7 | K41: =IFERROR((I41-J41)/J41,"") -> 0.65231262 | L41: =IFERROR((1+K41)/VLOOKUP(B41,'Исходные данные'!$A$4:$G$24,6,FALSE)-1,"") -> -0.46118072 | M41: =IFERROR((I41/J41)^(1/(B41-$B$30+1))-1,"") -> 0.042735962
A42: Облигации 100% | B42: ='Исходные данные'!$A16 -> 2016 | C42: =IF(AND(Таблица15[[#This Row],[Год]]>=Настройки!$B$4, Таблица15[[#This Row],[Год]]<=Настройки!$B$5),IFERROR(VLOOKUP(Таблица15[[#This Row],[Год]],Данные[#All],9,FALSE),0),0) -> 352652.47 | D42: =VLOOKUP($A$30,Настройки!$L$2:$N$13,2,FALSE) -> 0 | E42: =VLOOKUP($A$30,Настройки!$L$2:$N$13,3,FALSE) -> 1 | F42: =D42*VLOOKUP(B42,'Исходные данные'!$A$4:$G$24,2,FALSE)+E42*VLOOKUP(B42,'Исходные данные'!$A$4:$G$24,3,FALSE)+(1-D42-E42)*VLOOKUP(B42,'Исходные данные'!$A$4:$G$24,4,FALSE) -> 0.14878259 | G42: =I41 -> 4069136.6 | H42: =(G42+C42)*F42 -> 657885.22 | I42: =G42+C42+H42 -> 5079674.3 | J42: =J41+C42 -> 2815344.2 | K42: =IFERROR((I42-J42)/J42,"") -> 0.80428181 | L42: =IFERROR((1+K42)/VLOOKUP(B42,'Исходные данные'!$A$4:$G$24,6,FALSE)-1,"") -> -0.44166213 | M42: =IFERROR((I42/J42)^(1/(B42-$B$30+1))-1,"") -> 0.046443346
... A50: Облигации 100% | B50: ='Исходные данные'!$A24 -> 2024 | C50: =IF(AND(Таблица15[[#This Row],[Год]]>=Настройки!$B$4, Таблица15[[#This Row],[Год]]<=Настройки!$B$5),IFERROR(VLOOKUP(Таблица15[[#This Row],[Год]],Данные[#All],9,FALSE),0),0) -> 559754.57 | D50: =VLOOKUP($A$30,Настройки!$L$2:$N$13,2,FALSE) -> 0 | E50: =VLOOKUP($A$30,Настройки!$L$2:$N$13,3,FALSE) -> 1 | F50: =D50*VLOOKUP(B50,'Исходные данные'!$A$4:$G$24,2,FALSE)+E50*VLOOKUP(B50,'Исходные данные'!$A$4:$G$24,3,FALSE)+(1-D50-E50)*VLOOKUP(B50,'Исходные данные'!$A$4:$G$24,4,FALSE) -> -0.086555154 | G50: =I49 -> 11017802 | H50: =(G50+C50)*F50 -> -1002097.2 | I50: =G50+C50+H50 -> 10575459 | J50: =J49+C50 -> 6350420.1 | K50: =IFERROR((I50-J50)/J50,"") -> 0.66531648 | L50: =IFERROR((1+K50)/VLOOKUP(B50,'Исходные данные'!$A$4:$G$24,6,FALSE)-1,"") -> -0.68760539 | M50: =IFERROR((I50/J50)^(1/(B50-$B$30+1))-1,"") -> 0.024583755
A53: Стратегия | B53: Год | C53: Взнос | D53: Доля Акций | E53: Доля Облигаций | F53: Доходность стратегии за год | G53: Портфель на НАЧАЛО года | H53: Доход | I53: Итоговый портфель, ₽ | J53: Вложено всего, ₽ | K53: Номинальная доходность | L53: Реальная доходность, % | M53: Среднегодовой рост
A54: Вклады 100% | B54: ='Исходные данные'!$A4 -> 2004 | C54: =IF(AND(Таблица14[[#This Row],[Год]]>=Настройки!$B$4, Таблица14[[#This Row],[Год]]<=Настройки!$B$5),IFERROR(VLOOKUP(Таблица14[[#This Row],[Год]],Данные[#All],9,FALSE),0),0) -> 115000 | D54: =VLOOKUP($A$54,Настройки!$L$2:$N$13,2,FALSE) -> 0 | E54: =VLOOKUP($A$54,Настройки!$L$2:$N$13,3,FALSE) -> 0 | F54: =D54*VLOOKUP(B54,'Исходные данные'!$A$4:$G$24,2,FALSE)+E54*VLOOKUP(B54,'Исходные данные'!$A$4:$G$24,3,FALSE)+(1-D54-E54)*VLOOKUP(B54,'Исходные данные'!$A$4:$G$24,4,FALSE) -> 0.102 | G54: =0 -> 0 | H54: =(G54+C54)*F54 -> 11730 | I54: =G54+C54+H54 -> 126730 | J54: =C54 -> 115000 | K54: =IFERROR((I54-J54)/J54,"") -> 0.102 | L54: =IFERROR((1+K54)/VLOOKUP(B54,'Исходные данные'!$A$4:$G$24,6,FALSE)-1,"") -> -0.013781994 | M54: =IFERROR((I54/J54)^(1/(B54-$B$54+1))-1,"") -> 0.102
A55: Вклады 100% | B55: ='Исходные данные'!$A5 -> 2005 | C55: =IF(AND(Таблица14[[#This Row],[Год]]>=Настройки!$B$4, Таблица14[[#This Row],[Год]]<=Настройки!$B$5),IFERROR(VLOOKUP(Таблица14[[#This Row],[Год]],Данные[#All],9,FALSE),0),0) -> 128501 | D55: =VLOOKUP($A$54,Настройки!$L$2:$N$13,2,FALSE) -> 0 | E55: =VLOOKUP($A$54,Настройки!$L$2:$N$13,3,FALSE) -> 0 | F55: =D55*VLOOKUP(B55,'Исходные данные'!$A$4:$G$24,2,FALSE)+E55*VLOOKUP(B55,'Исходные данные'!$A$4:$G$24,3,FALSE)+(1-D55-E55)*VLOOKUP(B55,'Исходные данные'!$A$4:$G$24,4,FALSE) -> 0.084 | G55: =I54 -> 126730 | H55: =(G55+C55)*F55 -> 21439.404 | I55: =G55+C55+H55 -> 276670.4 | J55: =J54+C55 -> 243501 | K55: =IFERROR((I55-J55)/J55,"") -> 0.13621876 | L55: =IFERROR((1+K55)/VLOOKUP(B55,'Исходные данные'!$A$4:$G$24,6,FALSE)-1,"") -> -0.083183158 | M55: =IFERROR((I55/J55)^(1/(B55-$B$54+1))-1,"") -> 0.065935626
A56: Вклады 100% | B56: ='Исходные данные'!$A6 -> 2006 | C56: =IF(AND(Таблица14[[#This Row],[Год]]>=Настройки!$B$4, Таблица14[[#This Row],[Год]]<=Настройки!$B$5),IFERROR(VLOOKUP(Таблица14[[#This Row],[Год]],Данные[#All],9,FALSE),0),0) -> 142520.46 | D56: =VLOOKUP($A$54,Настройки!$L$2:$N$13,2,FALSE) -> 0 | E56: =VLOOKUP($A$54,Настройки!$L$2:$N$13,3,FALSE) -> 0 | F56: =D56*VLOOKUP(B56,'Исходные данные'!$A$4:$G$24,2,FALSE)+E56*VLOOKUP(B56,'Исходные данные'!$A$4:$G$24,3,FALSE)+(1-D56-E56)*VLOOKUP(B56,'Исходные данные'!$A$4:$G$24,4,FALSE) -> 0.089 | G56: =I55 -> 276670.4 | H56: =(G56+C56)*F56 -> 37307.987 | I56: =G56+C56+H56 -> 456498.85 | J56: =J55+C56 -> 386021.46 | K56: =IFERROR((I56-J56)/J56,"") -> 0.18257376 | L56: =IFERROR((1+K56)/VLOOKUP(B56,'Исходные данные'!$A$4:$G$24,6,FALSE)-1,"") -> -0.1245681 | M56: =IFERROR((I56/J56)^(1/(B56-$B$54+1))-1,"") -> 0.057489539
A57: Вклады 100% | B57: ='Исходные данные'!$A7 -> 2007 | C57: =IF(AND(Таблица14[[#This Row],[Год]]>=Настройки!$B$4, Таблица14[[#This Row],[Год]]<=Настройки!$B$5),IFERROR(VLOOKUP(Таблица14[[#This Row],[Год]],Данные[#All],9,FALSE),0),0) -> 155347.3 | D57: =VLOOKUP($A$54,Настройки!$L$2:$N$13,2,FALSE) -> 0 | E57: =VLOOKUP($A$54,Настройки!$L$2:$N$13,3,FALSE) -> 0 | F57: =D57*VLOOKUP(B57,'Исходные данные'!$A$4:$G$24,2,FALSE)+E57*VLOOKUP(B57,'Исходные данные'!$A$4:$G$24,3,FALSE)+(1-D57-E57)*VLOOKUP(B57,'Исходные данные'!$A$4:$G$24,4,FALSE) -> 0.08 | G57: =I56 -> 456498.85 | H57: =(G57+C57)*F57 -> 48947.692 | I57: =G57+C57+H57 -> 660793.84 | J57: =J56+C57 -> 541368.76 | K57: =IFERROR((I57-J57)/J57,"") -> 0.2205984 | L57: =IFERROR((1+K57)/VLOOKUP(B57,'Исходные данные'!$A$4:$G$24,6,FALSE)-1,"") -> -0.19229404 | M57: =IFERROR((I57/J57)^(1/(B57-$B$54+1))-1,"") -> 0.051097975
A58: Вклады 100% | B58: ='Исходные данные'!$A8 -> 2008 | C58: =IF(AND(Таблица14[[#This Row],[Год]]>=Настройки!$B$4, Таблица14[[#This Row],[Год]]<=Настройки!$B$5),IFERROR(VLOOKUP(Таблица14[[#This Row],[Год]],Данные[#All],9,FALSE),0),0) -> 173787.02 | D58: =VLOOKUP($A$54,Настройки!$L$2:$N$13,2,FALSE) -> 0 | E58: =VLOOKUP($A$54,Настройки!$L$2:$N$13,3,FALSE) -> 0 | F58: =D58*VLOOKUP(B58,'Исходные данные'!$A$4:$G$24,2,FALSE)+E58*VLOOKUP(B58,'Исходные данные'!$A$4:$G$24,3,FALSE)+(1-D58-E58)*VLOOKUP(B58,'Исходные данные'!$A$4:$G$24,4,FALSE) -> 0.112 | G58: =I57 -> 660793.84 | H58: =(G58+C58)*F58 -> 93473.057 | I58: =G58+C58+H58 -> 928053.92 | J58: =J57+C58 -> 715155.78 | K58: =IFERROR((I58-J58)/J58,"") -> 0.29769477 | L58: =IFERROR((1+K58)/VLOOKUP(B58,'Исходные данные'!$A$4:$G$24,6,FALSE)-1,"") -> -0.24194659 | M58: =IFERROR((I58/J58)^(1/(B58-$B$54+1))-1,"") -> 0.05349993
A59: Вклады 100% | B59: ='Исходные данные'!$A9 -> 2009 | C59: =IF(AND(Таблица14[[#This Row],[Год]]>=Настройки!$B$4, Таблица14[[#This Row],[Год]]<=Настройки!$B$5),IFERROR(VLOOKUP(Таблица14[[#This Row],[Год]],Данные[#All],9,FALSE),0),0) -> 196865.94 | D59: =VLOOKUP($A$54,Настройки!$L$2:$N$13,2,FALSE) -> 0 | E59: =VLOOKUP($A$54,Настройки!$L$2:$N$13,3,FALSE) -> 0 | F59: =D59*VLOOKUP(B59,'Исходные данные'!$A$4:$G$24,2,FALSE)+E59*VLOOKUP(B59,'Исходные данные'!$A$4:$G$24,3,FALSE)+(1-D59-E59)*VLOOKUP(B59,'Исходные данные'!$A$4:$G$24,4,FALSE) -> 0.112 | G59: =I58 -> 928053.92 | H59: =(G59+C59)*F59 -> 125991.03 | I59: =G59+C59+H59 -> 1250910.9 | J59: =J58+C59 -> 912021.73 | K59: =IFERROR((I59-J59)/J59,"") -> 0.37158014 | L59: =IFERROR((1+K59)/VLOOKUP(B59,'Исходные данные'!$A$4:$G$24,6,FALSE)-1,"") -> -0.26359022 | M59: =IFERROR((I59/J59)^(1/(B59-$B$54+1))-1,"") -> 0.054071809
A60: Вклады 100% | B60: ='Исходные данные'!$A10 -> 2010 | C60: =IF(AND(Таблица14[[#This Row],[Год]]>=Настройки!$B$4, Таблица14[[#This Row],[Год]]<=Настройки!$B$5),IFERROR(VLOOKUP(Таблица14[[#This Row],[Год]],Данные[#All],9,FALSE),0),0) -> 214190.14 | D60: =VLOOKUP($A$54,Настройки!$L$2:$N$13,2,FALSE) -> 0 | E60: =VLOOKUP($A$54,Настройки!$L$2:$N$13,3,FALSE) -> 0 | F60: =D60*VLOOKUP(B60,'Исходные данные'!$A$4:$G$24,2,FALSE)+E60*VLOOKUP(B60,'Исходные данные'!$A$4:$G$24,3,FALSE)+(1-D60-E60)*VLOOKUP(B60,'Исходные данные'!$A$4:$G$24,4,FALSE) -> 0.068 | G60: =I59 -> 1250910.9 | H60: =(G60+C60)*F60 -> 99626.87 | I60: =G60+C60+H60 -> 1564727.9 | J60: =J59+C60 -> 1126211.9 | K60: =IFERROR((I60-J60)/J60,"") -> 0.38937259 | L60: =IFERROR((1+K60)/VLOOKUP(B60,'Исходные данные'!$A$4:$G$24,6,FALSE)-1,"") -> -0.31424651 | M60: =IFERROR((I60/J60)^(1/(B60-$B$54+1))-1,"") -> 0.04809989
A61: Вклады 100% | B61: ='Исходные данные'!$A11 -> 2011 | C61: =IF(AND(Таблица14[[#This Row],[Год]]>=Настройки!$B$4, Таблица14[[#This Row],[Год]]<=Настройки!$B$5),IFERROR(VLOOKUP(Таблица14[[#This Row],[Год]],Данные[#All],9,FALSE),0),0) -> 232996.04 | D61: =VLOOKUP($A$54,Настройки!$L$2:$N$13,2,FALSE) -> 0 | E61: =VLOOKUP($A$54,Настройки!$L$2:$N$13,3,FALSE) -> 0 | F61: =D61*VLOOKUP(B61,'Исходные данные'!$A$4:$G$24,2,FALSE)+E61*VLOOKUP(B61,'Исходные данные'!$A$4:$G$24,3,FALSE)+(1-D61-E61)*VLOOKUP(B61,'Исходные данные'!$A$4:$G$24,4,FALSE) -> 0.078 | G61: =I60 -> 1564727.9 | H61: =(G61+C61)*F61 -> 140222.47 | I61: =G61+C61+H61 -> 1937946.4 | J61: =J60+C61 -> 1359207.9 | K61: =IFERROR((I61-J61)/J61,"") -> 0.42579101 | L61: =IFERROR((1+K61)/VLOOKUP(B61,'Исходные данные'!$A$4:$G$24,6,FALSE)-1,"") -> -0.33673086 | M61: =IFERROR((I61/J61)^(1/(B61-$B$54+1))-1,"") -> 0.045338591
A62: Вклады 100% | B62: ='Исходные данные'!$A12 -> 2012 | C62: =IF(AND(Таблица14[[#This Row],[Год]]>=Настройки!$B$4, Таблица14[[#This Row],[Год]]<=Настройки!$B$5),IFERROR(VLOOKUP(Таблица14[[#This Row],[Год]],Данные[#All],9,FALSE),0),0) -> 247208.8 | D62: =VLOOKUP($A$54,Настройки!$L$2:$N$13,2,FALSE) -> 0 | E62: =VLOOKUP($A$54,Настройки!$L$2:$N$13,3,FALSE) -> 0 | F62: =D62*VLOOKUP(B62,'Исходные данные'!$A$4:$G$24,2,FALSE)+E62*VLOOKUP(B62,'Исходные данные'!$A$4:$G$24,3,FALSE)+(1-D62-E62)*VLOOKUP(B62,'Исходные данные'!$A$4:$G$24,4,FALSE) -> 0.084 | G62: =I61 -> 1937946.4 | H62: =(G62+C62)*F62 -> 183553.04 | I62: =G62+C62+H62 -> 2368708.2 | J62: =J61+C62 -> 1606416.7 | K62: =IFERROR((I62-J62)/J62,"") -> 0.47452914 | L62: =IFERROR((1+K62)/VLOOKUP(B62,'Исходные данные'!$A$4:$G$24,6,FALSE)-1,"") -> -0.35640663 | M62: =IFERROR((I62/J62)^(1/(B62-$B$54+1))-1,"") -> 0.044093188
A63: Вклады 100% | B63: ='Исходные данные'!$A13 -> 2013 | C63: =IF(AND(Таблица14[[#This Row],[Год]]>=Настройки!$B$4, Таблица14[[#This Row],[Год]]<=Настройки!$B$5),IFERROR(VLOOKUP(Таблица14[[#This Row],[Год]],Данные[#All],9,FALSE),0),0) -> 263475.14 | D63: =VLOOKUP($A$54,Настройки!$L$2:$N$13,2,FALSE) -> 0 | E63: =VLOOKUP($A$54,Настройки!$L$2:$N$13,3,FALSE) -> 0 | F63: =D63*VLOOKUP(B63,'Исходные данные'!$A$4:$G$24,2,FALSE)+E63*VLOOKUP(B63,'Исходные данные'!$A$4:$G$24,3,FALSE)+(1-D63-E63)*VLOOKUP(B63,'Исходные данные'!$A$4:$G$24,4,FALSE) -> 0.074 | G63: =I62 -> 2368708.2 | H63: =(G63+C63)*F63 -> 194781.57 | I63: =G63+C63+H63 -> 2826965 | J63: =J62+C63 -> 1869891.8 | K63: =IFERROR((I63-J63)/J63,"") -> 0.51183341 | L63: =IFERROR((1+K63)/VLOOKUP(B63,'Исходные данные'!$A$4:$G$24,6,FALSE)-1,"") -> -0.38010737 | M63: =IFERROR((I63/J63)^(1/(B63-$B$54+1))-1,"") -> 0.04219838
A64: Вклады 100% | B64: ='Исходные данные'!$A14 -> 2014 | C64: =IF(AND(Таблица14[[#This Row],[Год]]>=Настройки!$B$4, Таблица14[[#This Row],[Год]]<=Настройки!$B$5),IFERROR(VLOOKUP(Таблица14[[#This Row],[Год]],Данные[#All],9,FALSE),0),0) -> 280469.28 | D64: =VLOOKUP($A$54,Настройки!$L$2:$N$13,2,FALSE) -> 0 | E64: =VLOOKUP($A$54,Настройки!$L$2:$N$13,3,FALSE) -> 0 | F64: =D64*VLOOKUP(B64,'Исходные данные'!$A$4:$G$24,2,FALSE)+E64*VLOOKUP(B64,'Исходные данные'!$A$4:$G$24,3,FALSE)+(1-D64-E64)*VLOOKUP(B64,'Исходные данные'!$A$4:$G$24,4,FALSE) -> 0.081 | G64: =I63 -> 2826965 | H64: =(G64+C64)*F64 -> 251702.17 | I64: =G64+C64+H64 -> 3359136.4 | J64: =J63+C64 -> 2150361.1 | K64: =IFERROR((I64-J64)/J64,"") -> 0.56212664 | L64: =IFERROR((1+K64)/VLOOKUP(B64,'Исходные данные'!$A$4:$G$24,6,FALSE)-1,"") -> -0.42482559 | M64: =IFERROR((I64/J64)^(1/(B64-$B$54+1))-1,"") -> 0.0413832
A65: Вклады 100% | B65: ='Исходные данные'!$A15 -> 2015 | C65: =IF(AND(Таблица14[[#This Row],[Год]]>=Настройки!$B$4, Таблица14[[#This Row],[Год]]<=Настройки!$B$5),IFERROR(VLOOKUP(Таблица14[[#This Row],[Год]],Данные[#All],9,FALSE),0),0) -> 312330.59 | D65: =VLOOKUP($A$54,Настройки!$L$2:$N$13,2,FALSE) -> 0 | E65: =VLOOKUP($A$54,Настройки!$L$2:$N$13,3,FALSE) -> 0 | F65: =D65*VLOOKUP(B65,'Исходные данные'!$A$4:$G$24,2,FALSE)+E65*VLOOKUP(B65,'Исходные данные'!$A$4:$G$24,3,FALSE)+(1-D65-E65)*VLOOKUP(B65,'Исходные данные'!$A$4:$G$24,4,FALSE) -> 0.101 | G65: =I64 -> 3359136.4 | H65: =(G65+C65)*F65 -> 370818.17 | I65: =G65+C65+H65 -> 4042285.2 | J65: =J64+C65 -> 2462691.7 | K65: =IFERROR((I65-J65)/J65,"") -> 0.64140933 | L65: =IFERROR((1+K65)/VLOOKUP(B65,'Исходные данные'!$A$4:$G$24,6,FALSE)-1,"") -> -0.46473628 | M65: =IFERROR((I65/J65)^(1/(B65-$B$54+1))-1,"") -> 0.042160819
A66: Вклады 100% | B66: ='Исходные данные'!$A16 -> 2016 | C66: =IF(AND(Таблица14[[#This Row],[Год]]>=Настройки!$B$4, Таблица14[[#This Row],[Год]]<=Настройки!$B$5),IFERROR(VLOOKUP(Таблица14[[#This Row],[Год]],Данные[#All],9,FALSE),0),0) -> 352652.47 | D66: =VLOOKUP($A$54,Настройки!$L$2:$N$13,2,FALSE) -> 0 | E66: =VLOOKUP($A$54,Настройки!$L$2:$N$13,3,FALSE) -> 0 | F66: =D66*VLOOKUP(B66,'Исходные данные'!$A$4:$G$24,2,FALSE)+E66*VLOOKUP(B66,'Исходные данные'!$A$4:$G$24,3,FALSE)+(1-D66-E66)*VLOOKUP(B66,'Исходные данные'!$A$4:$G$24,4,FALSE) -> 0.084 | G66: =I65 -> 4042285.2 | H66: =(G66+C66)*F66 -> 369174.76 | I66: =G66+C66+H66 -> 4764112.4 | J66: =J65+C66 -> 2815344.2 | K66: =IFERROR((I66-J66)/J66,"") -> 0.69219537 | L66: =IFERROR((1+K66)/VLOOKUP(B66,'Исходные данные'!$A$4:$G$24,6,FALSE)-1,"") -> -0.47634746 | M66: =IFERROR((I66/J66)^(1/(B66-$B$54+1))-1,"") -> 0.0412934
... A74: Вклады 100% | B74: ='Исходные данные'!$A24 -> 2024 | C74: =IF(AND(Таблица14[[#This Row],[Год]]>=Настройки!$B$4, Таблица14[[#This Row],[Год]]<=Настройки!$B$5),IFERROR(VLOOKUP(Таблица14[[#This Row],[Год]],Данные[#All],9,FALSE),0),0) -> 559754.57 | D74: =VLOOKUP($A$54,Настройки!$L$2:$N$13,2,FALSE) -> 0 | E74: =VLOOKUP($A$54,Настройки!$L$2:$N$13,3,FALSE) -> 0 | F74: =D74*VLOOKUP(B74,'Исходные данные'!$A$4:$G$24,2,FALSE)+E74*VLOOKUP(B74,'Исходные данные'!$A$4:$G$24,3,FALSE)+(1-D74-E74)*VLOOKUP(B74,'Исходные данные'!$A$4:$G$24,4,FALSE) -> 0.153 | G74: =I73 -> 11463790 | H74: =(G74+C74)*F74 -> 1839602.3 | I74: =G74+C74+H74 -> 13863147 | J74: =J73+C74 -> 6350420.1 | K74: =IFERROR((I74-J74)/J74,"") -> 1.1830283 | L74: =IFERROR((1+K74)/VLOOKUP(B74,'Исходные данные'!$A$4:$G$24,6,FALSE)-1,"") -> -0.59048848 | M74: =IFERROR((I74/J74)^(1/(B74-$B$54+1))-1,"") -> 0.037876513
A77: Стратегия | B77: Год | C77: Взнос | D77: Доля Акций | E77: Доля Облигаций | F77: Доходность стратегии за год | G77: Портфель на НАЧАЛО года | H77: Доход | I77: Итоговый портфель, ₽ | J77: Вложено всего, ₽ | K77: Номинальная доходность | L77: Реальная доходность, % | M77: Среднегодовой рост
A78: А50%/О50% | B78: ='Исходные данные'!$A4 -> 2004 | C78: =IF(AND(Таблица13[[#This Row],[Год]]>=Настройки!$B$4, Таблица13[[#This Row],[Год]]<=Настройки!$B$5),IFERROR(VLOOKUP(Таблица13[[#This Row],[Год]],Данные[#All],9,FALSE),0),0) -> 115000 | D78: =VLOOKUP($A$78,Настройки!$L$2:$N$13,2,FALSE) -> 0.5 | E78: =VLOOKUP($A$78,Настройки!$L$2:$N$13,3,FALSE) -> 0.5 | F78: =D78*VLOOKUP(B78,'Исходные данные'!$A$4:$G$24,2,FALSE)+E78*VLOOKUP(B78,'Исходные данные'!$A$4:$G$24,3,FALSE)+(1-D78-E78)*VLOOKUP(B78,'Исходные данные'!$A$4:$G$24,4,FALSE) -> 0.090888789 | G78: =0 -> 0 | H78: =(G78+C78)*F78 -> 10452.211 | I78: =G78+C78+H78 -> 125452.21 | J78: =C78 -> 115000 | K78: =IFERROR((I78-J78)/J78,"") -> 0.090888789 | L78: =IFERROR((1+K78)/VLOOKUP(B78,'Исходные данные'!$A$4:$G$24,6,FALSE)-1,"") -> -0.023725802 | M78: =IFERROR((I78/J78)^(1/(B78-$B$78+1))-1,"") -> 0.090888789
A79: А50%/О50% | B79: ='Исходные данные'!$A5 -> 2005 | C79: =IF(AND(Таблица13[[#This Row],[Год]]>=Настройки!$B$4, Таблица13[[#This Row],[Год]]<=Настройки!$B$5),IFERROR(VLOOKUP(Таблица13[[#This Row],[Год]],Данные[#All],9,FALSE),0),0) -> 128501 | D79: =VLOOKUP($A$78,Настройки!$L$2:$N$13,2,FALSE) -> 0.5 | E79: =VLOOKUP($A$78,Настройки!$L$2:$N$13,3,FALSE) -> 0.5 | F79: =D79*VLOOKUP(B79,'Исходные данные'!$A$4:$G$24,2,FALSE)+E79*VLOOKUP(B79,'Исходные данные'!$A$4:$G$24,3,FALSE)+(1-D79-E79)*VLOOKUP(B79,'Исходные данные'!$A$4:$G$24,4,FALSE) -> 0.48257987 | G79: =I78 -> 125452.21 | H79: =(G79+C79)*F79 -> 122552.71 | I79: =G79+C79+H79 -> 376505.92 | J79: =J78+C79 -> 243501 | K79: =IFERROR((I79-J79)/J79,"") -> 0.54621918 | L79: =IFERROR((1+K79)/VLOOKUP(B79,'Исходные данные'!$A$4:$G$24,6,FALSE)-1,"") -> 0.24764688 | M79: =IFERROR((I79/J79)^(1/(B79-$B$78+1))-1,"") -> 0.24347062
A80: А50%/О50% | B80: ='Исходные данные'!$A6 -> 2006 | C80: =IF(AND(Таблица13[[#This Row],[Год]]>=Настройки!$B$4, Таблица13[[#This Row],[Год]]<=Настройки!$B$5),IFERROR(VLOOKUP(Таблица13[[#This Row],[Год]],Данные[#All],9,FALSE),0),0) -> 142520.46 | D80: =VLOOKUP($A$78,Настройки!$L$2:$N$13,2,FALSE) -> 0.5 | E80: =VLOOKUP($A$78,Настройки!$L$2:$N$13,3,FALSE) -> 0.5 | F80: =D80*VLOOKUP(B80,'Исходные данные'!$A$4:$G$24,2,FALSE)+E80*VLOOKUP(B80,'Исходные данные'!$A$4:$G$24,3,FALSE)+(1-D80-E80)*VLOOKUP(B80,'Исходные данные'!$A$4:$G$24,4,FALSE) -> 0.38334609 | G80: =I79 -> 376505.92 | H80: =(G80+C80)*F80 -> 198966.73 | I80: =G80+C80+H80 -> 717993.11 | J80: =J79+C80 -> 386021.46 | K80: =IFERROR((I80-J80)/J80,"") -> 0.85998238 | L80: =IFERROR((1+K80)/VLOOKUP(B80,'Исходные данные'!$A$4:$G$24,6,FALSE)-1,"") -> 0.37690177 | M80: =IFERROR((I80/J80)^(1/(B80-$B$78+1))-1,"") -> 0.22980506
A81: А50%/О50% | B81: ='Исходные данные'!$A7 -> 2007 | C81: =IF(AND(Таблица13[[#This Row],[Год]]>=Настройки!$B$4, Таблица13[[#This Row],[Год]]<=Настройки!$B$5),IFERROR(VLOOKUP(Таблица13[[#This Row],[Год]],Данные[#All],9,FALSE),0),0) -> 155347.3 | D81: =VLOOKUP($A$78,Настройки!$L$2:$N$13,2,FALSE) -> 0.5 | E81: =VLOOKUP($A$78,Настройки!$L$2:$N$13,3,FALSE) -> 0.5 | F81: =D81*VLOOKUP(B81,'Исходные данные'!$A$4:$G$24,2,FALSE)+E81*VLOOKUP(B81,'Исходные данные'!$A$4:$G$24,3,FALSE)+(1-D81-E81)*VLOOKUP(B81,'Исходные данные'!$A$4:$G$24,4,FALSE) -> 0.10026971 | G81: =I80 -> 717993.11 | H81: =(G81+C81)*F81 -> 87569.592 | I81: =G81+C81+H81 -> 960910 | J81: =J80+C81 -> 541368.76 | K81: =IFERROR((I81-J81)/J81,"") -> 0.7749639 | L81: =IFERROR((1+K81)/VLOOKUP(B81,'Исходные данные'!$A$4:$G$24,6,FALSE)-1,"") -> 0.17454596 | M81: =IFERROR((I81/J81)^(1/(B81-$B$78+1))-1,"") -> 0.15424335
A82: А50%/О50% | B82: ='Исходные данные'!$A8 -> 2008 | C82: =IF(AND(Таблица13[[#This Row],[Год]]>=Настройки!$B$4, Таблица13[[#This Row],[Год]]<=Настройки!$B$5),IFERROR(VLOOKUP(Таблица13[[#This Row],[Год]],Данные[#All],9,FALSE),0),0) -> 173787.02 | D82: =VLOOKUP($A$78,Настройки!$L$2:$N$13,2,FALSE) -> 0.5 | E82: =VLOOKUP($A$78,Настройки!$L$2:$N$13,3,FALSE) -> 0.5 | F82: =D82*VLOOKUP(B82,'Исходные данные'!$A$4:$G$24,2,FALSE)+E82*VLOOKUP(B82,'Исходные данные'!$A$4:$G$24,3,FALSE)+(1-D82-E82)*VLOOKUP(B82,'Исходные данные'!$A$4:$G$24,4,FALSE) -> -0.3608109 | G82: =I81 -> 960910 | H82: =(G82+C82)*F82 -> -409411.05 | I82: =G82+C82+H82 -> 725285.97 | J82: =J81+C82 -> 715155.78 | K82: =IFERROR((I82-J82)/J82,"") -> 0.014165012 | L82: =IFERROR((1+K82)/VLOOKUP(B82,'Исходные данные'!$A$4:$G$24,6,FALSE)-1,"") -> -0.40757159 | M82: =IFERROR((I82/J82)^(1/(B82-$B$78+1))-1,"") -> 0.0028170856
A83: А50%/О50% | B83: ='Исходные данные'!$A9 -> 2009 | C83: =IF(AND(Таблица13[[#This Row],[Год]]>=Настройки!$B$4, Таблица13[[#This Row],[Год]]<=Настройки!$B$5),IFERROR(VLOOKUP(Таблица13[[#This Row],[Год]],Данные[#All],9,FALSE),0),0) -> 196865.94 | D83: =VLOOKUP($A$78,Настройки!$L$2:$N$13,2,FALSE) -> 0.5 | E83: =VLOOKUP($A$78,Настройки!$L$2:$N$13,3,FALSE) -> 0.5 | F83: =D83*VLOOKUP(B83,'Исходные данные'!$A$4:$G$24,2,FALSE)+E83*VLOOKUP(B83,'Исходные данные'!$A$4:$G$24,3,FALSE)+(1-D83-E83)*VLOOKUP(B83,'Исходные данные'!$A$4:$G$24,4,FALSE) -> 0.80718596 | G83: =I82 -> 725285.97 | H83: =(G83+C83)*F83 -> 744348.08 | I83: =G83+C83+H83 -> 1666500 | J83: =J82+C83 -> 912021.73 | K83: =IFERROR((I83-J83)/J83,"") -> 0.8272591 | L83: =IFERROR((1+K83)/VLOOKUP(B83,'Исходные данные'!$A$4:$G$24,6,FALSE)-1,"") -> -0.018933402 | M83: =IFERROR((I83/J83)^(1/(B83-$B$78+1))-1,"") -> 0.10568993
A84: А50%/О50% | B84: ='Исходные данные'!$A10 -> 2010 | C84: =IF(AND(Таблица13[[#This Row],[Год]]>=Настройки!$B$4, Таблица13[[#This Row],[Год]]<=Настройки!$B$5),IFERROR(VLOOKUP(Таблица13[[#This Row],[Год]],Данные[#All],9,FALSE),0),0) -> 214190.14 | D84: =VLOOKUP($A$78,Настройки!$L$2:$N$13,2,FALSE) -> 0.5 | E84: =VLOOKUP($A$78,Настройки!$L$2:$N$13,3,FALSE) -> 0.5 | F84: =D84*VLOOKUP(B84,'Исходные данные'!$A$4:$G$24,2,FALSE)+E84*VLOOKUP(B84,'Исходные данные'!$A$4:$G$24,3,FALSE)+(1-D84-E84)*VLOOKUP(B84,'Исходные данные'!$A$4:$G$24,4,FALSE) -> 0.18216101 | G84: =I83 -> 1666500 | H84: =(G84+C84)*F84 -> 342588.42 | I84: =G84+C84+H84 -> 2223278.6 | J84: =J83+C84 -> 1126211.9 | K84: =IFERROR((I84-J84)/J84,"") -> 0.97412106 | L84: =IFERROR((1+K84)/VLOOKUP(B84,'Исходные данные'!$A$4:$G$24,6,FALSE)-1,"") -> -0.025631843 | M84: =IFERROR((I84/J84)^(1/(B84-$B$78+1))-1,"") -> 0.1020372
A85: А50%/О50% | B85: ='Исходные данные'!$A11 -> 2011 | C85: =IF(AND(Таблица13[[#This Row],[Год]]>=Настройки!$B$4, Таблица13[[#This Row],[Год]]<=Настройки!$B$5),IFERROR(VLOOKUP(Таблица13[[#This Row],[Год]],Данные[#All],9,FALSE),0),0) -> 232996.04 | D85: =VLOOKUP($A$78,Настройки!$L$2:$N$13,2,FALSE) -> 0.5 | E85: =VLOOKUP($A$78,Настройки!$L$2:$N$13,3,FALSE) -> 0.5 | F85: =D85*VLOOKUP(B85,'Исходные данные'!$A$4:$G$24,2,FALSE)+E85*VLOOKUP(B85,'Исходные данные'!$A$4:$G$24,3,FALSE)+(1-D85-E85)*VLOOKUP(B85,'Исходные данные'!$A$4:$G$24,4,FALSE) -> -0.043305113 | G85: =I84 -> 2223278.6 | H85: =(G85+C85)*F85 -> -106369.25 | I85: =G85+C85+H85 -> 2349905.4 | J85: =J84+C85 -> 1359207.9 | K85: =IFERROR((I85-J85)/J85,"") -> 0.72887852 | L85: =IFERROR((1+K85)/VLOOKUP(B85,'Исходные данные'!$A$4:$G$24,6,FALSE)-1,"") -> -0.19573643 | M85: =IFERROR((I85/J85)^(1/(B85-$B$78+1))-1,"") -> 0.070830074
A86: А50%/О50% | B86: ='Исходные данные'!$A12 -> 2012 | C86: =IF(AND(Таблица13[[#This Row],[Год]]>=Настройки!$B$4, Таблица13[[#This Row],[Год]]<=Настройки!$B$5),IFERROR(VLOOKUP(Таблица13[[#This Row],[Год]],Данные[#All],9,FALSE),0),0) -> 247208.8 | D86: =VLOOKUP($A$78,Настройки!$L$2:$N$13,2,FALSE) -> 0.5 | E86: =VLOOKUP($A$78,Настройки!$L$2:$N$13,3,FALSE) -> 0.5 | F86: =D86*VLOOKUP(B86,'Исходные данные'!$A$4:$G$24,2,FALSE)+E86*VLOOKUP(B86,'Исходные данные'!$A$4:$G$24,3,FALSE)+(1-D86-E86)*VLOOKUP(B86,'Исходные данные'!$A$4:$G$24,4,FALSE) -> 0.1170735 | G86: =I85 -> 2349905.4 | H86: =(G86+C86)*F86 -> 304053.25 | I86: =G86+C86+H86 -> 2901167.4 | J86: =J85+C86 -> 1606416.7 | K86: =IFERROR((I86-J86)/J86,"") -> 0.80598682 | L86: =IFERROR((1+K86)/VLOOKUP(B86,'Исходные данные'!$A$4:$G$24,6,FALSE)-1,"") -> -0.21173403 | M86: =IFERROR((I86/J86)^(1/(B86-$B$78+1))-1,"") -> 0.067883416
A87: А50%/О50% | B87: ='Исходные данные'!$A13 -> 2013 | C87: =IF(AND(Таблица13[[#This Row],[Год]]>=Настройки!$B$4, Таблица13[[#This Row],[Год]]<=Настройки!$B$5),IFERROR(VLOOKUP(Таблица13[[#This Row],[Год]],Данные[#All],9,FALSE),0),0) -> 263475.14 | D87: =VLOOKUP($A$78,Настройки!$L$2:$N$13,2,FALSE) -> 0.5 | E87: =VLOOKUP($A$78,Настройки!$L$2:$N$13,3,FALSE) -> 0.5 | F87: =D87*VLOOKUP(B87,'Исходные данные'!$A$4:$G$24,2,FALSE)+E87*VLOOKUP(B87,'Исходные данные'!$A$4:$G$24,3,FALSE)+(1-D87-E87)*VLOOKUP(B87,'Исходные данные'!$A$4:$G$24,4,FALSE) -> 0.050585098 | G87: =I86 -> 2901167.4 | H87: =(G87+C87)*F87 -> 160083.75 | I87: =G87+C87+H87 -> 3324726.3 | J87: =J86+C87 -> 1869891.8 | K87: =IFERROR((I87-J87)/J87,"") -> 0.77803134 | L87: =IFERROR((1+K87)/VLOOKUP(B87,'Исходные данные'!$A$4:$G$24,6,FALSE)-1,"") -> -0.27095901 | M87: =IFERROR((I87/J87)^(1/(B87-$B$78+1))-1,"") -> 0.059238947
A88: А50%/О50% | B88: ='Исходные данные'!$A14 -> 2014 | C88: =IF(AND(Таблица13[[#This Row],[Год]]>=Настройки!$B$4, Таблица13[[#This Row],[Год]]<=Настройки!$B$5),IFERROR(VLOOKUP(Таблица13[[#This Row],[Год]],Данные[#All],9,FALSE),0),0) -> 280469.28 | D88: =VLOOKUP($A$78,Настройки!$L$2:$N$13,2,FALSE) -> 0.5 | E88: =VLOOKUP($A$78,Настройки!$L$2:$N$13,3,FALSE) -> 0.5 | F88: =D88*VLOOKUP(B88,'Исходные данные'!$A$4:$G$24,2,FALSE)+E88*VLOOKUP(B88,'Исходные данные'!$A$4:$G$24,3,FALSE)+(1-D88-E88)*VLOOKUP(B88,'Исходные данные'!$A$4:$G$24,4,FALSE) -> -0.080997486 | G88: =I87 -> 3324726.3 | H88: =(G88+C88)*F88 -> -292011.78 | I88: =G88+C88+H88 -> 3313183.8 | J88: =J87+C88 -> 2150361.1 | K88: =IFERROR((I88-J88)/J88,"") -> 0.54075693 | L88: =IFERROR((1+K88)/VLOOKUP(B88,'Исходные данные'!$A$4:$G$24,6,FALSE)-1,"") -> -0.43269391 | M88: =IFERROR((I88/J88)^(1/(B88-$B$78+1))-1,"") -> 0.040079985
A89: А50%/О50% | B89: ='Исходные данные'!$A15 -> 2015 | C89: =IF(AND(Таблица13[[#This Row],[Год]]>=Настройки!$B$4, Таблица13[[#This Row],[Год]]<=Настройки!$B$5),IFERROR(VLOOKUP(Таблица13[[#This Row],[Год]],Данные[#All],9,FALSE),0),0) -> 312330.59 | D89: =VLOOKUP($A$78,Настройки!$L$2:$N$13,2,FALSE) -> 0.5 | E89: =VLOOKUP($A$78,Настройки!$L$2:$N$13,3,FALSE) -> 0.5 | F89: =D89*VLOOKUP(B89,'Исходные данные'!$A$4:$G$24,2,FALSE)+E89*VLOOKUP(B89,'Исходные данные'!$A$4:$G$24,3,FALSE)+(1-D89-E89)*VLOOKUP(B89,'Исходные данные'!$A$4:$G$24,4,FALSE) -> 0.3091537 | G89: =I88 -> 3313183.8 | H89: =(G89+C89)*F89 -> 1120841.2 | I89: =G89+C89+H89 -> 4746355.6 | J89: =J88+C89 -> 2462691.7 | K89: =IFERROR((I89-J89)/J89,"") -> 0.92730399 | L89: =IFERROR((1+K89)/VLOOKUP(B89,'Исходные данные'!$A$4:$G$24,6,FALSE)-1,"") -> -0.37150601 | M89: =IFERROR((I89/J89)^(1/(B89-$B$78+1))-1,"") -> 0.056199243
A90: А50%/О50% | B90: ='Исходные данные'!$A16 -> 2016 | C90: =IF(AND(Таблица13[[#This Row],[Год]]>=Настройки!$B$4, Таблица13[[#This Row],[Год]]<=Настройки!$B$5),IFERROR(VLOOKUP(Таблица13[[#This Row],[Год]],Данные[#All],9,FALSE),0),0) -> 352652.47 | D90: =VLOOKUP($A$78,Настройки!$L$2:$N$13,2,FALSE) -> 0.5 | E90: =VLOOKUP($A$78,Настройки!$L$2:$N$13,3,FALSE) -> 0.5 | F90: =D90*VLOOKUP(B90,'Исходные данные'!$A$4:$G$24,2,FALSE)+E90*VLOOKUP(B90,'Исходные данные'!$A$4:$G$24,3,FALSE)+(1-D90-E90)*VLOOKUP(B90,'Исходные данные'!$A$4:$G$24,4,FALSE) -> 0.23829293 | G90: =I89 -> 4746355.6 | H90: =(G90+C90)*F90 -> 1215057.6 | I90: =G90+C90+H90 -> 6314065.6 | J90: =J89+C90 -> 2815344.2 | K90: =IFERROR((I90-J90)/J90,"") -> 1.2427331 | L90: =IFERROR((1+K90)/VLOOKUP(B90,'Исходные данные'!$A$4:$G$24,6,FALSE)-1,"") -> -0.30598268 | M90: =IFERROR((I90/J90)^(1/(B90-$B$78+1))-1,"") -> 0.064101099
... A98: А50%/О50% | B98: ='Исходные данные'!$A24 -> 2024 | C98: =IF(AND(Таблица13[[#This Row],[Год]]>=Настройки!$B$4, Таблица13[[#This Row],[Год]]<=Настройки!$B$5),IFERROR(VLOOKUP(Таблица13[[#This Row],[Год]],Данные[#All],9,FALSE),0),0) -> 559754.57 | D98: =VLOOKUP($A$78,Настройки!$L$2:$N$13,2,FALSE) -> 0.5 | E98: =VLOOKUP($A$78,Настройки!$L$2:$N$13,3,FALSE) -> 0.5 | F98: =D98*VLOOKUP(B98,'Исходные данные'!$A$4:$G$24,2,FALSE)+E98*VLOOKUP(B98,'Исходные данные'!$A$4:$G$24,3,FALSE)+(1-D98-E98)*VLOOKUP(B98,'Исходные данные'!$A$4:$G$24,4,FALSE) -> -0.035093436 | G98: =I97 -> 16564500 | H98: =(G98+C98)*F98 -> -600948.91 | I98: =G98+C98+H98 -> 16523305 | J98: =J97+C98 -> 6350420.1 | K98: =IFERROR((I98-J98)/J98,"") -> 1.6019232 | L98: =IFERROR((1+K98)/VLOOKUP(B98,'Исходные данные'!$A$4:$G$24,6,FALSE)-1,"") -> -0.51190852 | M98: =IFERROR((I98/J98)^(1/(B98-$B$78+1))-1,"") -> 0.046588424
A101: Стратегия | B101: Год | C101: Взнос | D101: Доля Акций | E101: Доля Облигаций | F101: Доходность стратегии за год | G101: Портфель на НАЧАЛО года | H101: Доход | I101: Итоговый портфель, ₽ | J101: Вложено всего, ₽ | K101: Номинальная доходность | L101: Реальная доходность, % | M101: Среднегодовой рост
A102: А10%/О90% | B102: ='Исходные данные'!$A4 -> 2004 | C102: =IF(AND(Таблица12[[#This Row],[Год]]>=Настройки!$B$4, Таблица12[[#This Row],[Год]]<=Настройки!$B$5),IFERROR(VLOOKUP(Таблица12[[#This Row],[Год]],Данные[#All],9,FALSE),0),0) -> 115000 | D102: =VLOOKUP($A$102,Настройки!$L$2:$N$13,2,FALSE) -> 0.1 | E102: =VLOOKUP($A$102,Настройки!$L$2:$N$13,3,FALSE) -> 0.9 | F102: =D102*VLOOKUP(B102,'Исходные данные'!$A$4:$G$24,2,FALSE)+E102*VLOOKUP(B102,'Исходные данные'!$A$4:$G$24,3,FALSE)+(1-D102-E102)*VLOOKUP(B102,'Исходные данные'!$A$4:$G$24,4,FALSE) -> 0.10529903 | G102: =0 -> 0 | H102: =(G102+C102)*F102 -> 12109.388 | I102: =G102+C102+H102 -> 127109.39 | J102: =C102 -> 115000 | K102: =IFERROR((I102-J102)/J102,"") -> 0.10529903 | L102: =IFERROR((1+K102)/VLOOKUP(B102,'Исходные данные'!$A$4:$G$24,6,FALSE)-1,"") -> -0.010829578 | M102: =IFERROR((I102/J102)^(1/(B102-$B$102+1))-1,"") -> 0.10529903
A103: А10%/О90% | B103: ='Исходные данные'!$A5 -> 2005 | C103: =IF(AND(Таблица12[[#This Row],[Год]]>=Настройки!$B$4, Таблица12[[#This Row],[Год]]<=Настройки!$B$5),IFERROR(VLOOKUP(Таблица12[[#This Row],[Год]],Данные[#All],9,FALSE),0),0) -> 128501 | D103: =VLOOKUP($A$102,Настройки!$L$2:$N$13,2,FALSE) -> 0.1 | E103: =VLOOKUP($A$102,Настройки!$L$2:$N$13,3,FALSE) -> 0.9 | F103: =D103*VLOOKUP(B103,'Исходные данные'!$A$4:$G$24,2,FALSE)+E103*VLOOKUP(B103,'Исходные данные'!$A$4:$G$24,3,FALSE)+(1-D103-E103)*VLOOKUP(B103,'Исходные данные'!$A$4:$G$24,4,FALSE) -> 0.18965351 | G103: =I102 -> 127109.39 | H103: =(G103+C103)*F103 -> 48477.406 | I103: =G103+C103+H103 -> 304087.79 | J103: =J102+C103 -> 243501 | K103: =IFERROR((I103-J103)/J103,"") -> 0.24881538 | L103: =IFERROR((1+K103)/VLOOKUP(B103,'Исходные данные'!$A$4:$G$24,6,FALSE)-1,"") -> 0.007671249 | M103: =IFERROR((I103/J103)^(1/(B103-$B$102+1))-1,"") -> 0.11750409
A104: А10%/О90% | B104: ='Исходные данные'!$A6 -> 2006 | C104: =IF(AND(Таблица12[[#This Row],[Год]]>=Настройки!$B$4, Таблица12[[#This Row],[Год]]<=Настройки!$B$5),IFERROR(VLOOKUP(Таблица12[[#This Row],[Год]],Данные[#All],9,FALSE),0),0) -> 142520.46 | D104: =VLOOKUP($A$102,Настройки!$L$2:$N$13,2,FALSE) -> 0.1 | E104: =VLOOKUP($A$102,Настройки!$L$2:$N$13,3,FALSE) -> 0.9 | F104: =D104*VLOOKUP(B104,'Исходные данные'!$A$4:$G$24,2,FALSE)+E104*VLOOKUP(B104,'Исходные данные'!$A$4:$G$24,3,FALSE)+(1-D104-E104)*VLOOKUP(B104,'Исходные данные'!$A$4:$G$24,4,FALSE) -> 0.13161135 | G104: =I103 -> 304087.79 | H104: =(G104+C104)*F104 -> 58778.717 | I104: =G104+C104+H104 -> 505386.97 | J104: =J103+C104 -> 386021.46 | K104: =IFERROR((I104-J104)/J104,"") -> 0.30921989 | L104: =IFERROR((1+K104)/VLOOKUP(B104,'Исходные данные'!$A$4:$G$24,6,FALSE)-1,"") -> -0.030814912 | M104: =IFERROR((I104/J104)^(1/(B104-$B$102+1))-1,"") -> 0.09396694
A105: А10%/О90% | B105: ='Исходные данные'!$A7 -> 2007 | C105: =IF(AND(Таблица12[[#This Row],[Год]]>=Настройки!$B$4, Таблица12[[#This Row],[Год]]<=Настройки!$B$5),IFERROR(VLOOKUP(Таблица12[[#This Row],[Год]],Данные[#All],9,FALSE),0),0) -> 155347.3 | D105: =VLOOKUP($A$102,Настройки!$L$2:$N$13,2,FALSE) -> 0.1 | E105: =VLOOKUP($A$102,Настройки!$L$2:$N$13,3,FALSE) -> 0.9 | F105: =D105*VLOOKUP(B105,'Исходные данные'!$A$4:$G$24,2,FALSE)+E105*VLOOKUP(B105,'Исходные данные'!$A$4:$G$24,3,FALSE)+(1-D105-E105)*VLOOKUP(B105,'Исходные данные'!$A$4:$G$24,4,FALSE) -> 0.079276382 | G105: =I104 -> 505386.97 | H105: =(G105+C105)*F105 -> 52380.622 | I105: =G105+C105+H105 -> 713114.89 | J105: =J104+C105 -> 541368.76 | K105: =IFERROR((I105-J105)/J105,"") -> 0.31724426 | L105: =IFERROR((1+K105)/VLOOKUP(B105,'Исходные данные'!$A$4:$G$24,6,FALSE)-1,"") -> -0.12834062 | M105: =IFERROR((I105/J105)^(1/(B105-$B$102+1))-1,"") -> 0.071313504
A106: А10%/О90% | B106: ='Исходные данные'!$A8 -> 2008 | C106: =IF(AND(Таблица12[[#This Row],[Год]]>=Настройки!$B$4, Таблица12[[#This Row],[Год]]<=Настройки!$B$5),IFERROR(VLOOKUP(Таблица12[[#This Row],[Год]],Данные[#All],9,FALSE),0),0) -> 173787.02 | D106: =VLOOKUP($A$102,Настройки!$L$2:$N$13,2,FALSE) -> 0.1 | E106: =VLOOKUP($A$102,Настройки!$L$2:$N$13,3,FALSE) -> 0.9 | F106: =D106*VLOOKUP(B106,'Исходные данные'!$A$4:$G$24,2,FALSE)+E106*VLOOKUP(B106,'Исходные данные'!$A$4:$G$24,3,FALSE)+(1-D106-E106)*VLOOKUP(B106,'Исходные данные'!$A$4:$G$24,4,FALSE) -> -0.11659193 | G106: =I105 -> 713114.89 | H106: =(G106+C106)*F106 -> -103405.61 | I106: =G106+C106+H106 -> 783496.31 | J106: =J105+C106 -> 715155.78 | K106: =IFERROR((I106-J106)/J106,"") -> 0.095560335 | L106: =IFERROR((1+K106)/VLOOKUP(B106,'Исходные данные'!$A$4:$G$24,6,FALSE)-1,"") -> -0.3600242 | M106: =IFERROR((I106/J106)^(1/(B106-$B$102+1))-1,"") -> 0.018420798
A107: А10%/О90% | B107: ='Исходные данные'!$A9 -> 2009 | C107: =IF(AND(Таблица12[[#This Row],[Год]]>=Настройки!$B$4, Таблица12[[#This Row],[Год]]<=Настройки!$B$5),IFERROR(VLOOKUP(Таблица12[[#This Row],[Год]],Данные[#All],9,FALSE),0),0) -> 196865.94 | D107: =VLOOKUP($A$102,Настройки!$L$2:$N$13,2,FALSE) -> 0.1 | E107: =VLOOKUP($A$102,Настройки!$L$2:$N$13,3,FALSE) -> 0.9 | F107: =D107*VLOOKUP(B107,'Исходные данные'!$A$4:$G$24,2,FALSE)+E107*VLOOKUP(B107,'Исходные данные'!$A$4:$G$24,3,FALSE)+(1-D107-E107)*VLOOKUP(B107,'Исходные данные'!$A$4:$G$24,4,FALSE) -> 0.44406466 | G107: =I106 -> 783496.31 | H107: =(G107+C107)*F107 -> 435344.23 | I107: =G107+C107+H107 -> 1415706.5 | J107: =J106+C107 -> 912021.73 | K107: =IFERROR((I107-J107)/J107,"") -> 0.55227276 | L107: =IFERROR((1+K107)/VLOOKUP(B107,'Исходные данные'!$A$4:$G$24,6,FALSE)-1,"") -> -0.16657525 | M107: =IFERROR((I107/J107)^(1/(B107-$B$102+1))-1,"") -> 0.076038985
A108: А10%/О90% | B108: ='Исходные данные'!$A10 -> 2010 | C108: =IF(AND(Таблица12[[#This Row],[Год]]>=Настройки!$B$4, Таблица12[[#This Row],[Год]]<=Настройки!$B$5),IFERROR(VLOOKUP(Таблица12[[#This Row],[Год]],Данные[#All],9,FALSE),0),0) -> 214190.14 | D108: =VLOOKUP($A$102,Настройки!$L$2:$N$13,2,FALSE) -> 0.1 | E108: =VLOOKUP($A$102,Настройки!$L$2:$N$13,3,FALSE) -> 0.9 | F108: =D108*VLOOKUP(B108,'Исходные данные'!$A$4:$G$24,2,FALSE)+E108*VLOOKUP(B108,'Исходные данные'!$A$4:$G$24,3,FALSE)+(1-D108-E108)*VLOOKUP(B108,'Исходные данные'!$A$4:$G$24,4,FALSE) -> 0.1256123 | G108: =I107 -> 1415706.5 | H108: =(G108+C108)*F108 -> 204735.07 | I108: =G108+C108+H108 -> 1834631.7 | J108: =J107+C108 -> 1126211.9 | K108: =IFERROR((I108-J108)/J108,"") -> 0.62902891 | L108: =IFERROR((1+K108)/VLOOKUP(B108,'Исходные данные'!$A$4:$G$24,6,FALSE)-1,"") -> -0.19595919 | M108: =IFERROR((I108/J108)^(1/(B108-$B$102+1))-1,"") -> 0.072199355
A109: А10%/О90% | B109: ='Исходные данные'!$A11 -> 2011 | C109: =IF(AND(Таблица12[[#This Row],[Год]]>=Настройки!$B$4, Таблица12[[#This Row],[Год]]<=Настройки!$B$5),IFERROR(VLOOKUP(Таблица12[[#This Row],[Год]],Данные[#All],9,FALSE),0),0) -> 232996.04 | D109: =VLOOKUP($A$102,Настройки!$L$2:$N$13,2,FALSE) -> 0.1 | E109: =VLOOKUP($A$102,Настройки!$L$2:$N$13,3,FALSE) -> 0.9 | F109: =D109*VLOOKUP(B109,'Исходные данные'!$A$4:$G$24,2,FALSE)+E109*VLOOKUP(B109,'Исходные данные'!$A$4:$G$24,3,FALSE)+(1-D109-E109)*VLOOKUP(B109,'Исходные данные'!$A$4:$G$24,4,FALSE) -> 0.037693306 | G109: =I108 -> 1834631.7 | H109: =(G109+C109)*F109 -> 77935.724 | I109: =G109+C109+H109 -> 2145563.5 | J109: =J108+C109 -> 1359207.9 | K109: =IFERROR((I109-J109)/J109,"") -> 0.57853956 | L109: =IFERROR((1+K109)/VLOOKUP(B109,'Исходные данные'!$A$4:$G$24,6,FALSE)-1,"") -> -0.26567318 | M109: =IFERROR((I109/J109)^(1/(B109-$B$102+1))-1,"") -> 0.058721991
A110: А10%/О90% | B110: ='Исходные данные'!$A12 -> 2012 | C110: =IF(AND(Таблица12[[#This Row],[Год]]>=Настройки!$B$4, Таблица12[[#This Row],[Год]]<=Настройки!$B$5),IFERROR(VLOOKUP(Таблица12[[#This Row],[Год]],Данные[#All],9,FALSE),0),0) -> 247208.8 | D110: =VLOOKUP($A$102,Настройки!$L$2:$N$13,2,FALSE) -> 0.1 | E110: =VLOOKUP($A$102,Настройки!$L$2:$N$13,3,FALSE) -> 0.9 | F110: =D110*VLOOKUP(B110,'Исходные данные'!$A$4:$G$24,2,FALSE)+E110*VLOOKUP(B110,'Исходные данные'!$A$4:$G$24,3,FALSE)+(1-D110-E110)*VLOOKUP(B110,'Исходные данные'!$A$4:$G$24,4,FALSE) -> 0.14057872 | G110: =I109 -> 2145563.5 | H110: =(G110+C110)*F110 -> 336372.85 | I110: =G110+C110+H110 -> 2729145.1 | J110: =J109+C110 -> 1606416.7 | K110: =IFERROR((I110-J110)/J110,"") -> 0.69890234 | L110: =IFERROR((1+K110)/VLOOKUP(B110,'Исходные данные'!$A$4:$G$24,6,FALSE)-1,"") -> -0.2584736 | M110: =IFERROR((I110/J110)^(1/(B110-$B$102+1))-1,"") -> 0.060655305
A111: А10%/О90% | B111: ='Исходные данные'!$A13 -> 2013 | C111: =IF(AND(Таблица12[[#This Row],[Год]]>=Настройки!$B$4, Таблица12[[#This Row],[Год]]<=Настройки!$B$5),IFERROR(VLOOKUP(Таблица12[[#This Row],[Год]],Данные[#All],9,FALSE),0),0) -> 263475.14 | D111: =VLOOKUP($A$102,Настройки!$L$2:$N$13,2,FALSE) -> 0.1 | E111: =VLOOKUP($A$102,Настройки!$L$2:$N$13,3,FALSE) -> 0.9 | F111: =D111*VLOOKUP(B111,'Исходные данные'!$A$4:$G$24,2,FALSE)+E111*VLOOKUP(B111,'Исходные данные'!$A$4:$G$24,3,FALSE)+(1-D111-E111)*VLOOKUP(B111,'Исходные данные'!$A$4:$G$24,4,FALSE) -> 0.040533033 | G111: =I110 -> 2729145.1 | H111: =(G111+C111)*F111 -> 121299.98 | I111: =G111+C111+H111 -> 3113920.2 | J111: =J110+C111 -> 1869891.8 | K111: =IFERROR((I111-J111)/J111,"") -> 0.66529429 | L111: =IFERROR((1+K111)/VLOOKUP(B111,'Исходные данные'!$A$4:$G$24,6,FALSE)-1,"") -> -0.31718425 | M111: =IFERROR((I111/J111)^(1/(B111-$B$102+1))-1,"") -> 0.052323089
A112: А10%/О90% | B112: ='Исходные данные'!$A14 -> 2014 | C112: =IF(AND(Таблица12[[#This Row],[Год]]>=Настройки!$B$4, Таблица12[[#This Row],[Год]]<=Настройки!$B$5),IFERROR(VLOOKUP(Таблица12[[#This Row],[Год]],Данные[#All],9,FALSE),0),0) -> 280469.28 | D112: =VLOOKUP($A$102,Настройки!$L$2:$N$13,2,FALSE) -> 0.1 | E112: =VLOOKUP($A$102,Настройки!$L$2:$N$13,3,FALSE) -> 0.9 | F112: =D112*VLOOKUP(B112,'Исходные данные'!$A$4:$G$24,2,FALSE)+E112*VLOOKUP(B112,'Исходные данные'!$A$4:$G$24,3,FALSE)+(1-D112-E112)*VLOOKUP(B112,'Исходные данные'!$A$4:$G$24,4,FALSE) -> -0.13104147 | G112: =I111 -> 3113920.2 | H112: =(G112+C112)*F112 -> -444805.78 | I112: =G112+C112+H112 -> 2949583.7 | J112: =J111+C112 -> 2150361.1 | K112: =IFERROR((I112-J112)/J112,"") -> 0.37166901 | L112: =IFERROR((1+K112)/VLOOKUP(B112,'Исходные данные'!$A$4:$G$24,6,FALSE)-1,"") -> -0.49495202 | M112: =IFERROR((I112/J112)^(1/(B112-$B$102+1))-1,"") -> 0.029146524
A113: А10%/О90% | B113: ='Исходные данные'!$A15 -> 2015 | C113: =IF(AND(Таблица12[[#This Row],[Год]]>=Настройки!$B$4, Таблица12[[#This Row],[Год]]<=Настройки!$B$5),IFERROR(VLOOKUP(Таблица12[[#This Row],[Год]],Данные[#All],9,FALSE),0),0) -> 312330.59 | D113: =VLOOKUP($A$102,Настройки!$L$2:$N$13,2,FALSE) -> 0.1 | E113: =VLOOKUP($A$102,Настройки!$L$2:$N$13,3,FALSE) -> 0.9 | F113: =D113*VLOOKUP(B113,'Исходные данные'!$A$4:$G$24,2,FALSE)+E113*VLOOKUP(B113,'Исходные данные'!$A$4:$G$24,3,FALSE)+(1-D113-E113)*VLOOKUP(B113,'Исходные данные'!$A$4:$G$24,4,FALSE) -> 0.29827416 | G113: =I112 -> 2949583.7 | H113: =(G113+C113)*F113 -> 972944.76 | I113: =G113+C113+H113 -> 4234859.1 | J113: =J112+C113 -> 2462691.7 | K113: =IFERROR((I113-J113)/J113,"") -> 0.71960584 | L113: =IFERROR((1+K113)/VLOOKUP(B113,'Исходные данные'!$A$4:$G$24,6,FALSE)-1,"") -> -0.4392364 | M113: =IFERROR((I113/J113)^(1/(B113-$B$102+1))-1,"") -> 0.046210504
A114: А10%/О90% | B114: ='Исходные данные'!$A16 -> 2016 | C114: =IF(AND(Таблица12[[#This Row],[Год]]>=Настройки!$B$4, Таблица12[[#This Row],[Год]]<=Настройки!$B$5),IFERROR(VLOOKUP(Таблица12[[#This Row],[Год]],Данные[#All],9,FALSE),0),0) -> 352652.47 | D114: =VLOOKUP($A$102,Настройки!$L$2:$N$13,2,FALSE) -> 0.1 | E114: =VLOOKUP($A$102,Настройки!$L$2:$N$13,3,FALSE) -> 0.9 | F114: =D114*VLOOKUP(B114,'Исходные данные'!$A$4:$G$24,2,FALSE)+E114*VLOOKUP(B114,'Исходные данные'!$A$4:$G$24,3,FALSE)+(1-D114-E114)*VLOOKUP(B114,'Исходные данные'!$A$4:$G$24,4,FALSE) -> 0.16668466 | G114: =I113 -> 4234859.1 | H114: =(G114+C114)*F114 -> 764667.79 | I114: =G114+C114+H114 -> 5352179.3 | J114: =J113+C114 -> 2815344.2 | K114: =IFERROR((I114-J114)/J114,"") -> 0.9010746 | L114: =IFERROR((1+K114)/VLOOKUP(B114,'Исходные данные'!$A$4:$G$24,6,FALSE)-1,"") -> -0.41170945 | M114: =IFERROR((I114/J114)^(1/(B114-$B$102+1))-1,"") -> 0.050658247
... A122: А10%/О90% | B122: ='Исходные данные'!$A24 -> 2024 | C122: =IF(AND(Таблица12[[#This Row],[Год]]>=Настройки!$B$4, Таблица12[[#This Row],[Год]]<=Настройки!$B$5),IFERROR(VLOOKUP(Таблица12[[#This Row],[Год]],Данные[#All],9,FALSE),0),0) -> 559754.57 | D122: =VLOOKUP($A$102,Настройки!$L$2:$N$13,2,FALSE) -> 0.1 | E122: =VLOOKUP($A$102,Настройки!$L$2:$N$13,3,FALSE) -> 0.9 | F122: =D122*VLOOKUP(B122,'Исходные данные'!$A$4:$G$24,2,FALSE)+E122*VLOOKUP(B122,'Исходные данные'!$A$4:$G$24,3,FALSE)+(1-D122-E122)*VLOOKUP(B122,'Исходные данные'!$A$4:$G$24,4,FALSE) -> -0.07626281 | G122: =I121 -> 12136293 | H122: =(G122+C122)*F122 -> -968236.25 | I122: =G122+C122+H122 -> 11727811 | J122: =J121+C122 -> 6350420.1 | K122: =IFERROR((I122-J122)/J122,"") -> 0.84677721 | L122: =IFERROR((1+K122)/VLOOKUP(B122,'Исходные данные'!$A$4:$G$24,6,FALSE)-1,"") -> -0.6535654 | M122: =IFERROR((I122/J122)^(1/(B122-$B$102+1))-1,"") -> 0.029642369
A125: Стратегия | B125: Год | C125: Взнос | D125: Доля Акций | E125: Доля Облигаций | F125: Доходность стратегии за год | G125: Портфель на НАЧАЛО года | H125: Доход | I125: Итоговый портфель, ₽ | J125: Вложено всего, ₽ | K125: Номинальная доходность | L125: Реальная доходность, % | M125: Среднегодовой рост
A126: А20%/О80% | B126: ='Исходные данные'!$A4 -> 2004 | C126: =IF(AND(Таблица11[[#This Row],[Год]]>=Настройки!$B$4, Таблица11[[#This Row],[Год]]<=Настройки!$B$5),IFERROR(VLOOKUP(Таблица11[[#This Row],[Год]],Данные[#All],9,FALSE),0),0) -> 115000 | D126: =VLOOKUP($A$126,Настройки!$L$2:$N$13,2,FALSE) -> 0.2 | E126: =VLOOKUP($A$126,Настройки!$L$2:$N$13,3,FALSE) -> 0.8 | F126: =D126*VLOOKUP(B126,'Исходные данные'!$A$4:$G$24,2,FALSE)+E126*VLOOKUP(B126,'Исходные данные'!$A$4:$G$24,3,FALSE)+(1-D126-E126)*VLOOKUP(B126,'Исходные данные'!$A$4:$G$24,4,FALSE) -> 0.10169647 | G126: =0 -> 0 | H126: =(G126+C126)*F126 -> 11695.094 | I126: =G126+C126+H126 -> 126695.09 | J126: =C126 -> 115000 | K126: =IFERROR((I126-J126)/J126,"") -> 0.10169647 | L126: =IFERROR((1+K126)/VLOOKUP(B126,'Исходные данные'!$A$4:$G$24,6,FALSE)-1,"") -> -0.014053634 | M126: =IFERROR((I126/J126)^(1/(B126-$B$126+1))-1,"") -> 0.10169647
A127: А20%/О80% | B127: ='Исходные данные'!$A5 -> 2005 | C127: =IF(AND(Таблица11[[#This Row],[Год]]>=Настройки!$B$4, Таблица11[[#This Row],[Год]]<=Настройки!$B$5),IFERROR(VLOOKUP(Таблица11[[#This Row],[Год]],Данные[#All],9,FALSE),0),0) -> 128501 | D127: =VLOOKUP($A$126,Настройки!$L$2:$N$13,2,FALSE) -> 0.2 | E127: =VLOOKUP($A$126,Настройки!$L$2:$N$13,3,FALSE) -> 0.8 | F127: =D127*VLOOKUP(B127,'Исходные данные'!$A$4:$G$24,2,FALSE)+E127*VLOOKUP(B127,'Исходные данные'!$A$4:$G$24,3,FALSE)+(1-D127-E127)*VLOOKUP(B127,'Исходные данные'!$A$4:$G$24,4,FALSE) -> 0.2628851 | G127: =I126 -> 126695.09 | H127: =(G127+C127)*F127 -> 67087.25 | I127: =G127+C127+H127 -> 322283.34 | J127: =J126+C127 -> 243501 | K127: =IFERROR((I127-J127)/J127,"") -> 0.32354012 | L127: =IFERROR((1+K127)/VLOOKUP(B127,'Исходные данные'!$A$4:$G$24,6,FALSE)-1,"") -> 0.067966769 | M127: =IFERROR((I127/J127)^(1/(B127-$B$126+1))-1,"") -> 0.15045214
A128: А20%/О80% | B128: ='Исходные данные'!$A6 -> 2006 | C128: =IF(AND(Таблица11[[#This Row],[Год]]>=Настройки!$B$4, Таблица11[[#This Row],[Год]]<=Настройки!$B$5),IFERROR(VLOOKUP(Таблица11[[#This Row],[Год]],Данные[#All],9,FALSE),0),0) -> 142520.46 | D128: =VLOOKUP($A$126,Настройки!$L$2:$N$13,2,FALSE) -> 0.2 | E128: =VLOOKUP($A$126,Настройки!$L$2:$N$13,3,FALSE) -> 0.8 | F128: =D128*VLOOKUP(B128,'Исходные данные'!$A$4:$G$24,2,FALSE)+E128*VLOOKUP(B128,'Исходные данные'!$A$4:$G$24,3,FALSE)+(1-D128-E128)*VLOOKUP(B128,'Исходные данные'!$A$4:$G$24,4,FALSE) -> 0.19454504 | G128: =I127 -> 322283.34 | H128: =(G128+C128)*F128 -> 90425.274 | I128: =G128+C128+H128 -> 555229.08 | J128: =J127+C128 -> 386021.46 | K128: =IFERROR((I128-J128)/J128,"") -> 0.43833734 | L128: =IFERROR((1+K128)/VLOOKUP(B128,'Исходные данные'!$A$4:$G$24,6,FALSE)-1,"") -> 0.064767737 | M128: =IFERROR((I128/J128)^(1/(B128-$B$126+1))-1,"") -> 0.12880845
A129: А20%/О80% | B129: ='Исходные данные'!$A7 -> 2007 | C129: =IF(AND(Таблица11[[#This Row],[Год]]>=Настройки!$B$4, Таблица11[[#This Row],[Год]]<=Настройки!$B$5),IFERROR(VLOOKUP(Таблица11[[#This Row],[Год]],Данные[#All],9,FALSE),0),0) -> 155347.3 | D129: =VLOOKUP($A$126,Настройки!$L$2:$N$13,2,FALSE) -> 0.2 | E129: =VLOOKUP($A$126,Настройки!$L$2:$N$13,3,FALSE) -> 0.8 | F129: =D129*VLOOKUP(B129,'Исходные данные'!$A$4:$G$24,2,FALSE)+E129*VLOOKUP(B129,'Исходные данные'!$A$4:$G$24,3,FALSE)+(1-D129-E129)*VLOOKUP(B129,'Исходные данные'!$A$4:$G$24,4,FALSE) -> 0.084524714 | G129: =I128 -> 555229.08 | H129: =(G129+C129)*F129 -> 60061.265 | I129: =G129+C129+H129 -> 770637.64 | J129: =J128+C129 -> 541368.76 | K129: =IFERROR((I129-J129)/J129,"") -> 0.42349855 | L129: =IFERROR((1+K129)/VLOOKUP(B129,'Исходные данные'!$A$4:$G$24,6,FALSE)-1,"") -> -0.058029028 | M129: =IFERROR((I129/J129)^(1/(B129-$B$126+1))-1,"") -> 0.092293268
A130: А20%/О80% | B130: ='Исходные данные'!$A8 -> 2008 | C130: =IF(AND(Таблица11[[#This Row],[Год]]>=Настройки!$B$4, Таблица11[[#This Row],[Год]]<=Настройки!$B$5),IFERROR(VLOOKUP(Таблица11[[#This Row],[Год]],Данные[#All],9,FALSE),0),0) -> 173787.02 | D130: =VLOOKUP($A$126,Настройки!$L$2:$N$13,2,FALSE) -> 0.2 | E130: =VLOOKUP($A$126,Настройки!$L$2:$N$13,3,FALSE) -> 0.8 | F130: =D130*VLOOKUP(B130,'Исходные данные'!$A$4:$G$24,2,FALSE)+E130*VLOOKUP(B130,'Исходные данные'!$A$4:$G$24,3,FALSE)+(1-D130-E130)*VLOOKUP(B130,'Исходные данные'!$A$4:$G$24,4,FALSE) -> -0.17764667 | G130: =I129 -> 770637.64 | H130: =(G130+C130)*F130 -> -167773.9 | I130: =G130+C130+H130 -> 776650.77 | J130: =J129+C130 -> 715155.78 | K130: =IFERROR((I130-J130)/J130,"") -> 0.085988234 | L130: =IFERROR((1+K130)/VLOOKUP(B130,'Исходные данные'!$A$4:$G$24,6,FALSE)-1,"") -> -0.36561578 | M130: =IFERROR((I130/J130)^(1/(B130-$B$126+1))-1,"") -> 0.016634922
A131: А20%/О80% | B131: ='Исходные данные'!$A9 -> 2009 | C131: =IF(AND(Таблица11[[#This Row],[Год]]>=Настройки!$B$4, Таблица11[[#This Row],[Год]]<=Настройки!$B$5),IFERROR(VLOOKUP(Таблица11[[#This Row],[Год]],Данные[#All],9,FALSE),0),0) -> 196865.94 | D131: =VLOOKUP($A$126,Настройки!$L$2:$N$13,2,FALSE) -> 0.2 | E131: =VLOOKUP($A$126,Настройки!$L$2:$N$13,3,FALSE) -> 0.8 | F131: =D131*VLOOKUP(B131,'Исходные данные'!$A$4:$G$24,2,FALSE)+E131*VLOOKUP(B131,'Исходные данные'!$A$4:$G$24,3,FALSE)+(1-D131-E131)*VLOOKUP(B131,'Исходные данные'!$A$4:$G$24,4,FALSE) -> 0.53484498 | G131: =I130 -> 776650.77 | H131: =(G131+C131)*F131 -> 520680.53 | I131: =G131+C131+H131 -> 1494197.2 | J131: =J130+C131 -> 912021.73 | K131: =IFERROR((I131-J131)/J131,"") -> 0.63833513 | L131: =IFERROR((1+K131)/VLOOKUP(B131,'Исходные данные'!$A$4:$G$24,6,FALSE)-1,"") -> -0.12036784 | M131: =IFERROR((I131/J131)^(1/(B131-$B$126+1))-1,"") -> 0.085759882
A132: А20%/О80% | B132: ='Исходные данные'!$A10 -> 2010 | C132: =IF(AND(Таблица11[[#This Row],[Год]]>=Настройки!$B$4, Таблица11[[#This Row],[Год]]<=Настройки!$B$5),IFERROR(VLOOKUP(Таблица11[[#This Row],[Год]],Данные[#All],9,FALSE),0),0) -> 214190.14 | D132: =VLOOKUP($A$126,Настройки!$L$2:$N$13,2,FALSE) -> 0.2 | E132: =VLOOKUP($A$126,Настройки!$L$2:$N$13,3,FALSE) -> 0.8 | F132: =D132*VLOOKUP(B132,'Исходные данные'!$A$4:$G$24,2,FALSE)+E132*VLOOKUP(B132,'Исходные данные'!$A$4:$G$24,3,FALSE)+(1-D132-E132)*VLOOKUP(B132,'Исходные данные'!$A$4:$G$24,4,FALSE) -> 0.13974948 | G132: =I131 -> 1494197.2 | H132: =(G132+C132)*F132 -> 238746.25 | I132: =G132+C132+H132 -> 1947133.6 | J132: =J131+C132 -> 1126211.9 | K132: =IFERROR((I132-J132)/J132,"") -> 0.72892302 | L132: =IFERROR((1+K132)/VLOOKUP(B132,'Исходные данные'!$A$4:$G$24,6,FALSE)-1,"") -> -0.14665439 | M132: =IFERROR((I132/J132)^(1/(B132-$B$126+1))-1,"") -> 0.08135415
A133: А20%/О80% | B133: ='Исходные данные'!$A11 -> 2011 | C133: =IF(AND(Таблица11[[#This Row],[Год]]>=Настройки!$B$4, Таблица11[[#This Row],[Год]]<=Настройки!$B$5),IFERROR(VLOOKUP(Таблица11[[#This Row],[Год]],Данные[#All],9,FALSE),0),0) -> 232996.04 | D133: =VLOOKUP($A$126,Настройки!$L$2:$N$13,2,FALSE) -> 0.2 | E133: =VLOOKUP($A$126,Настройки!$L$2:$N$13,3,FALSE) -> 0.8 | F133: =D133*VLOOKUP(B133,'Исходные данные'!$A$4:$G$24,2,FALSE)+E133*VLOOKUP(B133,'Исходные данные'!$A$4:$G$24,3,FALSE)+(1-D133-E133)*VLOOKUP(B133,'Исходные данные'!$A$4:$G$24,4,FALSE) -> 0.017443701 | G133: =I132 -> 1947133.6 | H133: =(G133+C133)*F133 -> 38029.53 | I133: =G133+C133+H133 -> 2218159.2 | J133: =J132+C133 -> 1359207.9 | K133: =IFERROR((I133-J133)/J133,"") -> 0.63194989 | L133: =IFERROR((1+K133)/VLOOKUP(B133,'Исходные данные'!$A$4:$G$24,6,FALSE)-1,"") -> -0.24082703 | M133: =IFERROR((I133/J133)^(1/(B133-$B$126+1))-1,"") -> 0.063134845
A134: А20%/О80% | B134: ='Исходные данные'!$A12 -> 2012 | C134: =IF(AND(Таблица11[[#This Row],[Год]]>=Настройки!$B$4, Таблица11[[#This Row],[Год]]<=Настройки!$B$5),IFERROR(VLOOKUP(Таблица11[[#This Row],[Год]],Данные[#All],9,FALSE),0),0) -> 247208.8 | D134: =VLOOKUP($A$126,Настройки!$L$2:$N$13,2,FALSE) -> 0.2 | E134: =VLOOKUP($A$126,Настройки!$L$2:$N$13,3,FALSE) -> 0.8 | F134: =D134*VLOOKUP(B134,'Исходные данные'!$A$4:$G$24,2,FALSE)+E134*VLOOKUP(B134,'Исходные данные'!$A$4:$G$24,3,FALSE)+(1-D134-E134)*VLOOKUP(B134,'Исходные данные'!$A$4:$G$24,4,FALSE) -> 0.13470241 | G134: =I133 -> 2218159.2 | H134: =(G134+C134)*F134 -> 332091.02 | I134: =G134+C134+H134 -> 2797459 | J134: =J133+C134 -> 1606416.7 | K134: =IFERROR((I134-J134)/J134,"") -> 0.74142799 | L134: =IFERROR((1+K134)/VLOOKUP(B134,'Исходные данные'!$A$4:$G$24,6,FALSE)-1,"") -> -0.23991227 | M134: =IFERROR((I134/J134)^(1/(B134-$B$126+1))-1,"") -> 0.063572942
A135: А20%/О80% | B135: ='Исходные данные'!$A13 -> 2013 | C135: =IF(AND(Таблица11[[#This Row],[Год]]>=Настройки!$B$4, Таблица11[[#This Row],[Год]]<=Настройки!$B$5),IFERROR(VLOOKUP(Таблица11[[#This Row],[Год]],Данные[#All],9,FALSE),0),0) -> 263475.14 | D135: =VLOOKUP($A$126,Настройки!$L$2:$N$13,2,FALSE) -> 0.2 | E135: =VLOOKUP($A$126,Настройки!$L$2:$N$13,3,FALSE) -> 0.8 | F135: =D135*VLOOKUP(B135,'Исходные данные'!$A$4:$G$24,2,FALSE)+E135*VLOOKUP(B135,'Исходные данные'!$A$4:$G$24,3,FALSE)+(1-D135-E135)*VLOOKUP(B135,'Исходные данные'!$A$4:$G$24,4,FALSE) -> 0.043046049 | G135: =I134 -> 2797459 | H135: =(G135+C135)*F135 -> 131761.12 | I135: =G135+C135+H135 -> 3192695.3 | J135: =J134+C135 -> 1869891.8 | K135: =IFERROR((I135-J135)/J135,"") -> 0.70742243 | L135: =IFERROR((1+K135)/VLOOKUP(B135,'Исходные данные'!$A$4:$G$24,6,FALSE)-1,"") -> -0.29991057 | M135: =IFERROR((I135/J135)^(1/(B135-$B$126+1))-1,"") -> 0.054955397
A136: А20%/О80% | B136: ='Исходные данные'!$A14 -> 2014 | C136: =IF(AND(Таблица11[[#This Row],[Год]]>=Настройки!$B$4, Таблица11[[#This Row],[Год]]<=Настройки!$B$5),IFERROR(VLOOKUP(Таблица11[[#This Row],[Год]],Данные[#All],9,FALSE),0),0) -> 280469.28 | D136: =VLOOKUP($A$126,Настройки!$L$2:$N$13,2,FALSE) -> 0.2 | E136: =VLOOKUP($A$126,Настройки!$L$2:$N$13,3,FALSE) -> 0.8 | F136: =D136*VLOOKUP(B136,'Исходные данные'!$A$4:$G$24,2,FALSE)+E136*VLOOKUP(B136,'Исходные данные'!$A$4:$G$24,3,FALSE)+(1-D136-E136)*VLOOKUP(B136,'Исходные данные'!$A$4:$G$24,4,FALSE) -> -0.11853047 | G136: =I135 -> 3192695.3 | H136: =(G136+C136)*F136 -> -411675.83 | I136: =G136+C136+H136 -> 3061488.7 | J136: =J135+C136 -> 2150361.1 | K136: =IFERROR((I136-J136)/J136,"") -> 0.42370911 | L136: =IFERROR((1+K136)/VLOOKUP(B136,'Исходные данные'!$A$4:$G$24,6,FALSE)-1,"") -> -0.47579087 | M136: =IFERROR((I136/J136)^(1/(B136-$B$126+1))-1,"") -> 0.0326363
A137: А20%/О80% | B137: ='Исходные данные'!$A15 -> 2015 | C137: =IF(AND(Таблица11[[#This Row],[Год]]>=Настройки!$B$4, Таблица11[[#This Row],[Год]]<=Настройки!$B$5),IFERROR(VLOOKUP(Таблица11[[#This Row],[Год]],Данные[#All],9,FALSE),0),0) -> 312330.59 | D137: =VLOOKUP($A$126,Настройки!$L$2:$N$13,2,FALSE) -> 0.2 | E137: =VLOOKUP($A$126,Настройки!$L$2:$N$13,3,FALSE) -> 0.8 | F137: =D137*VLOOKUP(B137,'Исходные данные'!$A$4:$G$24,2,FALSE)+E137*VLOOKUP(B137,'Исходные данные'!$A$4:$G$24,3,FALSE)+(1-D137-E137)*VLOOKUP(B137,'Исходные данные'!$A$4:$G$24,4,FALSE) -> 0.30099405 | G137: =I136 -> 3061488.7 | H137: =(G137+C137)*F137 -> 1015499.5 | I137: =G137+C137+H137 -> 4389318.9 | J137: =J136+C137 -> 2462691.7 | K137: =IFERROR((I137-J137)/J137,"") -> 0.78232574 | L137: =IFERROR((1+K137)/VLOOKUP(B137,'Исходные данные'!$A$4:$G$24,6,FALSE)-1,"") -> -0.41878343 | M137: =IFERROR((I137/J137)^(1/(B137-$B$126+1))-1,"") -> 0.049338458
A138: А20%/О80% | B138: ='Исходные данные'!$A16 -> 2016 | C138: =IF(AND(Таблица11[[#This Row],[Год]]>=Настройки!$B$4, Таблица11[[#This Row],[Год]]<=Настройки!$B$5),IFERROR(VLOOKUP(Таблица11[[#This Row],[Год]],Данные[#All],9,FALSE),0),0) -> 352652.47 | D138: =VLOOKUP($A$126,Настройки!$L$2:$N$13,2,FALSE) -> 0.2 | E138: =VLOOKUP($A$126,Настройки!$L$2:$N$13,3,FALSE) -> 0.8 | F138: =D138*VLOOKUP(B138,'Исходные данные'!$A$4:$G$24,2,FALSE)+E138*VLOOKUP(B138,'Исходные данные'!$A$4:$G$24,3,FALSE)+(1-D138-E138)*VLOOKUP(B138,'Исходные данные'!$A$4:$G$24,4,FALSE) -> 0.18458673 | G138: =I137 -> 4389318.9 | H138: =(G138+C138)*F138 -> 875304.96 | I138: =G138+C138+H138 -> 5617276.3 | J138: =J137+C138 -> 2815344.2 | K138: =IFERROR((I138-J138)/J138,"") -> 0.99523607 | L138: =IFERROR((1+K138)/VLOOKUP(B138,'Исходные данные'!$A$4:$G$24,6,FALSE)-1,"") -> -0.38257104 | M138: =IFERROR((I138/J138)^(1/(B138-$B$126+1))-1,"") -> 0.054572601
... A146: А20%/О80% | B146: ='Исходные данные'!$A24 -> 2024 | C146: =IF(AND(Таблица11[[#This Row],[Год]]>=Настройки!$B$4, Таблица11[[#This Row],[Год]]<=Настройки!$B$5),IFERROR(VLOOKUP(Таблица11[[#This Row],[Год]],Данные[#All],9,FALSE),0),0) -> 559754.57 | D146: =VLOOKUP($A$126,Настройки!$L$2:$N$13,2,FALSE) -> 0.2 | E146: =VLOOKUP($A$126,Настройки!$L$2:$N$13,3,FALSE) -> 0.8 | F146: =D146*VLOOKUP(B146,'Исходные данные'!$A$4:$G$24,2,FALSE)+E146*VLOOKUP(B146,'Исходные данные'!$A$4:$G$24,3,FALSE)+(1-D146-E146)*VLOOKUP(B146,'Исходные данные'!$A$4:$G$24,4,FALSE) -> -0.065970466 | G146: =I145 -> 13273413 | H146: =(G146+C146)*F146 -> -912580.49 | I146: =G146+C146+H146 -> 12920587 | J146: =J145+C146 -> 6350420.1 | K146: =IFERROR((I146-J146)/J146,"") -> 1.0346034 | L146: =IFERROR((1+K146)/VLOOKUP(B146,'Исходные данные'!$A$4:$G$24,6,FALSE)-1,"") -> -0.61833131 | M146: =IFERROR((I146/J146)^(1/(B146-$B$126+1))-1,"") -> 0.034402385
A149: Стратегия | B149: Год | C149: Взнос | D149: Доля Акций | E149: Доля Облигаций | F149: Доходность стратегии за год | G149: Портфель на НАЧАЛО года | H149: Доход | I149: Итоговый портфель, ₽ | J149: Вложено всего, ₽ | K149: Номинальная доходность | L149: Реальная доходность, % | M149: Среднегодовой рост
A150: А30%/О70 | B150: ='Исходные данные'!$A4 -> 2004 | C150: =IF(AND(Таблица10[[#This Row],[Год]]>=Настройки!$B$4, Таблица10[[#This Row],[Год]]<=Настройки!$B$5),IFERROR(VLOOKUP(Таблица10[[#This Row],[Год]],Данные[#All],9,FALSE),0),0) -> 115000 | D150: =VLOOKUP($A$150,Настройки!$L$2:$N$13,2,FALSE) -> 0.3 | E150: =VLOOKUP($A$150,Настройки!$L$2:$N$13,3,FALSE) -> 0.7 | F150: =D150*VLOOKUP(B150,'Исходные данные'!$A$4:$G$24,2,FALSE)+E150*VLOOKUP(B150,'Исходные данные'!$A$4:$G$24,3,FALSE)+(1-D150-E150)*VLOOKUP(B150,'Исходные данные'!$A$4:$G$24,4,FALSE) -> 0.098093909 | G150: =0 -> 0 | H150: =(G150+C150)*F150 -> 11280.8 | I150: =G150+C150+H150 -> 126280.8 | J150: =C150 -> 115000 | K150: =IFERROR((I150-J150)/J150,"") -> 0.098093909 | L150: =IFERROR((1+K150)/VLOOKUP(B150,'Исходные данные'!$A$4:$G$24,6,FALSE)-1,"") -> -0.01727769 | M150: =IFERROR((I150/J150)^(1/(B150-$B$150+1))-1,"") -> 0.098093909
A151: А30%/О70 | B151: ='Исходные данные'!$A5 -> 2005 | C151: =IF(AND(Таблица10[[#This Row],[Год]]>=Настройки!$B$4, Таблица10[[#This Row],[Год]]<=Настройки!$B$5),IFERROR(VLOOKUP(Таблица10[[#This Row],[Год]],Данные[#All],9,FALSE),0),0) -> 128501 | D151: =VLOOKUP($A$150,Настройки!$L$2:$N$13,2,FALSE) -> 0.3 | E151: =VLOOKUP($A$150,Настройки!$L$2:$N$13,3,FALSE) -> 0.7 | F151: =D151*VLOOKUP(B151,'Исходные данные'!$A$4:$G$24,2,FALSE)+E151*VLOOKUP(B151,'Исходные данные'!$A$4:$G$24,3,FALSE)+(1-D151-E151)*VLOOKUP(B151,'Исходные данные'!$A$4:$G$24,4,FALSE) -> 0.33611669 | G151: =I150 -> 126280.8 | H151: =(G151+C151)*F151 -> 85636.414 | I151: =G151+C151+H151 -> 340418.21 | J151: =J150+C151 -> 243501 | K151: =IFERROR((I151-J151)/J151,"") -> 0.39801567 | L151: =IFERROR((1+K151)/VLOOKUP(B151,'Исходные данные'!$A$4:$G$24,6,FALSE)-1,"") -> 0.12806121 | M151: =IFERROR((I151/J151)^(1/(B151-$B$150+1))-1,"") -> 0.18237713
...

Sheet Итоги
A1: Лучшая стратегия | D1: Максимальный капитал | G1: Лучший Среднегодовой рост | J1: Макс. Капитал | K1: =MAX(C7:C18) -> 20545366
J2: Лучшая стратегия | K2: =INDEX(A7:A18,MATCH(K1,C7:C18,0)) -> Акции 100%
J3: Лучший Среднегодовой рост | K3: =MAX(G7:G18) -> 0.057502729
J4: Худшая стратегия | K4: =INDEX(A7:A18,MATCH(MIN(C7:C18),C7:C18,0)) -> Облигации 100%
J5: Всего вложено | K5: =B7 -> 6350420.1
A6: Стратегия | B6: Вложено всего, ₽ | C6: Итоговый портфель, ₽ | D6: Прибыль, ₽ | E6: Номинальная доходность, % | F6: Реальная доходность, % | G6: Среднегодовой рост, % | H6: Тренды (2004-2024)
A7: Акции 100% | B7: ='Расчёт всех стратегий'!J26 -> 6350420.1 | C7: ='Расчёт всех стратегий'!I26 -> 20545366 | D7: =Таблица2[[#This Row],[Итоговый портфель, ₽]] - Таблица2[[#This Row],[Вложено всего, ₽]] -> 14194946 | E7: =Таблица2[[#This Row],[Прибыль, ₽]] / Таблица2[[#This Row],[Вложено всего, ₽]] -> 2.2352767 | F7: ='Расчёт всех стратегий'!L26 -> -0.39309853 | G7: =( Таблица2[[#This Row],[Итоговый портфель, ₽]] / Таблица2[[#This Row],[Вложено всего, ₽]] ) ^ (1 / 21) - 1 -> 0.057502729
A8: Облигации 100% | B8: ='Расчёт всех стратегий'!J50 -> 6350420.1 | C8: ='Расчёт всех стратегий'!I50 -> 10575459 | D8: =Таблица2[[#This Row],[Итоговый портфель, ₽]] - Таблица2[[#This Row],[Вложено всего, ₽]] -> 4225039.2 | E8: =Таблица2[[#This Row],[Прибыль, ₽]] / Таблица2[[#This Row],[Вложено всего, ₽]] -> 0.66531648 | F8: ='Расчёт всех стратегий'!L50 -> -0.68760539 | G8: =( Таблица2[[#This Row],[Итоговый портфель, ₽]] / Таблица2[[#This Row],[Вложено всего, ₽]] ) ^ (1 / 21) - 1 -> 0.024583755
A9: Вклады 100% | B9: ='Расчёт всех стратегий'!J74 -> 6350420.1 | C9: ='Расчёт всех стратегий'!I74 -> 13863147 | D9: =Таблица2[[#This Row],[Итоговый портфель, ₽]] - Таблица2[[#This Row],[Вложено всего, ₽]] -> 7512726.8 | E9: =Таблица2[[#This Row],[Прибыль, ₽]] / Таблица2[[#This Row],[Вложено всего, ₽]] -> 1.1830283 | F9: ='Расчёт всех стратегий'!L74 -> -0.59048848 | G9: =( Таблица2[[#This Row],[Итоговый портфель, ₽]] / Таблица2[[#This Row],[Вложено всего, ₽]] ) ^ (1 / 21) - 1 -> 0.037876513
A10: А50%/О50% | B10: ='Расчёт всех стратегий'!J98 -> 6350420.1 | C10: ='Расчёт всех стратегий'!I98 -> 16523305 | D10: =Таблица2[[#This Row],[Итоговый портфель, ₽]] - Таблица2[[#This Row],[Вложено всего, ₽]] -> 10172885 | E10: =Таблица2[[#This Row],[Прибыль, ₽]] / Таблица2[[#This Row],[Вложено всего, ₽]] -> 1.6019232 | F10: ='Расчёт всех стратегий'!L98 -> -0.51190852 | G10: =( Таблица2[[#This Row],[Итоговый портфель, ₽]] / Таблица2[[#This Row],[Вложено всего, ₽]] ) ^ (1 / 21) - 1 -> 0.046588424
A11: А10%/О90% | B11: ='Расчёт всех стратегий'!J122 -> 6350420.1 | C11: ='Расчёт всех стратегий'!I122 -> 11727811 | D11: =Таблица2[[#This Row],[Итоговый портфель, ₽]] - Таблица2[[#This Row],[Вложено всего, ₽]] -> 5377391 | E11: =Таблица2[[#This Row],[Прибыль, ₽]] / Таблица2[[#This Row],[Вложено всего, ₽]] -> 0.84677721 | F11: ='Расчёт всех стратегий'!L122 -> -0.6535654 | G11: =( Таблица2[[#This Row],[Итоговый портфель, ₽]] / Таблица2[[#This Row],[Вложено всего, ₽]] ) ^ (1 / 21) - 1 -> 0.029642369
A12: А20%/О80% | B12: ='Расчёт всех стратегий'!J146 -> 6350420.1 | C12: ='Расчёт всех стратегий'!I146 -> 12920587 | D12: =Таблица2[[#This Row],[Итоговый портфель, ₽]] - Таблица2[[#This Row],[Вложено всего, ₽]] -> 6570166.5 | E12: =Таблица2[[#This Row],[Прибыль, ₽]] / Таблица2[[#This Row],[Вложено всего, ₽]] -> 1.0346034 | F12: ='Расчёт всех стратегий'!L146 -> -0.61833131 | G12: =( Таблица2[[#This Row],[Итоговый портфель, ₽]] / Таблица2[[#This Row],[Вложено всего, ₽]] ) ^ (1 / 21) - 1 -> 0.034402385
A13: А30%/О70% | B13: ='Расчёт всех стратегий'!J170 -> 6350420.1 | C13: ='Расчёт всех стратегий'!I170 -> 14134529 | D13: =Таблица2[[#This Row],[Итоговый портфель, ₽]] - Таблица2[[#This Row],[Вложено всего, ₽]] -> 7784109.3 | E13: =Таблица2[[#This Row],[Прибыль, ₽]] / Таблица2[[#This Row],[Вложено всего, ₽]] -> 1.2257629 | F13: ='Расчёт всех стратегий'!L170 -> -0.58247196 | G13: =( Таблица2[[#This Row],[Итоговый портфель, ₽]] / Таблица2[[#This Row],[Вложено всего, ₽]] ) ^ (1 / 21) - 1 -> 0.038835098
A14: А40%/О60% | B14: ='Расчёт всех стратегий'!J194 -> 6350420.1 | C14: ='Расчёт всех стратегий'!I194 -> 15345305 | D14: =Таблица2[[#This Row],[Итоговый портфель, ₽]] - Таблица2[[#This Row],[Вложено всего, ₽]] -> 8994884.7 | E14: =Таблица2[[#This Row],[Прибыль, ₽]] / Таблица2[[#This Row],[Вложено всего, ₽]] -> 1.4164236 | F14: ='Расчёт всех стратегий'!L194 -> -0.54670616 | G14: =( Таблица2[[#This Row],[Итоговый портфель, ₽]] / Таблица2[[#This Row],[Вложено всего, ₽]] ) ^ (1 / 21) - 1 -> 0.04290881
A15: А60%/О40% | B15: ='Расчёт всех стратегий'!J218 -> 6350420.1 | C15: ='Расчёт всех стратегий'!I218 -> 17633674 | D15: =Таблица2[[#This Row],[Итоговый портфель, ₽]] - Таблица2[[#This Row],[Вложено всего, ₽]] -> 11283254 | E15: =Таблица2[[#This Row],[Прибыль, ₽]] / Таблица2[[#This Row],[Вложено всего, ₽]] -> 1.7767729 | F15: ='Расчёт всех стратегий'!L218 -> -0.47910869 | G15: =( Таблица2[[#This Row],[Итоговый портфель, ₽]] / Таблица2[[#This Row],[Вложено всего, ₽]] ) ^ (1 / 21) - 1 -> 0.049834811
A16: А70%/О30% | B16: ='Расчёт всех стратегий'!J242 -> 6350420.1 | C16: ='Расчёт всех стратегий'!I242 -> 18636611 | D16: =Таблица2[[#This Row],[Итоговый портфель, ₽]] - Таблица2[[#This Row],[Вложено всего, ₽]] -> 12286191 | E16: =Таблица2[[#This Row],[Прибыль, ₽]] / Таблица2[[#This Row],[Вложено всего, ₽]] -> 1.9347052 | F16: ='Расчёт всех стратегий'!L242 -> -0.44948236 | G16: =( Таблица2[[#This Row],[Итоговый портфель, ₽]] / Таблица2[[#This Row],[Вложено всего, ₽]] ) ^ (1 / 21) - 1 -> 0.052603901
A17: А80%/О20% | B17: ='Расчёт всех стратегий'!J266 -> 6350420.1 | C17: ='Расчёт всех стратегий'!I266 -> 19488024 | D17: =Таблица2[[#This Row],[Итоговый портфель, ₽]] - Таблица2[[#This Row],[Вложено всего, ₽]] -> 13137604 | E17: =Таблица2[[#This Row],[Прибыль, ₽]] / Таблица2[[#This Row],[Вложено всего, ₽]] -> 2.0687771 | F17: ='Расчёт всех стратегий'!L266 -> -0.42433199 | G17: =( Таблица2[[#This Row],[Итоговый портфель, ₽]] / Таблица2[[#This Row],[Вложено всего, ₽]] ) ^ (1 / 21) - 1 -> 0.05484543
A18: А90%/О10% | B18: ='Расчёт всех стратегий'!J290 -> 6350420.1 | C18: ='Расчёт всех стратегий'!I290 -> 20140600 | D18: =Таблица2[[#This Row],[Итоговый портфель, ₽]] - Таблица2[[#This Row],[Вложено всего, ₽]] -> 13790180 | E18: =Таблица2[[#This Row],[Прибыль, ₽]] / Таблица2[[#This Row],[Вложено всего, ₽]] -> 2.1715382 | F18: ='Расчёт всех стратегий'!L290 -> -0.40505516 | G18: =( Таблица2[[#This Row],[Итоговый портфель, ₽]] / Таблица2[[#This Row],[Вложено всего, ₽]] ) ^ (1 / 21) - 1 -> 0.056501206
A20: ="По итогам расчётов с "&Настройки!B4&" по "&Настройки!B5&" год лучшей стратегией стала «"&K2&"» с итоговым капиталом "&TEXT(K1,"# ##0 ₽")&" и среднегодовой доходностью "&TEXT(K3,"0,00%")&". Разница между лучшей и худшей стратегией составила "&TEXT(MAX(C7:C18)-MIN(C7:C18),"# ##0 ₽")&". Всего за период было вложено "&TEXT(B7,"# ##0 ₽")&"." -> По итогам расчётов с 2004 по 2024 год лучшей стратегией стала «Акции 100%» с итоговым капиталом 20 545 366 ₽ и среднегодовой доходностью 5,75%. Разница между лучшей и худшей стратегией составила 9 969 907 ₽. Всего за период было вложено 6 350 420 ₽.

Sheet Дашборды
A1: ="DCA-стратегии на рынке РФ: "&Настройки!B4&"–"&Настройки!B5 -> DCA-стратегии на рынке РФ: 2004–2024
C3: Всего вложено | I3: Максимальный капитал | O3: Лучшая стратегия | U3: Накопленная инфляция
C5: =Итоги!K5 -> 6350420.1 | I5: =MAX(Итоги!C7:C18) -> 20545366 | O5: =INDEX(Итоги!A7:A18,MATCH(MAX(Итоги!C7:C18),Итоги!C7:C18,0)) -> Акции 100% | U5: ='Исходные данные'!F24-1 -> 4.3308105

Sheet Калькулятор
A1: Калькулятор | M1: Год | N1: Стартовый капитал | O1: Портфель(номинал) | P1: Портфель (реал.)
A2: Поможет вам оценить потенциальную доходность ваших вложений | M2: =IF($B$6>=1, 1, "") -> 1 | N2: =IF(M2>$B$6,"",$B$3) -> 100000 | O2: =IF(M2>$B$6,"",$B$3) -> 100000 | P2: =IF(OR(M3>$B$6,$B$8="Нет"),"",O3/(1+$B$9)^M3) -> 473100.25
A3: Стартовый капитал | B3: 100000 | M3: =IF(M2="", "", IF(M2>=$B$6, "", M2+1)) -> 2 | N3: =IF(M3>$B$6,"",$B$3) -> 100000 | O3: =IF(M3>$B$6,"", IF($B$7="Да", FV($B$5/12,M3*12,-$B$4,-$B$3,0), $B$3+($B$4*12*M3)+($B$3*$B$5*M3))) -> 531575.44 | P3: =IF(OR(M3>$B$6,$B$8="Нет"),"",O3/(1+$B$9)^M3) -> 473100.25
A4: Ежемесячное пополнение | B4: 15000 | M4: =IF(M3="", "", IF(M3>=$B$6, "", M3+1)) -> 3 | N4: =IF(M4>$B$6,"",$B$3) -> 100000 | O4: =IF(M4>$B$6,"", IF($B$7="Да", FV($B$5/12,M4*12,-$B$4,-$B$3,0), $B$3+($B$4*12*M4)+($B$3*$B$5*M4))) -> 789230.05 | P4: =IF(OR(M4>$B$6,$B$8="Нет"),"",O4/(1+$B$9)^M4) -> 662652.77
A5: Годовая процентная ставка | B5: 0.12 | M5: =IF(M4="", "", IF(M4>=$B$6, "", M4+1)) -> 4 | N5: =IF(M5>$B$6,"",$B$3) -> 100000 | O5: =IF(M5>$B$6,"", IF($B$7="Да", FV($B$5/12,M5*12,-$B$4,-$B$3,0), $B$3+($B$4*12*M5)+($B$3*$B$5*M5))) -> 1079561.7 | P5: =IF(OR(M5>$B$6,$B$8="Нет"),"",O5/(1+$B$9)^M5) -> 855114
A6: Срок инвестирования (лет) | B6: 20 | M6: =IF(M5="", "", IF(M5>=$B$6, "", M5+1)) -> 5 | N6: =IF(M6>$B$6,"",$B$3) -> 100000 | O6: =IF(M6>$B$6,"", IF($B$7="Да", FV($B$5/12,M6*12,-$B$4,-$B$3,0), $B$3+($B$4*12*M6)+($B$3*$B$5*M6))) -> 1406714.7 | P6: =IF(OR(M6>$B$6,$B$8="Нет"),"",O6/(1+$B$9)^M6) -> 1051179.1
A7: Реинвестировать доход? | B7: Да | M7: =IF(M6="", "", IF(M6>=$B$6, "", M6+1)) -> 6 | N7: =IF(M7>$B$6,"",$B$3) -> 100000 | O7: =IF(M7>$B$6,"", IF($B$7="Да", FV($B$5/12,M7*12,-$B$4,-$B$3,0), $B$3+($B$4*12*M7)+($B$3*$B$5*M7))) -> 1775358.9 | P7: =IF(OR(M7>$B$6,$B$8="Нет"),"",O7/(1+$B$9)^M7) -> 1251558
A8: Учитывать инфляцию? | B8: Да | M8: =IF(M7="", "", IF(M7>=$B$6, "", M7+1)) -> 7 | N8: =IF(M8>$B$6,"",$B$3) -> 100000 | O8: =IF(M8>$B$6,"", IF($B$7="Да", FV($B$5/12,M8*12,-$B$4,-$B$3,0), $B$3+($B$4*12*M8)+($B$3*$B$5*M8))) -> 2190756.4 | P8: =IF(OR(M8>$B$6,$B$8="Нет"),"",O8/(1+$B$9)^M8) -> 1456978.1
A9: Ожидаемая инфляция (годовая) | B9: 0.06 | M9: =IF(M8="", "", IF(M8>=$B$6, "", M8+1)) -> 8 | N9: =IF(M9>$B$6,"",$B$3) -> 100000 | O9: =IF(M9>$B$6,"", IF($B$7="Да", FV($B$5/12,M9*12,-$B$4,-$B$3,0), $B$3+($B$4*12*M9)+($B$3*$B$5*M9))) -> 2658836.7 | P9: =IF(OR(M9>$B$6,$B$8="Нет"),"",O9/(1+$B$9)^M9) -> 1668187
M10: =IF(M9="", "", IF(M9>=$B$6, "", M9+1)) -> 9 | N10: =IF(M10>$B$6,"",$B$3) -> 100000 | O10: =IF(M10>$B$6,"", IF($B$7="Да", FV($B$5/12,M10*12,-$B$4,-$B$3,0), $B$3+($B$4*12*M10)+($B$3*$B$5*M10))) -> 3186281.3 | P10: =IF(OR(M10>$B$6,$B$8="Нет"),"",O10/(1+$B$9)^M10) -> 1885955
A11: РЕЗУЛЬТАТЫ | M11: =IF(M10="", "", IF(M10>=$B$6, "", M10+1)) -> 10 | N11: =IF(M11>$B$6,"",$B$3) -> 100000 | O11: =IF(M11>$B$6,"", IF($B$7="Да", FV($B$5/12,M11*12,-$B$4,-$B$3,0), $B$3+($B$4*12*M11)+($B$3*$B$5*M11))) -> 3780619 | P11: =IF(OR(M11>$B$6,$B$8="Нет"),"",O11/(1+$B$9)^M11) -> 2111077.9
A12: Всего вложено | B12: =(B3+(B4*12*B6)) -> 3700000 | M12: =IF(M11="", "", IF(M11>=$B$6, "", M11+1)) -> 11 | N12: =IF(M12>$B$6,"",$B$3) -> 100000 | O12: =IF(M12>$B$6,"", IF($B$7="Да", FV($B$5/12,M12*12,-$B$4,-$B$3,0), $B$3+($B$4*12*M12)+($B$3*$B$5*M12))) -> 4450333.7 | P12: =IF(OR(M12>$B$6,$B$8="Нет"),"",O12/(1+$B$9)^M12) -> 2344380.3
A13: Итоговая сумма (номинал) | B13: =IF(B7="Да", FV(B5/12, B6*12, -B4, -B3, 0), B3 + (B4*12*B6) + (B3*B5*B6)) -> 15928086 | M13: =IF(M12="", "", IF(M12>=$B$6, "", M12+1)) -> 12 | N13: =IF(M13>$B$6,"",$B$3) -> 100000 | O13: =IF(M13>$B$6,"", IF($B$7="Да", FV($B$5/12,M13*12,-$B$4,-$B$3,0), $B$3+($B$4*12*M13)+($B$3*$B$5*M13))) -> 5204984.9 | P13: =IF(OR(M13>$B$6,$B$8="Нет"),"",O13/(1+$B$9)^M13) -> 2586718.1
A14: Доход | B14: =B13-B12 -> 12228086 | M14: =IF(M13="", "", IF(M13>=$B$6, "", M13+1)) -> 13 | N14: =IF(M14>$B$6,"",$B$3) -> 100000 | O14: =IF(M14>$B$6,"", IF($B$7="Да", FV($B$5/12,M14*12,-$B$4,-$B$3,0), $B$3+($B$4*12*M14)+($B$3*$B$5*M14))) -> 6055344.9 | P14: =IF(OR(M14>$B$6,$B$8="Нет"),"",O14/(1+$B$9)^M14) -> 2838982
A15: Прирост (%) | B15: =B14/B12 -> 3.3048881 | M15: =IF(M14="", "", IF(M14>=$B$6, "", M14+1)) -> 14 | N15: =IF(M15>$B$6,"",$B$3) -> 100000 | O15: =IF(M15>$B$6,"", IF($B$7="Да", FV($B$5/12,M15*12,-$B$4,-$B$3,0), $B$3+($B$4*12*M15)+($B$3*$B$5*M15))) -> 7013551.7 | P15: =IF(OR(M15>$B$6,$B$8="Нет"),"",O15/(1+$B$9)^M15) -> 3102100.7
A16: Реальная итоговая сумма | B16: =IF(B8="Да", B13 / (1 + B9)^B6, B13) -> 4966452.5 | M16: =IF(M15="", "", IF(M15>=$B$6, "", M15+1)) -> 15 | N16: =IF(M16>$B$6,"",$B$3) -> 100000 | O16: =IF(M16>$B$6,"", IF($B$7="Да", FV($B$5/12,M16*12,-$B$4,-$B$3,0), $B$3+($B$4*12*M16)+($B$3*$B$5*M16))) -> 8093283.2 | P16: =IF(OR(M16>$B$6,$B$8="Нет"),"",O16/(1+$B$9)^M16) -> 3377044.3
M17: =IF(M16="", "", IF(M16>=$B$6, "", M16+1)) -> 16 | N17: =IF(M17>$B$6,"",$B$3) -> 100000 | O17: =IF(M17>$B$6,"", IF($B$7="Да", FV($B$5/12,M17*12,-$B$4,-$B$3,0), $B$3+($B$4*12*M17)+($B$3*$B$5*M17))) -> 9309951.6 | P17: =IF(OR(M17>$B$6,$B$8="Нет"),"",O17/(1+$B$9)^M17) -> 3664827.8
M18: =IF(M17="", "", IF(M17>=$B$6, "", M17+1)) -> 17 | N18: =IF(M18>$B$6,"",$B$3) -> 100000 | O18: =IF(M18>$B$6,"", IF($B$7="Да", FV($B$5/12,M18*12,-$B$4,-$B$3,0), $B$3+($B$4*12*M18)+($B$3*$B$5*M18))) -> 10680924 | P18: =IF(OR(M18>$B$6,$B$8="Нет"),"",O18/(1+$B$9)^M18) -> 3966515.1
M19: =IF(M18="", "", IF(M18>=$B$6, "", M18+1)) -> 18 | N19: =IF(M19>$B$6,"",$B$3) -> 100000 | O19: =IF(M19>$B$6,"", IF($B$7="Да", FV($B$5/12,M19*12,-$B$4,-$B$3,0), $B$3+($B$4*12*M19)+($B$3*$B$5*M19))) -> 12225770 | P19: =IF(OR(M19>$B$6,$B$8="Нет"),"",O19/(1+$B$9)^M19) -> 4283222.6
M20: =IF(M19="", "", IF(M19>=$B$6, "", M19+1)) -> 19 | N20: =IF(M20>$B$6,"",$B$3) -> 100000 | O20: =IF(M20>$B$6,"", IF($B$7="Да", FV($B$5/12,M20*12,-$B$4,-$B$3,0), $B$3+($B$4*12*M20)+($B$3*$B$5*M20))) -> 13966541 | P20: =IF(OR(M20>$B$6,$B$8="Нет"),"",O20/(1+$B$9)^M20) -> 4616123.6
M21: =IF(M20="", "", IF(M20>=$B$6, "", M20+1)) -> 20 | N21: =IF(M21>$B$6,"",$B$3) -> 100000 | O21: =IF(M21>$B$6,"", IF($B$7="Да", FV($B$5/12,M21*12,-$B$4,-$B$3,0), $B$3+($B$4*12*M21)+($B$3*$B$5*M21))) -> 15928086 | P21: =IF(OR(M21>$B$6,$B$8="Нет"),"",O21/(1+$B$9)^M21) -> 4966452.5
M22: =IF(M21="", "", IF(M21>=$B$6, "", M21+1)) | N22: =IF(M22>$B$6,"",$B$3) | O22: =IF(M22>$B$6,"", IF($B$7="Да", FV($B$5/12,M22*12,-$B$4,-$B$3,0), $B$3+($B$4*12*M22)+($B$3*$B$5*M22))) | P22: =IF(OR(M22>$B$6,$B$8="Нет"),"",O22/(1+$B$9)^M22)
M23: =IF(M22="", "", IF(M22>=$B$6, "", M22+1)) | N23: =IF(M23>$B$6,"",$B$3) | O23: =IF(M23>$B$6,"", IF($B$7="Да", FV($B$5/12,M23*12,-$B$4,-$B$3,0), $B$3+($B$4*12*M23)+($B$3*$B$5*M23))) | P23: =IF(OR(M23>$B$6,$B$8="Нет"),"",O23/(1+$B$9)^M23)
M24: =IF(M23="", "", IF(M23>=$B$6, "", M23+1)) | N24: =IF(M24>$B$6,"",$B$3) | O24: =IF(M24>$B$6,"", IF($B$7="Да", FV($B$5/12,M24*12,-$B$4,-$B$3,0), $B$3+($B$4*12*M24)+($B$3*$B$5*M24))) | P24: =IF(OR(M24>$B$6,$B$8="Нет"),"",O24/(1+$B$9)^M24)
M25: =IF(M24="", "", IF(M24>=$B$6, "", M24+1)) | N25: =IF(M25>$B$6,"",$B$3) | O25: =IF(M25>$B$6,"", IF($B$7="Да", FV($B$5/12,M25*12,-$B$4,-$B$3,0), $B$3+($B$4*12*M25)+($B$3*$B$5*M25))) | P25: =IF(OR(M25>$B$6,$B$8="Нет"),"",O25/(1+$B$9)^M25)
M26: =IF(M25="", "", IF(M25>=$B$6, "", M25+1)) | N26: =IF(M26>$B$6,"",$B$3) | O26: =IF(M26>$B$6,"", IF($B$7="Да", FV($B$5/12,M26*12,-$B$4,-$B$3,0), $B$3+($B$4*12*M26)+($B$3*$B$5*M26))) | P26: =IF(OR(M26>$B$6,$B$8="Нет"),"",O26/(1+$B$9)^M26)
M27: =IF(M26="", "", IF(M26>=$B$6, "", M26+1)) | N27: =IF(M27>$B$6,"",$B$3) | O27: =IF(M27>$B$6,"", IF($B$7="Да", FV($B$5/12,M27*12,-$B$4,-$B$3,0), $B$3+($B$4*12*M27)+($B$3*$B$5*M27))) | P27: =IF(OR(M27>$B$6,$B$8="Нет"),"",O27/(1+$B$9)^M27)
M28: =IF(M27="", "", IF(M27>=$B$6, "", M27+1)) | N28: =IF(M28>$B$6,"",$B$3) | O28: =IF(M28>$B$6,"", IF($B$7="Да", FV($B$5/12,M28*12,-$B$4,-$B$3,0), $B$3+($B$4*12*M28)+($B$3*$B$5*M28))) | P28: =IF(OR(M28>$B$6,$B$8="Нет"),"",O28/(1+$B$9)^M28)
... M41: =IF(M40="", "", IF(M40>=$B$6, "", M40+1)) | N41: =IF(M41>$B$6,"",$B$3) | O41: =IF(M41>$B$6,"", IF($B$7="Да", FV($B$5/12,M41*12,-$B$4,-$B$3,0), $B$3+($B$4*12*M41)+($B$3*$B$5*M41))) | P41: =IF(OR(M41>$B$6,$B$8="Нет"),"",O41/(1+$B$9)^M41)
M43: =IF(M42="", "", IF(M42>=$B$6, "", M42+1))

Sheet Сводный анализ
A1: Сводный анализ эффективности DCA-стратегий
A2: Источник: расчёты стратегий на основе индексов Московской биржи, данных Банка России и Росстата.
A3: Стратегия | B3: Итоговый портфель | C3: Прибыль | D3: Реальная доходность | E3: Среднегодовой рост
A4: Акции 100% | B4: 20545366 | C4: 14194946 | D4: -0.39309853 | E4: 0.057502729
A5: А90%/О10% | B5: 20140600 | C5: 13790180 | D5: -0.40505516 | E5: 0.056501206
A6: А80%/О20% | B6: 19488024 | C6: 13137604 | D6: -0.42433199 | E6: 0.05484543
A7: А70%/О30% | B7: 18636611 | C7: 12286191 | D7: -0.44948236 | E7: 0.052603901
A8: А60%/О40% | B8: 17633674 | C8: 11283254 | D8: -0.47910869 | E8: 0.049834811
A9: А50%/О50% | B9: 16523305 | C9: 10172885 | D9: -0.51190852 | E9: 0.046588424
A10: А40%/О60% | B10: 15345305 | C10: 8994884.7 | D10: -0.54670616 | E10: 0.04290881
A11: А30%/О70% | B11: 14134529 | C11: 7784109.3 | D11: -0.58247196 | E11: 0.038835098
A12: Вклады 100% | B12: 13863147 | C12: 7512726.8 | D12: -0.59048848 | E12: 0.037876513
A13: А20%/О80% | B13: 12920587 | C13: 6570166.5 | D13: -0.61833131 | E13: 0.034402385
A14: А10%/О90% | B14: 11727811 | C14: 5377391 | D14: -0.6535654 | E14: 0.029642369
A15: Облигации 100% | B15: 10575459 | C15: 4225039.2 | D15: -0.68760539 | E15: 0.024583755

Sheet Источники работы
A2: https://www.moex.com/ru/index/totalreturn/MCFTR/archive | B2: брал данные по акциям с 2004 по 2024 год
A3: https://www.moex.com/ru/index/RGBITR/archive?from=2002-12-31&till=2024-08-31&sort=TRADEDATE&order=desc | B3: брал данные по облигациям с 2004 по 2024 год
A4: https://cbr.ru/hd_base/KeyRate/ | B4: вклады
A5: https://rosstat.gov.ru/statistics/price | B5: инфляция
